{"id":"7776958251256","title":"Gorgeous Plastic Shoes","handle":"modi","status":"active","options":[{"id":"9863855341816","product_id":"7776958251256","name":"Size","position":"1","values":["Metal","Rubber","Concrete"]},{"id":"9863855374584","product_id":"7776958251256","name":"Color","position":"2","values":["lavender","white","orchid"]},{"id":"9863855407352","product_id":"7776958251256","name":"Fabric","position":"3","values":["veniam","nisi","aut"]}],"body_html":"New range of formal shirts are designed keeping you in mind. With fits and styling that will make you stand apart","tags":"ducimus, eaque, eligendi","product_type":"ut","ProductTypes":{"Id":null,"StandardizedProductType":null,"CustomProductType":"ut"},"vendor":"deserunt","published_at":"2022-05-04T13:02:44+00:00","published_scope":"web","updated_at":"2022-08-11T10:56:59+02:00","created_at":"2022-08-11T10:56:51+02:00","image":{"id":"37914730201336","product_id":"7776958251256","position":1,"src":"https://cdn.shopify.com/s/files/1/0549/3132/5176/products/invoice_8538aabe-6c69-4b8d-9e69-6daff316a898.jpg?v=1660208214","width":"128","height":"128","variant_ids":["43140212523256"],"created_at":"2022-08-11T08:56:51+00:00","updated_at":"2022-08-11T10:56:54+02:00","admin_graphql_api_id":"gid://shopify/ProductImage/37914730201336"},"images":[{"id":"37914730201336","product_id":"7776958251256","position":1,"src":"https://cdn.shopify.com/s/files/1/0549/3132/5176/products/invoice_8538aabe-6c69-4b8d-9e69-6daff316a898.jpg?v=1660208214","filename":"invoice_8538aabe-6c69-4b8d-9e69-6daff316a898.jpg","width":"128","height":"128","variant_ids":["43140212523256"],"metafields":[{"id":"23003688829176","namespace":"global","key":"0000","value":"This item contains dairy products.","type":"single_line_text_field","owner_id":"37914730201336","owner_resource":"product_image","created_at":"2022-08-11T10:56:51+02:00","updated_at":"2022-08-11T10:56:51+02:00","admin_graphql_api_id":"gid://shopify/Metafield/23003688829176"},{"id":"23003688894712","namespace":"global","key":"0001","value":"Ingredients: \r\nFlour \r\nWater \r\nMilk \r\nEggs","type":"multi_line_text_field","owner_id":"37914730201336","owner_resource":"product_image","created_at":"2022-08-11T10:56:51+02:00","updated_at":"2022-08-11T10:56:51+02:00","admin_graphql_api_id":"gid://shopify/Metafield/23003688894712"},{"id":"23003688927480","namespace":"global","key":"0002","value":"gid://shopify/OnlineStorePage/1","type":"page_reference","owner_id":"37914730201336","owner_resource":"product_image","created_at":"2022-08-11T10:56:51+02:00","updated_at":"2022-08-11T10:56:51+02:00","admin_graphql_api_id":"gid://shopify/Metafield/23003688927480"},{"id":"23003688960248","namespace":"global","key":"0003","value":"gid://shopify/Product/1","type":"product_reference","owner_id":"37914730201336","owner_resource":"product_image","created_at":"2022-08-11T10:56:51+02:00","updated_at":"2022-08-11T10:56:51+02:00","admin_graphql_api_id":"gid://shopify/Metafield/23003688960248"},{"id":"23003688993016","namespace":"global","key":"0004","value":"gid://shopify/ProductVariant/1","type":"variant_reference","owner_id":"37914730201336","owner_resource":"product_image","created_at":"2022-08-11T10:56:51+02:00","updated_at":"2022-08-11T10:56:51+02:00","admin_graphql_api_id":"gid://shopify/Metafield/23003688993016"},{"id":"23003689025784","namespace":"global","key":"0005","value":"gid://shopify/MediaImage/123","type":"file_reference","owner_id":"37914730201336","owner_resource":"product_image","created_at":"2022-08-11T10:56:51+02:00","updated_at":"2022-08-11T10:56:51+02:00","admin_graphql_api_id":"gid://shopify/Metafield/23003689025784"},{"id":"23003689058552","namespace":"global","key":"0006","value":"10","type":"number_integer","owner_id":"37914730201336","owner_resource":"product_image","created_at":"2022-08-11T10:56:51+02:00","updated_at":"2022-08-11T10:56:51+02:00","admin_graphql_api_id":"gid://shopify/Metafield/23003689058552"},{"id":"23003689091320","namespace":"global","key":"0007","value":"10.4","type":"number_decimal","owner_id":"37914730201336","owner_resource":"product_image","created_at":"2022-08-11T10:56:51+02:00","updated_at":"2022-08-11T10:56:51+02:00","admin_graphql_api_id":"gid://shopify/Metafield/23003689091320"},{"id":"23003689124088","namespace":"global","key":"0008","value":"2021-02-02","type":"date","owner_id":"37914730201336","owner_resource":"product_image","created_at":"2022-08-11T10:56:51+02:00","updated_at":"2022-08-11T10:56:51+02:00","admin_graphql_api_id":"gid://shopify/Metafield/23003689124088"},{"id":"23003689156856","namespace":"global","key":"0009","value":"2021-01-01T12:30:00+00:00","type":"date_time","owner_id":"37914730201336","owner_resource":"product_image","created_at":"2022-08-11T10:56:51+02:00","updated_at":"2022-08-11T10:56:51+02:00","admin_graphql_api_id":"gid://shopify/Metafield/23003689156856"},{"id":"23003689189624","namespace":"global","key":"0010","value":"https://www.shopify.com","type":"url","owner_id":"37914730201336","owner_resource":"product_image","created_at":"2022-08-11T10:56:51+02:00","updated_at":"2022-08-11T10:56:51+02:00","admin_graphql_api_id":"gid://shopify/Metafield/23003689189624"},{"id":"23003689222392","namespace":"global","key":"0011","value":"[{\"k\":\"v1\"},{\"k\":\"v2\"}]","type":"json","owner_id":"37914730201336","owner_resource":"product_image","created_at":"2022-08-11T10:56:51+02:00","updated_at":"2022-08-11T10:56:51+02:00","admin_graphql_api_id":"gid://shopify/Metafield/23003689222392"},{"id":"23003689255160","namespace":"global","key":"0012","value":"true","type":"boolean","owner_id":"37914730201336","owner_resource":"product_image","created_at":"2022-08-11T10:56:51+02:00","updated_at":"2022-08-11T10:56:51+02:00","admin_graphql_api_id":"gid://shopify/Metafield/23003689255160"},{"id":"23003689287928","namespace":"global","key":"0013","value":"#fff123","type":"color","owner_id":"37914730201336","owner_resource":"product_image","created_at":"2022-08-11T10:56:51+02:00","updated_at":"2022-08-11T10:56:51+02:00","admin_graphql_api_id":"gid://shopify/Metafield/23003689287928"},{"id":"23003689320696","namespace":"global","key":"0014","value":"{\"value\":2.5,\"unit\":\"kg\"}","type":"weight","owner_id":"37914730201336","owner_resource":"product_image","created_at":"2022-08-11T10:56:51+02:00","updated_at":"2022-08-11T10:56:51+02:00","admin_graphql_api_id":"gid://shopify/Metafield/23003689320696"},{"id":"23003689353464","namespace":"global","key":"0015","value":"{\"value\":20.0,\"unit\":\"ml\"}","type":"volume","owner_id":"37914730201336","owner_resource":"product_image","created_at":"2022-08-11T10:56:51+02:00","updated_at":"2022-08-11T10:56:51+02:00","admin_graphql_api_id":"gid://shopify/Metafield/23003689353464"},{"id":"23003689386232","namespace":"global","key":"0016","value":"{\"value\":20.5,\"unit\":\"cm\"}","type":"dimension","owner_id":"37914730201336","owner_resource":"product_image","created_at":"2022-08-11T10:56:51+02:00","updated_at":"2022-08-11T10:56:51+02:00","admin_graphql_api_id":"gid://shopify/Metafield/23003689386232"},{"id":"23003689419000","namespace":"global","key":"0017","value":"{\"scale_min\":\"1.0\",\"scale_max\":\"5.0\",\"value\":\"3.5\"}","type":"rating","owner_id":"37914730201336","owner_resource":"product_image","created_at":"2022-08-11T10:56:51+02:00","updated_at":"2022-08-11T10:56:51+02:00","admin_graphql_api_id":"gid://shopify/Metafield/23003689419000"}],"created_at":"2022-08-11T08:56:51+00:00","updated_at":"2022-08-11T10:56:54+02:00","admin_graphql_api_id":"gid://shopify/ProductImage/37914730201336"},{"id":"37914730234104","product_id":"7776958251256","position":2,"src":"https://cdn.shopify.com/s/files/1/0549/3132/5176/products/buckinghamshire_interactions_yellow_d27a410a-89dc-466d-a51d-3d29d0061e77.jpg?v=1660208214","filename":"buckinghamshire_interactions_yellow_d27a410a-89dc-466d-a51d-3d29d0061e77.jpg","width":"128","height":"128","variant_ids":["43140212556024"],"metafields":[{"id":"23003689451768","namespace":"global","key":"0000","value":"This item contains dairy products.","type":"single_line_text_field","owner_id":"37914730234104","owner_resource":"product_image","created_at":"2022-08-11T10:56:51+02:00","updated_at":"2022-08-11T10:56:51+02:00","admin_graphql_api_id":"gid://shopify/Metafield/23003689451768"},{"id":"23003689484536","namespace":"global","key":"0001","value":"Ingredients: \r\nFlour \r\nWater \r\nMilk \r\nEggs","type":"multi_line_text_field","owner_id":"37914730234104","owner_resource":"product_image","created_at":"2022-08-11T10:56:51+02:00","updated_at":"2022-08-11T10:56:51+02:00","admin_graphql_api_id":"gid://shopify/Metafield/23003689484536"},{"id":"23003689517304","namespace":"global","key":"0002","value":"gid://shopify/OnlineStorePage/1","type":"page_reference","owner_id":"37914730234104","owner_resource":"product_image","created_at":"2022-08-11T10:56:51+02:00","updated_at":"2022-08-11T10:56:51+02:00","admin_graphql_api_id":"gid://shopify/Metafield/23003689517304"},{"id":"23003689550072","namespace":"global","key":"0003","value":"gid://shopify/Product/1","type":"product_reference","owner_id":"37914730234104","owner_resource":"product_image","created_at":"2022-08-11T10:56:51+02:00","updated_at":"2022-08-11T10:56:51+02:00","admin_graphql_api_id":"gid://shopify/Metafield/23003689550072"},{"id":"23003689582840","namespace":"global","key":"0004","value":"gid://shopify/ProductVariant/1","type":"variant_reference","owner_id":"37914730234104","owner_resource":"product_image","created_at":"2022-08-11T10:56:51+02:00","updated_at":"2022-08-11T10:56:51+02:00","admin_graphql_api_id":"gid://shopify/Metafield/23003689582840"},{"id":"23003689615608","namespace":"global","key":"0005","value":"gid://shopify/MediaImage/123","type":"file_reference","owner_id":"37914730234104","owner_resource":"product_image","created_at":"2022-08-11T10:56:51+02:00","updated_at":"2022-08-11T10:56:51+02:00","admin_graphql_api_id":"gid://shopify/Metafield/23003689615608"},{"id":"23003689648376","namespace":"global","key":"0006","value":"10","type":"number_integer","owner_id":"37914730234104","owner_resource":"product_image","created_at":"2022-08-11T10:56:51+02:00","updated_at":"2022-08-11T10:56:51+02:00","admin_graphql_api_id":"gid://shopify/Metafield/23003689648376"},{"id":"23003689681144","namespace":"global","key":"0007","value":"10.4","type":"number_decimal","owner_id":"37914730234104","owner_resource":"product_image","created_at":"2022-08-11T10:56:51+02:00","updated_at":"2022-08-11T10:56:51+02:00","admin_graphql_api_id":"gid://shopify/Metafield/23003689681144"},{"id":"23003689713912","namespace":"global","key":"0008","value":"2021-02-02","type":"date","owner_id":"37914730234104","owner_resource":"product_image","created_at":"2022-08-11T10:56:51+02:00","updated_at":"2022-08-11T10:56:51+02:00","admin_graphql_api_id":"gid://shopify/Metafield/23003689713912"},{"id":"23003689746680","namespace":"global","key":"0009","value":"2021-01-01T12:30:00+00:00","type":"date_time","owner_id":"37914730234104","owner_resource":"product_image","created_at":"2022-08-11T10:56:51+02:00","updated_at":"2022-08-11T10:56:51+02:00","admin_graphql_api_id":"gid://shopify/Metafield/23003689746680"},{"id":"23003689779448","namespace":"global","key":"0010","value":"https://www.shopify.com","type":"url","owner_id":"37914730234104","owner_resource":"product_image","created_at":"2022-08-11T10:56:51+02:00","updated_at":"2022-08-11T10:56:51+02:00","admin_graphql_api_id":"gid://shopify/Metafield/23003689779448"},{"id":"23003689812216","namespace":"global","key":"0011","value":"[{\"k\":\"v1\"},{\"k\":\"v2\"}]","type":"json","owner_id":"37914730234104","owner_resource":"product_image","created_at":"2022-08-11T10:56:51+02:00","updated_at":"2022-08-11T10:56:51+02:00","admin_graphql_api_id":"gid://shopify/Metafield/23003689812216"},{"id":"23003689844984","namespace":"global","key":"0012","value":"true","type":"boolean","owner_id":"37914730234104","owner_resource":"product_image","created_at":"2022-08-11T10:56:51+02:00","updated_at":"2022-08-11T10:56:51+02:00","admin_graphql_api_id":"gid://shopify/Metafield/23003689844984"},{"id":"23003689877752","namespace":"global","key":"0013","value":"#fff123","type":"color","owner_id":"37914730234104","owner_resource":"product_image","created_at":"2022-08-11T10:56:51+02:00","updated_at":"2022-08-11T10:56:51+02:00","admin_graphql_api_id":"gid://shopify/Metafield/23003689877752"},{"id":"23003689910520","namespace":"global","key":"0014","value":"{\"value\":2.5,\"unit\":\"kg\"}","type":"weight","owner_id":"37914730234104","owner_resource":"product_image","created_at":"2022-08-11T10:56:51+02:00","updated_at":"2022-08-11T10:56:51+02:00","admin_graphql_api_id":"gid://shopify/Metafield/23003689910520"},{"id":"23003689943288","namespace":"global","key":"0015","value":"{\"value\":20.0,\"unit\":\"ml\"}","type":"volume","owner_id":"37914730234104","owner_resource":"product_image","created_at":"2022-08-11T10:56:51+02:00","updated_at":"2022-08-11T10:56:51+02:00","admin_graphql_api_id":"gid://shopify/Metafield/23003689943288"},{"id":"23003689976056","namespace":"global","key":"0016","value":"{\"value\":20.5,\"unit\":\"cm\"}","type":"dimension","owner_id":"37914730234104","owner_resource":"product_image","created_at":"2022-08-11T10:56:51+02:00","updated_at":"2022-08-11T10:56:51+02:00","admin_graphql_api_id":"gid://shopify/Metafield/23003689976056"},{"id":"23003690008824","namespace":"global","key":"0017","value":"{\"scale_min\":\"1.0\",\"scale_max\":\"5.0\",\"value\":\"3.5\"}","type":"rating","owner_id":"37914730234104","owner_resource":"product_image","created_at":"2022-08-11T10:56:51+02:00","updated_at":"2022-08-11T10:56:51+02:00","admin_graphql_api_id":"gid://shopify/Metafield/23003690008824"}],"created_at":"2022-08-11T08:56:51+00:00","updated_at":"2022-08-11T10:56:54+02:00","admin_graphql_api_id":"gid://shopify/ProductImage/37914730234104"},{"id":"37914730266872","product_id":"7776958251256","position":3,"src":"https://cdn.shopify.com/s/files/1/0549/3132/5176/products/intelligent_granite_fish_back_end_af34cafe-d13b-4fc2-aae3-b072b0e550d0.jpg?v=1660208214","filename":"intelligent_granite_fish_back_end_af34cafe-d13b-4fc2-aae3-b072b0e550d0.jpg","width":"128","height":"128","variant_ids":["43140212588792"],"metafields":[{"id":"23003690107128","namespace":"global","key":"0000","value":"This item contains dairy products.","type":"single_line_text_field","owner_id":"37914730266872","owner_resource":"product_image","created_at":"2022-08-11T10:56:52+02:00","updated_at":"2022-08-11T10:56:52+02:00","admin_graphql_api_id":"gid://shopify/Metafield/23003690107128"},{"id":"23003690139896","namespace":"global","key":"0001","value":"Ingredients: \r\nFlour \r\nWater \r\nMilk \r\nEggs","type":"multi_line_text_field","owner_id":"37914730266872","owner_resource":"product_image","created_at":"2022-08-11T10:56:52+02:00","updated_at":"2022-08-11T10:56:52+02:00","admin_graphql_api_id":"gid://shopify/Metafield/23003690139896"},{"id":"23003690172664","namespace":"global","key":"0002","value":"gid://shopify/OnlineStorePage/1","type":"page_reference","owner_id":"37914730266872","owner_resource":"product_image","created_at":"2022-08-11T10:56:52+02:00","updated_at":"2022-08-11T10:56:52+02:00","admin_graphql_api_id":"gid://shopify/Metafield/23003690172664"},{"id":"23003690205432","namespace":"global","key":"0003","value":"gid://shopify/Product/1","type":"product_reference","owner_id":"37914730266872","owner_resource":"product_image","created_at":"2022-08-11T10:56:52+02:00","updated_at":"2022-08-11T10:56:52+02:00","admin_graphql_api_id":"gid://shopify/Metafield/23003690205432"},{"id":"23003690238200","namespace":"global","key":"0004","value":"gid://shopify/ProductVariant/1","type":"variant_reference","owner_id":"37914730266872","owner_resource":"product_image","created_at":"2022-08-11T10:56:52+02:00","updated_at":"2022-08-11T10:56:52+02:00","admin_graphql_api_id":"gid://shopify/Metafield/23003690238200"},{"id":"23003690270968","namespace":"global","key":"0005","value":"gid://shopify/MediaImage/123","type":"file_reference","owner_id":"37914730266872","owner_resource":"product_image","created_at":"2022-08-11T10:56:52+02:00","updated_at":"2022-08-11T10:56:52+02:00","admin_graphql_api_id":"gid://shopify/Metafield/23003690270968"},{"id":"23003690303736","namespace":"global","key":"0006","value":"10","type":"number_integer","owner_id":"37914730266872","owner_resource":"product_image","created_at":"2022-08-11T10:56:52+02:00","updated_at":"2022-08-11T10:56:52+02:00","admin_graphql_api_id":"gid://shopify/Metafield/23003690303736"},{"id":"23003690336504","namespace":"global","key":"0007","value":"10.4","type":"number_decimal","owner_id":"37914730266872","owner_resource":"product_image","created_at":"2022-08-11T10:56:52+02:00","updated_at":"2022-08-11T10:56:52+02:00","admin_graphql_api_id":"gid://shopify/Metafield/23003690336504"},{"id":"23003690369272","namespace":"global","key":"0008","value":"2021-02-02","type":"date","owner_id":"37914730266872","owner_resource":"product_image","created_at":"2022-08-11T10:56:52+02:00","updated_at":"2022-08-11T10:56:52+02:00","admin_graphql_api_id":"gid://shopify/Metafield/23003690369272"},{"id":"23003690402040","namespace":"global","key":"0009","value":"2021-01-01T12:30:00+00:00","type":"date_time","owner_id":"37914730266872","owner_resource":"product_image","created_at":"2022-08-11T10:56:52+02:00","updated_at":"2022-08-11T10:56:52+02:00","admin_graphql_api_id":"gid://shopify/Metafield/23003690402040"},{"id":"23003690434808","namespace":"global","key":"0010","value":"https://www.shopify.com","type":"url","owner_id":"37914730266872","owner_resource":"product_image","created_at":"2022-08-11T10:56:52+02:00","updated_at":"2022-08-11T10:56:52+02:00","admin_graphql_api_id":"gid://shopify/Metafield/23003690434808"},{"id":"23003690467576","namespace":"global","key":"0011","value":"[{\"k\":\"v1\"},{\"k\":\"v2\"}]","type":"json","owner_id":"37914730266872","owner_resource":"product_image","created_at":"2022-08-11T10:56:52+02:00","updated_at":"2022-08-11T10:56:52+02:00","admin_graphql_api_id":"gid://shopify/Metafield/23003690467576"},{"id":"23003690500344","namespace":"global","key":"0012","value":"true","type":"boolean","owner_id":"37914730266872","owner_resource":"product_image","created_at":"2022-08-11T10:56:52+02:00","updated_at":"2022-08-11T10:56:52+02:00","admin_graphql_api_id":"gid://shopify/Metafield/23003690500344"},{"id":"23003690533112","namespace":"global","key":"0013","value":"#fff123","type":"color","owner_id":"37914730266872","owner_resource":"product_image","created_at":"2022-08-11T10:56:52+02:00","updated_at":"2022-08-11T10:56:52+02:00","admin_graphql_api_id":"gid://shopify/Metafield/23003690533112"},{"id":"23003690565880","namespace":"global","key":"0014","value":"{\"value\":2.5,\"unit\":\"kg\"}","type":"weight","owner_id":"37914730266872","owner_resource":"product_image","created_at":"2022-08-11T10:56:52+02:00","updated_at":"2022-08-11T10:56:52+02:00","admin_graphql_api_id":"gid://shopify/Metafield/23003690565880"},{"id":"23003690598648","namespace":"global","key":"0015","value":"{\"value\":20.0,\"unit\":\"ml\"}","type":"volume","owner_id":"37914730266872","owner_resource":"product_image","created_at":"2022-08-11T10:56:52+02:00","updated_at":"2022-08-11T10:56:52+02:00","admin_graphql_api_id":"gid://shopify/Metafield/23003690598648"},{"id":"23003690631416","namespace":"global","key":"0016","value":"{\"value\":20.5,\"unit\":\"cm\"}","type":"dimension","owner_id":"37914730266872","owner_resource":"product_image","created_at":"2022-08-11T10:56:52+02:00","updated_at":"2022-08-11T10:56:52+02:00","admin_graphql_api_id":"gid://shopify/Metafield/23003690631416"},{"id":"23003690664184","namespace":"global","key":"0017","value":"{\"scale_min\":\"1.0\",\"scale_max\":\"5.0\",\"value\":\"3.5\"}","type":"rating","owner_id":"37914730266872","owner_resource":"product_image","created_at":"2022-08-11T10:56:52+02:00","updated_at":"2022-08-11T10:56:52+02:00","admin_graphql_api_id":"gid://shopify/Metafield/23003690664184"}],"created_at":"2022-08-11T08:56:52+00:00","updated_at":"2022-08-11T10:56:54+02:00","admin_graphql_api_id":"gid://shopify/ProductImage/37914730266872"},{"id":"37914730299640","product_id":"7776958251256","position":4,"src":"https://cdn.shopify.com/s/files/1/0549/3132/5176/products/cross_platform_washington_043dd297-3ba8-4a8f-99e5-e3f7d9308803.jpg?v=1660208215","filename":"cross_platform_washington_043dd297-3ba8-4a8f-99e5-e3f7d9308803.jpg","width":"128","height":"128","variant_ids":[],"metafields":[{"id":"23003690696952","namespace":"global","key":"0000","value":"This item contains dairy products.","type":"single_line_text_field","owner_id":"37914730299640","owner_resource":"product_image","created_at":"2022-08-11T10:56:52+02:00","updated_at":"2022-08-11T10:56:52+02:00","admin_graphql_api_id":"gid://shopify/Metafield/23003690696952"},{"id":"23003690729720","namespace":"global","key":"0001","value":"Ingredients: \r\nFlour \r\nWater \r\nMilk \r\nEggs","type":"multi_line_text_field","owner_id":"37914730299640","owner_resource":"product_image","created_at":"2022-08-11T10:56:52+02:00","updated_at":"2022-08-11T10:56:52+02:00","admin_graphql_api_id":"gid://shopify/Metafield/23003690729720"},{"id":"23003690762488","namespace":"global","key":"0002","value":"gid://shopify/OnlineStorePage/1","type":"page_reference","owner_id":"37914730299640","owner_resource":"product_image","created_at":"2022-08-11T10:56:52+02:00","updated_at":"2022-08-11T10:56:52+02:00","admin_graphql_api_id":"gid://shopify/Metafield/23003690762488"},{"id":"23003690795256","namespace":"global","key":"0003","value":"gid://shopify/Product/1","type":"product_reference","owner_id":"37914730299640","owner_resource":"product_image","created_at":"2022-08-11T10:56:52+02:00","updated_at":"2022-08-11T10:56:52+02:00","admin_graphql_api_id":"gid://shopify/Metafield/23003690795256"},{"id":"23003690828024","namespace":"global","key":"0004","value":"gid://shopify/ProductVariant/1","type":"variant_reference","owner_id":"37914730299640","owner_resource":"product_image","created_at":"2022-08-11T10:56:52+02:00","updated_at":"2022-08-11T10:56:52+02:00","admin_graphql_api_id":"gid://shopify/Metafield/23003690828024"},{"id":"23003690860792","namespace":"global","key":"0005","value":"gid://shopify/MediaImage/123","type":"file_reference","owner_id":"37914730299640","owner_resource":"product_image","created_at":"2022-08-11T10:56:52+02:00","updated_at":"2022-08-11T10:56:52+02:00","admin_graphql_api_id":"gid://shopify/Metafield/23003690860792"},{"id":"23003690893560","namespace":"global","key":"0006","value":"10","type":"number_integer","owner_id":"37914730299640","owner_resource":"product_image","created_at":"2022-08-11T10:56:52+02:00","updated_at":"2022-08-11T10:56:52+02:00","admin_graphql_api_id":"gid://shopify/Metafield/23003690893560"},{"id":"23003690926328","namespace":"global","key":"0007","value":"10.4","type":"number_decimal","owner_id":"37914730299640","owner_resource":"product_image","created_at":"2022-08-11T10:56:52+02:00","updated_at":"2022-08-11T10:56:52+02:00","admin_graphql_api_id":"gid://shopify/Metafield/23003690926328"},{"id":"23003690959096","namespace":"global","key":"0008","value":"2021-02-02","type":"date","owner_id":"37914730299640","owner_resource":"product_image","created_at":"2022-08-11T10:56:52+02:00","updated_at":"2022-08-11T10:56:52+02:00","admin_graphql_api_id":"gid://shopify/Metafield/23003690959096"},{"id":"23003690991864","namespace":"global","key":"0009","value":"2021-01-01T12:30:00+00:00","type":"date_time","owner_id":"37914730299640","owner_resource":"product_image","created_at":"2022-08-11T10:56:52+02:00","updated_at":"2022-08-11T10:56:52+02:00","admin_graphql_api_id":"gid://shopify/Metafield/23003690991864"},{"id":"23003691024632","namespace":"global","key":"0010","value":"https://www.shopify.com","type":"url","owner_id":"37914730299640","owner_resource":"product_image","created_at":"2022-08-11T10:56:52+02:00","updated_at":"2022-08-11T10:56:52+02:00","admin_graphql_api_id":"gid://shopify/Metafield/23003691024632"},{"id":"23003691057400","namespace":"global","key":"0011","value":"[{\"k\":\"v1\"},{\"k\":\"v2\"}]","type":"json","owner_id":"37914730299640","owner_resource":"product_image","created_at":"2022-08-11T10:56:52+02:00","updated_at":"2022-08-11T10:56:52+02:00","admin_graphql_api_id":"gid://shopify/Metafield/23003691057400"},{"id":"23003691090168","namespace":"global","key":"0012","value":"true","type":"boolean","owner_id":"37914730299640","owner_resource":"product_image","created_at":"2022-08-11T10:56:52+02:00","updated_at":"2022-08-11T10:56:52+02:00","admin_graphql_api_id":"gid://shopify/Metafield/23003691090168"},{"id":"23003691122936","namespace":"global","key":"0013","value":"#fff123","type":"color","owner_id":"37914730299640","owner_resource":"product_image","created_at":"2022-08-11T10:56:52+02:00","updated_at":"2022-08-11T10:56:52+02:00","admin_graphql_api_id":"gid://shopify/Metafield/23003691122936"},{"id":"23003691155704","namespace":"global","key":"0014","value":"{\"value\":2.5,\"unit\":\"kg\"}","type":"weight","owner_id":"37914730299640","owner_resource":"product_image","created_at":"2022-08-11T10:56:52+02:00","updated_at":"2022-08-11T10:56:52+02:00","admin_graphql_api_id":"gid://shopify/Metafield/23003691155704"},{"id":"23003691188472","namespace":"global","key":"0015","value":"{\"value\":20.0,\"unit\":\"ml\"}","type":"volume","owner_id":"37914730299640","owner_resource":"product_image","created_at":"2022-08-11T10:56:52+02:00","updated_at":"2022-08-11T10:56:52+02:00","admin_graphql_api_id":"gid://shopify/Metafield/23003691188472"},{"id":"23003691221240","namespace":"global","key":"0016","value":"{\"value\":20.5,\"unit\":\"cm\"}","type":"dimension","owner_id":"37914730299640","owner_resource":"product_image","created_at":"2022-08-11T10:56:52+02:00","updated_at":"2022-08-11T10:56:52+02:00","admin_graphql_api_id":"gid://shopify/Metafield/23003691221240"},{"id":"23003691254008","namespace":"global","key":"0017","value":"{\"scale_min\":\"1.0\",\"scale_max\":\"5.0\",\"value\":\"3.5\"}","type":"rating","owner_id":"37914730299640","owner_resource":"product_image","created_at":"2022-08-11T10:56:52+02:00","updated_at":"2022-08-11T10:56:52+02:00","admin_graphql_api_id":"gid://shopify/Metafield/23003691254008"}],"created_at":"2022-08-11T08:56:52+00:00","updated_at":"2022-08-11T10:56:55+02:00","admin_graphql_api_id":"gid://shopify/ProductImage/37914730299640"},{"id":"37914730332408","product_id":"7776958251256","position":5,"src":"https://cdn.shopify.com/s/files/1/0549/3132/5176/products/practical_cotton_cheese_schemas_a90457e7-e280-4847-8636-54e5730607e4.jpg?v=1660208215","filename":"practical_cotton_cheese_schemas_a90457e7-e280-4847-8636-54e5730607e4.jpg","width":"128","height":"128","variant_ids":[],"metafields":[{"id":"23003691286776","namespace":"global","key":"0000","value":"This item contains dairy products.","type":"single_line_text_field","owner_id":"37914730332408","owner_resource":"product_image","created_at":"2022-08-11T10:56:52+02:00","updated_at":"2022-08-11T10:56:52+02:00","admin_graphql_api_id":"gid://shopify/Metafield/23003691286776"},{"id":"23003691319544","namespace":"global","key":"0001","value":"Ingredients: \r\nFlour \r\nWater \r\nMilk \r\nEggs","type":"multi_line_text_field","owner_id":"37914730332408","owner_resource":"product_image","created_at":"2022-08-11T10:56:52+02:00","updated_at":"2022-08-11T10:56:52+02:00","admin_graphql_api_id":"gid://shopify/Metafield/23003691319544"},{"id":"23003691352312","namespace":"global","key":"0002","value":"gid://shopify/OnlineStorePage/1","type":"page_reference","owner_id":"37914730332408","owner_resource":"product_image","created_at":"2022-08-11T10:56:52+02:00","updated_at":"2022-08-11T10:56:52+02:00","admin_graphql_api_id":"gid://shopify/Metafield/23003691352312"},{"id":"23003691385080","namespace":"global","key":"0003","value":"gid://shopify/Product/1","type":"product_reference","owner_id":"37914730332408","owner_resource":"product_image","created_at":"2022-08-11T10:56:52+02:00","updated_at":"2022-08-11T10:56:52+02:00","admin_graphql_api_id":"gid://shopify/Metafield/23003691385080"},{"id":"23003691417848","namespace":"global","key":"0004","value":"gid://shopify/ProductVariant/1","type":"variant_reference","owner_id":"37914730332408","owner_resource":"product_image","created_at":"2022-08-11T10:56:52+02:00","updated_at":"2022-08-11T10:56:52+02:00","admin_graphql_api_id":"gid://shopify/Metafield/23003691417848"},{"id":"23003691450616","namespace":"global","key":"0005","value":"gid://shopify/MediaImage/123","type":"file_reference","owner_id":"37914730332408","owner_resource":"product_image","created_at":"2022-08-11T10:56:52+02:00","updated_at":"2022-08-11T10:56:52+02:00","admin_graphql_api_id":"gid://shopify/Metafield/23003691450616"},{"id":"23003691483384","namespace":"global","key":"0006","value":"10","type":"number_integer","owner_id":"37914730332408","owner_resource":"product_image","created_at":"2022-08-11T10:56:52+02:00","updated_at":"2022-08-11T10:56:52+02:00","admin_graphql_api_id":"gid://shopify/Metafield/23003691483384"},{"id":"23003691516152","namespace":"global","key":"0007","value":"10.4","type":"number_decimal","owner_id":"37914730332408","owner_resource":"product_image","created_at":"2022-08-11T10:56:52+02:00","updated_at":"2022-08-11T10:56:52+02:00","admin_graphql_api_id":"gid://shopify/Metafield/23003691516152"},{"id":"23003691548920","namespace":"global","key":"0008","value":"2021-02-02","type":"date","owner_id":"37914730332408","owner_resource":"product_image","created_at":"2022-08-11T10:56:52+02:00","updated_at":"2022-08-11T10:56:52+02:00","admin_graphql_api_id":"gid://shopify/Metafield/23003691548920"},{"id":"23003691581688","namespace":"global","key":"0009","value":"2021-01-01T12:30:00+00:00","type":"date_time","owner_id":"37914730332408","owner_resource":"product_image","created_at":"2022-08-11T10:56:52+02:00","updated_at":"2022-08-11T10:56:52+02:00","admin_graphql_api_id":"gid://shopify/Metafield/23003691581688"},{"id":"23003691614456","namespace":"global","key":"0010","value":"https://www.shopify.com","type":"url","owner_id":"37914730332408","owner_resource":"product_image","created_at":"2022-08-11T10:56:52+02:00","updated_at":"2022-08-11T10:56:52+02:00","admin_graphql_api_id":"gid://shopify/Metafield/23003691614456"},{"id":"23003691647224","namespace":"global","key":"0011","value":"[{\"k\":\"v1\"},{\"k\":\"v2\"}]","type":"json","owner_id":"37914730332408","owner_resource":"product_image","created_at":"2022-08-11T10:56:52+02:00","updated_at":"2022-08-11T10:56:52+02:00","admin_graphql_api_id":"gid://shopify/Metafield/23003691647224"},{"id":"23003691679992","namespace":"global","key":"0012","value":"true","type":"boolean","owner_id":"37914730332408","owner_resource":"product_image","created_at":"2022-08-11T10:56:52+02:00","updated_at":"2022-08-11T10:56:52+02:00","admin_graphql_api_id":"gid://shopify/Metafield/23003691679992"},{"id":"23003691712760","namespace":"global","key":"0013","value":"#fff123","type":"color","owner_id":"37914730332408","owner_resource":"product_image","created_at":"2022-08-11T10:56:52+02:00","updated_at":"2022-08-11T10:56:52+02:00","admin_graphql_api_id":"gid://shopify/Metafield/23003691712760"},{"id":"23003691745528","namespace":"global","key":"0014","value":"{\"value\":2.5,\"unit\":\"kg\"}","type":"weight","owner_id":"37914730332408","owner_resource":"product_image","created_at":"2022-08-11T10:56:52+02:00","updated_at":"2022-08-11T10:56:52+02:00","admin_graphql_api_id":"gid://shopify/Metafield/23003691745528"},{"id":"23003691778296","namespace":"global","key":"0015","value":"{\"value\":20.0,\"unit\":\"ml\"}","type":"volume","owner_id":"37914730332408","owner_resource":"product_image","created_at":"2022-08-11T10:56:52+02:00","updated_at":"2022-08-11T10:56:52+02:00","admin_graphql_api_id":"gid://shopify/Metafield/23003691778296"},{"id":"23003691811064","namespace":"global","key":"0016","value":"{\"value\":20.5,\"unit\":\"cm\"}","type":"dimension","owner_id":"37914730332408","owner_resource":"product_image","created_at":"2022-08-11T10:56:52+02:00","updated_at":"2022-08-11T10:56:52+02:00","admin_graphql_api_id":"gid://shopify/Metafield/23003691811064"},{"id":"23003691843832","namespace":"global","key":"0017","value":"{\"scale_min\":\"1.0\",\"scale_max\":\"5.0\",\"value\":\"3.5\"}","type":"rating","owner_id":"37914730332408","owner_resource":"product_image","created_at":"2022-08-11T10:56:52+02:00","updated_at":"2022-08-11T10:56:52+02:00","admin_graphql_api_id":"gid://shopify/Metafield/23003691843832"}],"created_at":"2022-08-11T08:56:52+00:00","updated_at":"2022-08-11T10:56:55+02:00","admin_graphql_api_id":"gid://shopify/ProductImage/37914730332408"}],"variants":[{"id":"43140212523256","barcode":"78490727","compare_at_price":"720.37","title":"Metal / lavender / veniam","fulfillment_service":"manual","grams":"4139","image_id":"37914730201336","inventory_management":"shopify","inventory_policy":"deny","inventory_quantity":"0","metafields":[{"id":"23003691876600","namespace":"global","key":"0000","value":"This item contains dairy products.","type":"single_line_text_field","owner_id":"43140212523256","owner_resource":"variant","created_at":"2022-08-11T10:56:53+02:00","updated_at":"2022-08-11T10:56:53+02:00","admin_graphql_api_id":"gid://shopify/Metafield/23003691876600"},{"id":"23003691909368","namespace":"global","key":"0001","value":"Ingredients: \r\nFlour \r\nWater \r\nMilk \r\nEggs","type":"multi_line_text_field","owner_id":"43140212523256","owner_resource":"variant","created_at":"2022-08-11T10:56:53+02:00","updated_at":"2022-08-11T10:56:53+02:00","admin_graphql_api_id":"gid://shopify/Metafield/23003691909368"},{"id":"23003691942136","namespace":"global","key":"0002","value":"gid://shopify/OnlineStorePage/1","type":"page_reference","owner_id":"43140212523256","owner_resource":"variant","created_at":"2022-08-11T10:56:53+02:00","updated_at":"2022-08-11T10:56:53+02:00","admin_graphql_api_id":"gid://shopify/Metafield/23003691942136"},{"id":"23003691974904","namespace":"global","key":"0003","value":"gid://shopify/Product/1","type":"product_reference","owner_id":"43140212523256","owner_resource":"variant","created_at":"2022-08-11T10:56:53+02:00","updated_at":"2022-08-11T10:56:53+02:00","admin_graphql_api_id":"gid://shopify/Metafield/23003691974904"},{"id":"23003692007672","namespace":"global","key":"0004","value":"gid://shopify/ProductVariant/1","type":"variant_reference","owner_id":"43140212523256","owner_resource":"variant","created_at":"2022-08-11T10:56:53+02:00","updated_at":"2022-08-11T10:56:53+02:00","admin_graphql_api_id":"gid://shopify/Metafield/23003692007672"},{"id":"23003692040440","namespace":"global","key":"0005","value":"gid://shopify/MediaImage/123","type":"file_reference","owner_id":"43140212523256","owner_resource":"variant","created_at":"2022-08-11T10:56:53+02:00","updated_at":"2022-08-11T10:56:53+02:00","admin_graphql_api_id":"gid://shopify/Metafield/23003692040440"},{"id":"23003692073208","namespace":"global","key":"0006","value":"10","type":"number_integer","owner_id":"43140212523256","owner_resource":"variant","created_at":"2022-08-11T10:56:53+02:00","updated_at":"2022-08-11T10:56:53+02:00","admin_graphql_api_id":"gid://shopify/Metafield/23003692073208"},{"id":"23003692105976","namespace":"global","key":"0007","value":"10.4","type":"number_decimal","owner_id":"43140212523256","owner_resource":"variant","created_at":"2022-08-11T10:56:53+02:00","updated_at":"2022-08-11T10:56:53+02:00","admin_graphql_api_id":"gid://shopify/Metafield/23003692105976"},{"id":"23003692138744","namespace":"global","key":"0008","value":"2021-02-02","type":"date","owner_id":"43140212523256","owner_resource":"variant","created_at":"2022-08-11T10:56:53+02:00","updated_at":"2022-08-11T10:56:53+02:00","admin_graphql_api_id":"gid://shopify/Metafield/23003692138744"},{"id":"23003692171512","namespace":"global","key":"0009","value":"2021-01-01T12:30:00+00:00","type":"date_time","owner_id":"43140212523256","owner_resource":"variant","created_at":"2022-08-11T10:56:53+02:00","updated_at":"2022-08-11T10:56:53+02:00","admin_graphql_api_id":"gid://shopify/Metafield/23003692171512"},{"id":"23003692204280","namespace":"global","key":"0010","value":"https://www.shopify.com","type":"url","owner_id":"43140212523256","owner_resource":"variant","created_at":"2022-08-11T10:56:53+02:00","updated_at":"2022-08-11T10:56:53+02:00","admin_graphql_api_id":"gid://shopify/Metafield/23003692204280"},{"id":"23003692237048","namespace":"global","key":"0011","value":"[{\"k\":\"v1\"},{\"k\":\"v2\"}]","type":"json","owner_id":"43140212523256","owner_resource":"variant","created_at":"2022-08-11T10:56:53+02:00","updated_at":"2022-08-11T10:56:53+02:00","admin_graphql_api_id":"gid://shopify/Metafield/23003692237048"},{"id":"23003692269816","namespace":"global","key":"0012","value":"true","type":"boolean","owner_id":"43140212523256","owner_resource":"variant","created_at":"2022-08-11T10:56:53+02:00","updated_at":"2022-08-11T10:56:53+02:00","admin_graphql_api_id":"gid://shopify/Metafield/23003692269816"},{"id":"23003692302584","namespace":"global","key":"0013","value":"#fff123","type":"color","owner_id":"43140212523256","owner_resource":"variant","created_at":"2022-08-11T10:56:53+02:00","updated_at":"2022-08-11T10:56:53+02:00","admin_graphql_api_id":"gid://shopify/Metafield/23003692302584"},{"id":"23003692335352","namespace":"global","key":"0014","value":"{\"value\":2.5,\"unit\":\"kg\"}","type":"weight","owner_id":"43140212523256","owner_resource":"variant","created_at":"2022-08-11T10:56:53+02:00","updated_at":"2022-08-11T10:56:53+02:00","admin_graphql_api_id":"gid://shopify/Metafield/23003692335352"},{"id":"23003692368120","namespace":"global","key":"0015","value":"{\"value\":20.0,\"unit\":\"ml\"}","type":"volume","owner_id":"43140212523256","owner_resource":"variant","created_at":"2022-08-11T10:56:53+02:00","updated_at":"2022-08-11T10:56:53+02:00","admin_graphql_api_id":"gid://shopify/Metafield/23003692368120"},{"id":"23003692400888","namespace":"global","key":"0016","value":"{\"value\":20.5,\"unit\":\"cm\"}","type":"dimension","owner_id":"43140212523256","owner_resource":"variant","created_at":"2022-08-11T10:56:53+02:00","updated_at":"2022-08-11T10:56:53+02:00","admin_graphql_api_id":"gid://shopify/Metafield/23003692400888"},{"id":"23003692433656","namespace":"global","key":"0017","value":"{\"scale_min\":\"1.0\",\"scale_max\":\"5.0\",\"value\":\"3.5\"}","type":"rating","owner_id":"43140212523256","owner_resource":"variant","created_at":"2022-08-11T10:56:53+02:00","updated_at":"2022-08-11T10:56:53+02:00","admin_graphql_api_id":"gid://shopify/Metafield/23003692433656"}],"option1":"Metal","option2":"lavender","option3":"veniam","position":"1","product_id":"7776958251256","sku":"4650857861437","taxable":"false","weight":"146.0","weight_unit":"oz","price":"695.64","updated_at":"2022-08-11T10:56:59+02:00","created_at":"2022-08-11T10:56:53+02:00","inventory_item_id":"45234784141560","admin_graphql_api_id":"gid://shopify/ProductVariant/43140212523256"},{"id":"43140212556024","barcode":"23325265","compare_at_price":"319.09","title":"Rubber / white / nisi","fulfillment_service":"manual","grams":"15649","image_id":"37914730234104","inventory_management":"shopify","inventory_policy":"deny","inventory_quantity":"0","metafields":[{"id":"23003692466424","namespace":"global","key":"0000","value":"This item contains dairy products.","type":"single_line_text_field","owner_id":"43140212556024","owner_resource":"variant","created_at":"2022-08-11T10:56:53+02:00","updated_at":"2022-08-11T10:56:53+02:00","admin_graphql_api_id":"gid://shopify/Metafield/23003692466424"},{"id":"23003692499192","namespace":"global","key":"0001","value":"Ingredients: \r\nFlour \r\nWater \r\nMilk \r\nEggs","type":"multi_line_text_field","owner_id":"43140212556024","owner_resource":"variant","created_at":"2022-08-11T10:56:53+02:00","updated_at":"2022-08-11T10:56:53+02:00","admin_graphql_api_id":"gid://shopify/Metafield/23003692499192"},{"id":"23003692531960","namespace":"global","key":"0002","value":"gid://shopify/OnlineStorePage/1","type":"page_reference","owner_id":"43140212556024","owner_resource":"variant","created_at":"2022-08-11T10:56:53+02:00","updated_at":"2022-08-11T10:56:53+02:00","admin_graphql_api_id":"gid://shopify/Metafield/23003692531960"},{"id":"23003692564728","namespace":"global","key":"0003","value":"gid://shopify/Product/1","type":"product_reference","owner_id":"43140212556024","owner_resource":"variant","created_at":"2022-08-11T10:56:53+02:00","updated_at":"2022-08-11T10:56:53+02:00","admin_graphql_api_id":"gid://shopify/Metafield/23003692564728"},{"id":"23003692597496","namespace":"global","key":"0004","value":"gid://shopify/ProductVariant/1","type":"variant_reference","owner_id":"43140212556024","owner_resource":"variant","created_at":"2022-08-11T10:56:53+02:00","updated_at":"2022-08-11T10:56:53+02:00","admin_graphql_api_id":"gid://shopify/Metafield/23003692597496"},{"id":"23003692630264","namespace":"global","key":"0005","value":"gid://shopify/MediaImage/123","type":"file_reference","owner_id":"43140212556024","owner_resource":"variant","created_at":"2022-08-11T10:56:53+02:00","updated_at":"2022-08-11T10:56:53+02:00","admin_graphql_api_id":"gid://shopify/Metafield/23003692630264"},{"id":"23003692663032","namespace":"global","key":"0006","value":"10","type":"number_integer","owner_id":"43140212556024","owner_resource":"variant","created_at":"2022-08-11T10:56:53+02:00","updated_at":"2022-08-11T10:56:53+02:00","admin_graphql_api_id":"gid://shopify/Metafield/23003692663032"},{"id":"23003692695800","namespace":"global","key":"0007","value":"10.4","type":"number_decimal","owner_id":"43140212556024","owner_resource":"variant","created_at":"2022-08-11T10:56:53+02:00","updated_at":"2022-08-11T10:56:53+02:00","admin_graphql_api_id":"gid://shopify/Metafield/23003692695800"},{"id":"23003692728568","namespace":"global","key":"0008","value":"2021-02-02","type":"date","owner_id":"43140212556024","owner_resource":"variant","created_at":"2022-08-11T10:56:53+02:00","updated_at":"2022-08-11T10:56:53+02:00","admin_graphql_api_id":"gid://shopify/Metafield/23003692728568"},{"id":"23003692761336","namespace":"global","key":"0009","value":"2021-01-01T12:30:00+00:00","type":"date_time","owner_id":"43140212556024","owner_resource":"variant","created_at":"2022-08-11T10:56:53+02:00","updated_at":"2022-08-11T10:56:53+02:00","admin_graphql_api_id":"gid://shopify/Metafield/23003692761336"},{"id":"23003692794104","namespace":"global","key":"0010","value":"https://www.shopify.com","type":"url","owner_id":"43140212556024","owner_resource":"variant","created_at":"2022-08-11T10:56:53+02:00","updated_at":"2022-08-11T10:56:53+02:00","admin_graphql_api_id":"gid://shopify/Metafield/23003692794104"},{"id":"23003692826872","namespace":"global","key":"0011","value":"[{\"k\":\"v1\"},{\"k\":\"v2\"}]","type":"json","owner_id":"43140212556024","owner_resource":"variant","created_at":"2022-08-11T10:56:53+02:00","updated_at":"2022-08-11T10:56:53+02:00","admin_graphql_api_id":"gid://shopify/Metafield/23003692826872"},{"id":"23003692859640","namespace":"global","key":"0012","value":"true","type":"boolean","owner_id":"43140212556024","owner_resource":"variant","created_at":"2022-08-11T10:56:53+02:00","updated_at":"2022-08-11T10:56:53+02:00","admin_graphql_api_id":"gid://shopify/Metafield/23003692859640"},{"id":"23003692892408","namespace":"global","key":"0013","value":"#fff123","type":"color","owner_id":"43140212556024","owner_resource":"variant","created_at":"2022-08-11T10:56:53+02:00","updated_at":"2022-08-11T10:56:53+02:00","admin_graphql_api_id":"gid://shopify/Metafield/23003692892408"},{"id":"23003692925176","namespace":"global","key":"0014","value":"{\"value\":2.5,\"unit\":\"kg\"}","type":"weight","owner_id":"43140212556024","owner_resource":"variant","created_at":"2022-08-11T10:56:53+02:00","updated_at":"2022-08-11T10:56:53+02:00","admin_graphql_api_id":"gid://shopify/Metafield/23003692925176"},{"id":"23003692957944","namespace":"global","key":"0015","value":"{\"value\":20.0,\"unit\":\"ml\"}","type":"volume","owner_id":"43140212556024","owner_resource":"variant","created_at":"2022-08-11T10:56:53+02:00","updated_at":"2022-08-11T10:56:53+02:00","admin_graphql_api_id":"gid://shopify/Metafield/23003692957944"},{"id":"23003692990712","namespace":"global","key":"0016","value":"{\"value\":20.5,\"unit\":\"cm\"}","type":"dimension","owner_id":"43140212556024","owner_resource":"variant","created_at":"2022-08-11T10:56:53+02:00","updated_at":"2022-08-11T10:56:53+02:00","admin_graphql_api_id":"gid://shopify/Metafield/23003692990712"},{"id":"23003693023480","namespace":"global","key":"0017","value":"{\"scale_min\":\"1.0\",\"scale_max\":\"5.0\",\"value\":\"3.5\"}","type":"rating","owner_id":"43140212556024","owner_resource":"variant","created_at":"2022-08-11T10:56:53+02:00","updated_at":"2022-08-11T10:56:53+02:00","admin_graphql_api_id":"gid://shopify/Metafield/23003693023480"}],"option1":"Rubber","option2":"white","option3":"nisi","position":"2","product_id":"7776958251256","sku":"9481965969594","taxable":"false","weight":"552.0","weight_unit":"oz","price":"986.28","updated_at":"2022-08-11T10:56:59+02:00","created_at":"2022-08-11T10:56:53+02:00","inventory_item_id":"45234784174328","admin_graphql_api_id":"gid://shopify/ProductVariant/43140212556024"},{"id":"43140212588792","barcode":"93895415","compare_at_price":"302.41","title":"Concrete / orchid / aut","fulfillment_service":"manual","grams":"2863","image_id":"37914730266872","inventory_management":"shopify","inventory_policy":"deny","inventory_quantity":"0","metafields":[{"id":"23003693056248","namespace":"global","key":"0000","value":"This item contains dairy products.","type":"single_line_text_field","owner_id":"43140212588792","owner_resource":"variant","created_at":"2022-08-11T10:56:53+02:00","updated_at":"2022-08-11T10:56:53+02:00","admin_graphql_api_id":"gid://shopify/Metafield/23003693056248"},{"id":"23003693089016","namespace":"global","key":"0001","value":"Ingredients: \r\nFlour \r\nWater \r\nMilk \r\nEggs","type":"multi_line_text_field","owner_id":"43140212588792","owner_resource":"variant","created_at":"2022-08-11T10:56:53+02:00","updated_at":"2022-08-11T10:56:53+02:00","admin_graphql_api_id":"gid://shopify/Metafield/23003693089016"},{"id":"23003693121784","namespace":"global","key":"0002","value":"gid://shopify/OnlineStorePage/1","type":"page_reference","owner_id":"43140212588792","owner_resource":"variant","created_at":"2022-08-11T10:56:53+02:00","updated_at":"2022-08-11T10:56:53+02:00","admin_graphql_api_id":"gid://shopify/Metafield/23003693121784"},{"id":"23003693154552","namespace":"global","key":"0003","value":"gid://shopify/Product/1","type":"product_reference","owner_id":"43140212588792","owner_resource":"variant","created_at":"2022-08-11T10:56:53+02:00","updated_at":"2022-08-11T10:56:53+02:00","admin_graphql_api_id":"gid://shopify/Metafield/23003693154552"},{"id":"23003693187320","namespace":"global","key":"0004","value":"gid://shopify/ProductVariant/1","type":"variant_reference","owner_id":"43140212588792","owner_resource":"variant","created_at":"2022-08-11T10:56:53+02:00","updated_at":"2022-08-11T10:56:53+02:00","admin_graphql_api_id":"gid://shopify/Metafield/23003693187320"},{"id":"23003693220088","namespace":"global","key":"0005","value":"gid://shopify/MediaImage/123","type":"file_reference","owner_id":"43140212588792","owner_resource":"variant","created_at":"2022-08-11T10:56:53+02:00","updated_at":"2022-08-11T10:56:53+02:00","admin_graphql_api_id":"gid://shopify/Metafield/23003693220088"},{"id":"23003693252856","namespace":"global","key":"0006","value":"10","type":"number_integer","owner_id":"43140212588792","owner_resource":"variant","created_at":"2022-08-11T10:56:53+02:00","updated_at":"2022-08-11T10:56:53+02:00","admin_graphql_api_id":"gid://shopify/Metafield/23003693252856"},{"id":"23003693285624","namespace":"global","key":"0007","value":"10.4","type":"number_decimal","owner_id":"43140212588792","owner_resource":"variant","created_at":"2022-08-11T10:56:53+02:00","updated_at":"2022-08-11T10:56:53+02:00","admin_graphql_api_id":"gid://shopify/Metafield/23003693285624"},{"id":"23003693318392","namespace":"global","key":"0008","value":"2021-02-02","type":"date","owner_id":"43140212588792","owner_resource":"variant","created_at":"2022-08-11T10:56:53+02:00","updated_at":"2022-08-11T10:56:53+02:00","admin_graphql_api_id":"gid://shopify/Metafield/23003693318392"},{"id":"23003693351160","namespace":"global","key":"0009","value":"2021-01-01T12:30:00+00:00","type":"date_time","owner_id":"43140212588792","owner_resource":"variant","created_at":"2022-08-11T10:56:53+02:00","updated_at":"2022-08-11T10:56:53+02:00","admin_graphql_api_id":"gid://shopify/Metafield/23003693351160"},{"id":"23003693383928","namespace":"global","key":"0010","value":"https://www.shopify.com","type":"url","owner_id":"43140212588792","owner_resource":"variant","created_at":"2022-08-11T10:56:53+02:00","updated_at":"2022-08-11T10:56:53+02:00","admin_graphql_api_id":"gid://shopify/Metafield/23003693383928"},{"id":"23003693416696","namespace":"global","key":"0011","value":"[{\"k\":\"v1\"},{\"k\":\"v2\"}]","type":"json","owner_id":"43140212588792","owner_resource":"variant","created_at":"2022-08-11T10:56:53+02:00","updated_at":"2022-08-11T10:56:53+02:00","admin_graphql_api_id":"gid://shopify/Metafield/23003693416696"},{"id":"23003693449464","namespace":"global","key":"0012","value":"true","type":"boolean","owner_id":"43140212588792","owner_resource":"variant","created_at":"2022-08-11T10:56:53+02:00","updated_at":"2022-08-11T10:56:53+02:00","admin_graphql_api_id":"gid://shopify/Metafield/23003693449464"},{"id":"23003693482232","namespace":"global","key":"0013","value":"#fff123","type":"color","owner_id":"43140212588792","owner_resource":"variant","created_at":"2022-08-11T10:56:53+02:00","updated_at":"2022-08-11T10:56:53+02:00","admin_graphql_api_id":"gid://shopify/Metafield/23003693482232"},{"id":"23003693515000","namespace":"global","key":"0014","value":"{\"value\":2.5,\"unit\":\"kg\"}","type":"weight","owner_id":"43140212588792","owner_resource":"variant","created_at":"2022-08-11T10:56:53+02:00","updated_at":"2022-08-11T10:56:53+02:00","admin_graphql_api_id":"gid://shopify/Metafield/23003693515000"},{"id":"23003693547768","namespace":"global","key":"0015","value":"{\"value\":20.0,\"unit\":\"ml\"}","type":"volume","owner_id":"43140212588792","owner_resource":"variant","created_at":"2022-08-11T10:56:53+02:00","updated_at":"2022-08-11T10:56:53+02:00","admin_graphql_api_id":"gid://shopify/Metafield/23003693547768"},{"id":"23003693580536","namespace":"global","key":"0016","value":"{\"value\":20.5,\"unit\":\"cm\"}","type":"dimension","owner_id":"43140212588792","owner_resource":"variant","created_at":"2022-08-11T10:56:53+02:00","updated_at":"2022-08-11T10:56:53+02:00","admin_graphql_api_id":"gid://shopify/Metafield/23003693580536"},{"id":"23003693613304","namespace":"global","key":"0017","value":"{\"scale_min\":\"1.0\",\"scale_max\":\"5.0\",\"value\":\"3.5\"}","type":"rating","owner_id":"43140212588792","owner_resource":"variant","created_at":"2022-08-11T10:56:53+02:00","updated_at":"2022-08-11T10:56:53+02:00","admin_graphql_api_id":"gid://shopify/Metafield/23003693613304"}],"option1":"Concrete","option2":"orchid","option3":"aut","position":"3","product_id":"7776958251256","sku":"5683877525835","taxable":"false","weight":"101.0","weight_unit":"oz","price":"307.97","updated_at":"2022-08-11T10:56:59+02:00","created_at":"2022-08-11T10:56:53+02:00","inventory_item_id":"45234784207096","admin_graphql_api_id":"gid://shopify/ProductVariant/43140212588792"}],"metafields":[{"id":"23003693646072","namespace":"global","key":"title_tag","value":"facere","type":"string","owner_id":"7776958251256","owner_resource":"product","created_at":"2022-08-11T10:56:53+02:00","updated_at":"2022-08-11T10:56:53+02:00","admin_graphql_api_id":"gid://shopify/Metafield/23003693646072"},{"id":"23003693678840","namespace":"global","key":"0000","value":"This item contains dairy products.","type":"single_line_text_field","owner_id":"7776958251256","owner_resource":"product","created_at":"2022-08-11T10:56:53+02:00","updated_at":"2022-08-11T10:56:53+02:00","admin_graphql_api_id":"gid://shopify/Metafield/23003693678840"},{"id":"23003693711608","namespace":"global","key":"0001","value":"Ingredients: \r\nFlour \r\nWater \r\nMilk \r\nEggs","type":"multi_line_text_field","owner_id":"7776958251256","owner_resource":"product","created_at":"2022-08-11T10:56:53+02:00","updated_at":"2022-08-11T10:56:53+02:00","admin_graphql_api_id":"gid://shopify/Metafield/23003693711608"},{"id":"23003693809912","namespace":"global","key":"0002","value":"gid://shopify/OnlineStorePage/1","type":"page_reference","owner_id":"7776958251256","owner_resource":"product","created_at":"2022-08-11T10:56:53+02:00","updated_at":"2022-08-11T10:56:53+02:00","admin_graphql_api_id":"gid://shopify/Metafield/23003693809912"},{"id":"23003693842680","namespace":"global","key":"0003","value":"gid://shopify/Product/1","type":"product_reference","owner_id":"7776958251256","owner_resource":"product","created_at":"2022-08-11T10:56:53+02:00","updated_at":"2022-08-11T10:56:53+02:00","admin_graphql_api_id":"gid://shopify/Metafield/23003693842680"},{"id":"23003693875448","namespace":"global","key":"0004","value":"gid://shopify/ProductVariant/1","type":"variant_reference","owner_id":"7776958251256","owner_resource":"product","created_at":"2022-08-11T10:56:53+02:00","updated_at":"2022-08-11T10:56:53+02:00","admin_graphql_api_id":"gid://shopify/Metafield/23003693875448"},{"id":"23003693908216","namespace":"global","key":"0005","value":"gid://shopify/MediaImage/123","type":"file_reference","owner_id":"7776958251256","owner_resource":"product","created_at":"2022-08-11T10:56:53+02:00","updated_at":"2022-08-11T10:56:53+02:00","admin_graphql_api_id":"gid://shopify/Metafield/23003693908216"},{"id":"23003693940984","namespace":"global","key":"0006","value":"10","type":"number_integer","owner_id":"7776958251256","owner_resource":"product","created_at":"2022-08-11T10:56:53+02:00","updated_at":"2022-08-11T10:56:53+02:00","admin_graphql_api_id":"gid://shopify/Metafield/23003693940984"},{"id":"23003693973752","namespace":"global","key":"0007","value":"10.4","type":"number_decimal","owner_id":"7776958251256","owner_resource":"product","created_at":"2022-08-11T10:56:53+02:00","updated_at":"2022-08-11T10:56:53+02:00","admin_graphql_api_id":"gid://shopify/Metafield/23003693973752"},{"id":"23003694006520","namespace":"global","key":"0008","value":"2021-02-02","type":"date","owner_id":"7776958251256","owner_resource":"product","created_at":"2022-08-11T10:56:53+02:00","updated_at":"2022-08-11T10:56:53+02:00","admin_graphql_api_id":"gid://shopify/Metafield/23003694006520"},{"id":"23003694039288","namespace":"global","key":"0009","value":"2021-01-01T12:30:00+00:00","type":"date_time","owner_id":"7776958251256","owner_resource":"product","created_at":"2022-08-11T10:56:53+02:00","updated_at":"2022-08-11T10:56:53+02:00","admin_graphql_api_id":"gid://shopify/Metafield/23003694039288"},{"id":"23003694072056","namespace":"global","key":"0010","value":"https://www.shopify.com","type":"url","owner_id":"7776958251256","owner_resource":"product","created_at":"2022-08-11T10:56:53+02:00","updated_at":"2022-08-11T10:56:53+02:00","admin_graphql_api_id":"gid://shopify/Metafield/23003694072056"},{"id":"23003694104824","namespace":"global","key":"0011","value":"[{\"k\":\"v1\"},{\"k\":\"v2\"}]","type":"json","owner_id":"7776958251256","owner_resource":"product","created_at":"2022-08-11T10:56:53+02:00","updated_at":"2022-08-11T10:56:53+02:00","admin_graphql_api_id":"gid://shopify/Metafield/23003694104824"},{"id":"23003694137592","namespace":"global","key":"0012","value":"true","type":"boolean","owner_id":"7776958251256","owner_resource":"product","created_at":"2022-08-11T10:56:53+02:00","updated_at":"2022-08-11T10:56:53+02:00","admin_graphql_api_id":"gid://shopify/Metafield/23003694137592"},{"id":"23003694170360","namespace":"global","key":"0013","value":"#fff123","type":"color","owner_id":"7776958251256","owner_resource":"product","created_at":"2022-08-11T10:56:53+02:00","updated_at":"2022-08-11T10:56:53+02:00","admin_graphql_api_id":"gid://shopify/Metafield/23003694170360"},{"id":"23003694203128","namespace":"global","key":"0014","value":"{\"value\":2.5,\"unit\":\"kg\"}","type":"weight","owner_id":"7776958251256","owner_resource":"product","created_at":"2022-08-11T10:56:53+02:00","updated_at":"2022-08-11T10:56:53+02:00","admin_graphql_api_id":"gid://shopify/Metafield/23003694203128"},{"id":"23003694235896","namespace":"global","key":"0015","value":"{\"value\":20.0,\"unit\":\"ml\"}","type":"volume","owner_id":"7776958251256","owner_resource":"product","created_at":"2022-08-11T10:56:53+02:00","updated_at":"2022-08-11T10:56:53+02:00","admin_graphql_api_id":"gid://shopify/Metafield/23003694235896"},{"id":"23003694268664","namespace":"global","key":"0016","value":"{\"value\":20.5,\"unit\":\"cm\"}","type":"dimension","owner_id":"7776958251256","owner_resource":"product","created_at":"2022-08-11T10:56:53+02:00","updated_at":"2022-08-11T10:56:53+02:00","admin_graphql_api_id":"gid://shopify/Metafield/23003694268664"},{"id":"23003694301432","namespace":"global","key":"0017","value":"{\"scale_min\":\"1.0\",\"scale_max\":\"5.0\",\"value\":\"3.5\"}","type":"rating","owner_id":"7776958251256","owner_resource":"product","created_at":"2022-08-11T10:56:53+02:00","updated_at":"2022-08-11T10:56:53+02:00","admin_graphql_api_id":"gid://shopify/Metafield/23003694301432"},{"id":"23003694334200","namespace":"global","key":"new-key","value":"new value","type":"single_line_text_field","owner_id":"7776958251256","owner_resource":"product","created_at":"2022-08-11T10:56:53+02:00","updated_at":"2022-08-11T10:56:53+02:00","admin_graphql_api_id":"gid://shopify/Metafield/23003694334200"},{"id":"23003694366968","namespace":"global","key":"description_tag","value":"non","type":"string","owner_id":"7776958251256","owner_resource":"product","created_at":"2022-08-11T10:56:53+02:00","updated_at":"2022-08-11T10:56:53+02:00","admin_graphql_api_id":"gid://shopify/Metafield/23003694366968"}],"admin_graphql_api_id":"gid://shopify/Product/7776958251256"}