{"id":"588141691128","author":"Shopify API","blog_id":"88628068600","body_html":"Perferendis repudiandae repellendus eos magnam neque ipsa voluptatem autem.","handle":"expedita-illo-magni","image":{"created_at":"2022-09-07T12:44:02+02:00","src":"https://cdn.shopify.com/s/files/1/0549/3132/5176/articles/card_cc8a4037-8a1d-41c6-ae46-bed8d111aa00.png?v=1662547442","filename":"card_cc8a4037-8a1d-41c6-ae46-bed8d111aa00.png","width":"128","height":"128"},"metafields":[{"id":"23115103076600","namespace":"global","key":"0000","value":"This item contains dairy products.","type":"single_line_text_field","owner_id":"588141691128","owner_resource":"article","created_at":"2022-09-07T12:42:16+02:00","updated_at":"2022-09-07T12:42:16+02:00","admin_graphql_api_id":"gid://shopify/Metafield/23115103076600"},{"id":"23115103109368","namespace":"global","key":"0001","value":"Ingredients: \r\nFlour \r\nWater \r\nMilk \r\nEggs","type":"multi_line_text_field","owner_id":"588141691128","owner_resource":"article","created_at":"2022-09-07T12:42:16+02:00","updated_at":"2022-09-07T12:42:16+02:00","admin_graphql_api_id":"gid://shopify/Metafield/23115103109368"},{"id":"23115103142136","namespace":"global","key":"0002","value":"gid://shopify/OnlineStorePage/1","type":"page_reference","owner_id":"588141691128","owner_resource":"article","created_at":"2022-09-07T12:42:16+02:00","updated_at":"2022-09-07T12:42:16+02:00","admin_graphql_api_id":"gid://shopify/Metafield/23115103142136"},{"id":"23115103174904","namespace":"global","key":"0003","value":"gid://shopify/Product/1","type":"product_reference","owner_id":"588141691128","owner_resource":"article","created_at":"2022-09-07T12:42:16+02:00","updated_at":"2022-09-07T12:42:16+02:00","admin_graphql_api_id":"gid://shopify/Metafield/23115103174904"},{"id":"23115103207672","namespace":"global","key":"0004","value":"gid://shopify/ProductVariant/1","type":"variant_reference","owner_id":"588141691128","owner_resource":"article","created_at":"2022-09-07T12:42:16+02:00","updated_at":"2022-09-07T12:42:16+02:00","admin_graphql_api_id":"gid://shopify/Metafield/23115103207672"},{"id":"23115103240440","namespace":"global","key":"0005","value":"gid://shopify/MediaImage/123","type":"file_reference","owner_id":"588141691128","owner_resource":"article","created_at":"2022-09-07T12:42:16+02:00","updated_at":"2022-09-07T12:42:16+02:00","admin_graphql_api_id":"gid://shopify/Metafield/23115103240440"},{"id":"23115103273208","namespace":"global","key":"0006","value":"10","type":"number_integer","owner_id":"588141691128","owner_resource":"article","created_at":"2022-09-07T12:42:16+02:00","updated_at":"2022-09-07T12:42:16+02:00","admin_graphql_api_id":"gid://shopify/Metafield/23115103273208"},{"id":"23115103305976","namespace":"global","key":"0007","value":"10.4","type":"number_decimal","owner_id":"588141691128","owner_resource":"article","created_at":"2022-09-07T12:42:16+02:00","updated_at":"2022-09-07T12:42:16+02:00","admin_graphql_api_id":"gid://shopify/Metafield/23115103305976"},{"id":"23115103338744","namespace":"global","key":"0008","value":"2021-02-02","type":"date","owner_id":"588141691128","owner_resource":"article","created_at":"2022-09-07T12:42:16+02:00","updated_at":"2022-09-07T12:42:16+02:00","admin_graphql_api_id":"gid://shopify/Metafield/23115103338744"},{"id":"23115103371512","namespace":"global","key":"0009","value":"2021-01-01T12:30:00+00:00","type":"date_time","owner_id":"588141691128","owner_resource":"article","created_at":"2022-09-07T12:42:16+02:00","updated_at":"2022-09-07T12:42:16+02:00","admin_graphql_api_id":"gid://shopify/Metafield/23115103371512"},{"id":"23115103404280","namespace":"global","key":"0010","value":"https://www.shopify.com","type":"url","owner_id":"588141691128","owner_resource":"article","created_at":"2022-09-07T12:42:16+02:00","updated_at":"2022-09-07T12:42:16+02:00","admin_graphql_api_id":"gid://shopify/Metafield/23115103404280"},{"id":"23115103437048","namespace":"global","key":"0011","value":"[{\"k\":\"v1\"},{\"k\":\"v2\"}]","type":"json","owner_id":"588141691128","owner_resource":"article","created_at":"2022-09-07T12:42:16+02:00","updated_at":"2022-09-07T12:42:16+02:00","admin_graphql_api_id":"gid://shopify/Metafield/23115103437048"},{"id":"23115103469816","namespace":"global","key":"0012","value":"true","type":"boolean","owner_id":"588141691128","owner_resource":"article","created_at":"2022-09-07T12:42:16+02:00","updated_at":"2022-09-07T12:42:16+02:00","admin_graphql_api_id":"gid://shopify/Metafield/23115103469816"},{"id":"23115103502584","namespace":"global","key":"0013","value":"#fff123","type":"color","owner_id":"588141691128","owner_resource":"article","created_at":"2022-09-07T12:42:16+02:00","updated_at":"2022-09-07T12:42:16+02:00","admin_graphql_api_id":"gid://shopify/Metafield/23115103502584"},{"id":"23115103535352","namespace":"global","key":"0014","value":"{\"value\":2.5,\"unit\":\"kg\"}","type":"weight","owner_id":"588141691128","owner_resource":"article","created_at":"2022-09-07T12:42:16+02:00","updated_at":"2022-09-07T12:42:16+02:00","admin_graphql_api_id":"gid://shopify/Metafield/23115103535352"},{"id":"23115103568120","namespace":"global","key":"0015","value":"{\"value\":20.0,\"unit\":\"ml\"}","type":"volume","owner_id":"588141691128","owner_resource":"article","created_at":"2022-09-07T12:42:16+02:00","updated_at":"2022-09-07T12:42:16+02:00","admin_graphql_api_id":"gid://shopify/Metafield/23115103568120"},{"id":"23115103600888","namespace":"global","key":"0016","value":"{\"value\":20.5,\"unit\":\"cm\"}","type":"dimension","owner_id":"588141691128","owner_resource":"article","created_at":"2022-09-07T12:42:16+02:00","updated_at":"2022-09-07T12:42:16+02:00","admin_graphql_api_id":"gid://shopify/Metafield/23115103600888"},{"id":"23115103633656","namespace":"global","key":"0017","value":"{\"scale_min\":\"1.0\",\"scale_max\":\"5.0\",\"value\":\"3.5\"}","type":"rating","owner_id":"588141691128","owner_resource":"article","created_at":"2022-09-07T12:42:16+02:00","updated_at":"2022-09-07T12:42:16+02:00","admin_graphql_api_id":"gid://shopify/Metafield/23115103633656"}],"published_at":"2022-09-07T12:40:10+02:00","tags":"","title":"quam","updated_at":"2022-09-07T12:44:02+02:00","created_at":"2022-09-07T12:42:16+02:00","admin_graphql_api_id":"gid://shopify/OnlineStoreArticle/588141691128"}