{"id":"6329608372472","email":"kak811@comcast.net","accepts_marketing":true,"accepts_marketing_updated_at":"2021-10-13T22:53:22+02:00","marketing_opt_in_level":"single_opt_in","created_at":"2022-02-11T15:37:19+02:00","updated_at":"2022-02-11T15:37:19+02:00","first_name":"Kathy","last_name":"Perrone","orders_count":0,"state":"disabled","total_spent":0.00,"verified_email":true,"tax_exempt":false,"tax_exemptions":[],"tags":"","default_address":{"id":"7691418042616","customer_id":"6329608372472","first_name":"Kathy","last_name":"Perrone","company":"","address1":"2312 North Palmetto Fort Drive","address2":"","city":"Mount Pleasant","province":"South Carolina","country":"United States","zip":"29466","phone":"","name":"Kathy Perrone","province_code":"SC","country_code":"US","country_name":"United States","default":true},"addresses":[{"id":"7691418042616","customer_id":"6329608372472","first_name":"Kathy","last_name":"Perrone","company":"","address1":"2312 North Palmetto Fort Drive","address2":"","city":"Mount Pleasant","province":"South Carolina","country":"United States","zip":"29466","phone":"","name":"Kathy Perrone","province_code":"SC","country_code":"US","country_name":"United States","default":true}],"admin_graphql_api_id":"gid://shopify/Customer/6329608372472","currency":"AUD"}