{"id":"7776963264760","title":"Practical Frozen Pants","handle":"aut","status":"active","options":[{"id":"9863862059256","product_id":"7776963264760","name":"Size","position":"1","values":["Fresh","Concrete","Plastic"]},{"id":"9863862092024","product_id":"7776963264760","name":"Color","position":"2","values":["fuchsia","silver","maroon"]},{"id":"9863862124792","product_id":"7776963264760","name":"Fabric","position":"3","values":["quidem","hic","assumenda"]}],"body_html":"The Football Is Good For Training And Recreational Purposes","tags":"doloribus","product_type":"repudiandae","ProductTypes":{"Id":null,"StandardizedProductType":null,"CustomProductType":"repudiandae"},"vendor":"non","published_at":"2022-07-21T07:35:01+00:00","published_scope":"web","updated_at":"2022-08-11T11:00:51+02:00","created_at":"2022-08-11T11:00:43+02:00","image":{"id":"37914747011320","product_id":"7776963264760","position":1,"src":"https://cdn.shopify.com/s/files/1/0549/3132/5176/products/marketing_connecting_barbados_dollar.jpg?v=1660208446","width":"128","height":"128","variant_ids":["43140220518648"],"created_at":"2022-08-11T09:00:43+00:00","updated_at":"2022-08-11T11:00:46+02:00","admin_graphql_api_id":"gid://shopify/ProductImage/37914747011320"},"images":[{"id":"37914747011320","product_id":"7776963264760","position":1,"src":"https://cdn.shopify.com/s/files/1/0549/3132/5176/products/marketing_connecting_barbados_dollar.jpg?v=1660208446","filename":"marketing_connecting_barbados_dollar.jpg","width":"128","height":"128","variant_ids":["43140220518648"],"metafields":[{"id":"23003805057272","namespace":"global","key":"0000","value":"This item contains dairy products.","type":"single_line_text_field","owner_id":"37914747011320","owner_resource":"product_image","created_at":"2022-08-11T11:00:43+02:00","updated_at":"2022-08-11T11:00:43+02:00","admin_graphql_api_id":"gid://shopify/Metafield/23003805057272"},{"id":"23003805090040","namespace":"global","key":"0001","value":"Ingredients: \r\nFlour \r\nWater \r\nMilk \r\nEggs","type":"multi_line_text_field","owner_id":"37914747011320","owner_resource":"product_image","created_at":"2022-08-11T11:00:43+02:00","updated_at":"2022-08-11T11:00:43+02:00","admin_graphql_api_id":"gid://shopify/Metafield/23003805090040"},{"id":"23003805122808","namespace":"global","key":"0002","value":"gid://shopify/OnlineStorePage/1","type":"page_reference","owner_id":"37914747011320","owner_resource":"product_image","created_at":"2022-08-11T11:00:43+02:00","updated_at":"2022-08-11T11:00:43+02:00","admin_graphql_api_id":"gid://shopify/Metafield/23003805122808"},{"id":"23003805155576","namespace":"global","key":"0003","value":"gid://shopify/Product/1","type":"product_reference","owner_id":"37914747011320","owner_resource":"product_image","created_at":"2022-08-11T11:00:43+02:00","updated_at":"2022-08-11T11:00:43+02:00","admin_graphql_api_id":"gid://shopify/Metafield/23003805155576"},{"id":"23003805188344","namespace":"global","key":"0004","value":"gid://shopify/ProductVariant/1","type":"variant_reference","owner_id":"37914747011320","owner_resource":"product_image","created_at":"2022-08-11T11:00:43+02:00","updated_at":"2022-08-11T11:00:43+02:00","admin_graphql_api_id":"gid://shopify/Metafield/23003805188344"},{"id":"23003805221112","namespace":"global","key":"0005","value":"gid://shopify/MediaImage/123","type":"file_reference","owner_id":"37914747011320","owner_resource":"product_image","created_at":"2022-08-11T11:00:43+02:00","updated_at":"2022-08-11T11:00:43+02:00","admin_graphql_api_id":"gid://shopify/Metafield/23003805221112"},{"id":"23003805253880","namespace":"global","key":"0006","value":"10","type":"number_integer","owner_id":"37914747011320","owner_resource":"product_image","created_at":"2022-08-11T11:00:43+02:00","updated_at":"2022-08-11T11:00:43+02:00","admin_graphql_api_id":"gid://shopify/Metafield/23003805253880"},{"id":"23003805286648","namespace":"global","key":"0007","value":"10.4","type":"number_decimal","owner_id":"37914747011320","owner_resource":"product_image","created_at":"2022-08-11T11:00:43+02:00","updated_at":"2022-08-11T11:00:43+02:00","admin_graphql_api_id":"gid://shopify/Metafield/23003805286648"},{"id":"23003805319416","namespace":"global","key":"0008","value":"2021-02-02","type":"date","owner_id":"37914747011320","owner_resource":"product_image","created_at":"2022-08-11T11:00:43+02:00","updated_at":"2022-08-11T11:00:43+02:00","admin_graphql_api_id":"gid://shopify/Metafield/23003805319416"},{"id":"23003805352184","namespace":"global","key":"0009","value":"2021-01-01T12:30:00+00:00","type":"date_time","owner_id":"37914747011320","owner_resource":"product_image","created_at":"2022-08-11T11:00:43+02:00","updated_at":"2022-08-11T11:00:43+02:00","admin_graphql_api_id":"gid://shopify/Metafield/23003805352184"},{"id":"23003805384952","namespace":"global","key":"0010","value":"https://www.shopify.com","type":"url","owner_id":"37914747011320","owner_resource":"product_image","created_at":"2022-08-11T11:00:43+02:00","updated_at":"2022-08-11T11:00:43+02:00","admin_graphql_api_id":"gid://shopify/Metafield/23003805384952"},{"id":"23003805417720","namespace":"global","key":"0011","value":"[{\"k\":\"v1\"},{\"k\":\"v2\"}]","type":"json","owner_id":"37914747011320","owner_resource":"product_image","created_at":"2022-08-11T11:00:43+02:00","updated_at":"2022-08-11T11:00:43+02:00","admin_graphql_api_id":"gid://shopify/Metafield/23003805417720"},{"id":"23003805450488","namespace":"global","key":"0012","value":"true","type":"boolean","owner_id":"37914747011320","owner_resource":"product_image","created_at":"2022-08-11T11:00:43+02:00","updated_at":"2022-08-11T11:00:43+02:00","admin_graphql_api_id":"gid://shopify/Metafield/23003805450488"},{"id":"23003805483256","namespace":"global","key":"0013","value":"#fff123","type":"color","owner_id":"37914747011320","owner_resource":"product_image","created_at":"2022-08-11T11:00:43+02:00","updated_at":"2022-08-11T11:00:43+02:00","admin_graphql_api_id":"gid://shopify/Metafield/23003805483256"},{"id":"23003805516024","namespace":"global","key":"0014","value":"{\"value\":2.5,\"unit\":\"kg\"}","type":"weight","owner_id":"37914747011320","owner_resource":"product_image","created_at":"2022-08-11T11:00:43+02:00","updated_at":"2022-08-11T11:00:43+02:00","admin_graphql_api_id":"gid://shopify/Metafield/23003805516024"},{"id":"23003805548792","namespace":"global","key":"0015","value":"{\"value\":20.0,\"unit\":\"ml\"}","type":"volume","owner_id":"37914747011320","owner_resource":"product_image","created_at":"2022-08-11T11:00:43+02:00","updated_at":"2022-08-11T11:00:43+02:00","admin_graphql_api_id":"gid://shopify/Metafield/23003805548792"},{"id":"23003805581560","namespace":"global","key":"0016","value":"{\"value\":20.5,\"unit\":\"cm\"}","type":"dimension","owner_id":"37914747011320","owner_resource":"product_image","created_at":"2022-08-11T11:00:43+02:00","updated_at":"2022-08-11T11:00:43+02:00","admin_graphql_api_id":"gid://shopify/Metafield/23003805581560"},{"id":"23003805614328","namespace":"global","key":"0017","value":"{\"scale_min\":\"1.0\",\"scale_max\":\"5.0\",\"value\":\"3.5\"}","type":"rating","owner_id":"37914747011320","owner_resource":"product_image","created_at":"2022-08-11T11:00:43+02:00","updated_at":"2022-08-11T11:00:43+02:00","admin_graphql_api_id":"gid://shopify/Metafield/23003805614328"}],"created_at":"2022-08-11T09:00:43+00:00","updated_at":"2022-08-11T11:00:46+02:00","admin_graphql_api_id":"gid://shopify/ProductImage/37914747011320"},{"id":"37914747076856","product_id":"7776963264760","position":2,"src":"https://cdn.shopify.com/s/files/1/0549/3132/5176/products/tertiary.jpg?v=1660208447","filename":"tertiary.jpg","width":"128","height":"128","variant_ids":["43140220551416"],"metafields":[{"id":"23003805647096","namespace":"global","key":"0000","value":"This item contains dairy products.","type":"single_line_text_field","owner_id":"37914747076856","owner_resource":"product_image","created_at":"2022-08-11T11:00:44+02:00","updated_at":"2022-08-11T11:00:44+02:00","admin_graphql_api_id":"gid://shopify/Metafield/23003805647096"},{"id":"23003805679864","namespace":"global","key":"0001","value":"Ingredients: \r\nFlour \r\nWater \r\nMilk \r\nEggs","type":"multi_line_text_field","owner_id":"37914747076856","owner_resource":"product_image","created_at":"2022-08-11T11:00:44+02:00","updated_at":"2022-08-11T11:00:44+02:00","admin_graphql_api_id":"gid://shopify/Metafield/23003805679864"},{"id":"23003805712632","namespace":"global","key":"0002","value":"gid://shopify/OnlineStorePage/1","type":"page_reference","owner_id":"37914747076856","owner_resource":"product_image","created_at":"2022-08-11T11:00:44+02:00","updated_at":"2022-08-11T11:00:44+02:00","admin_graphql_api_id":"gid://shopify/Metafield/23003805712632"},{"id":"23003805745400","namespace":"global","key":"0003","value":"gid://shopify/Product/1","type":"product_reference","owner_id":"37914747076856","owner_resource":"product_image","created_at":"2022-08-11T11:00:44+02:00","updated_at":"2022-08-11T11:00:44+02:00","admin_graphql_api_id":"gid://shopify/Metafield/23003805745400"},{"id":"23003805778168","namespace":"global","key":"0004","value":"gid://shopify/ProductVariant/1","type":"variant_reference","owner_id":"37914747076856","owner_resource":"product_image","created_at":"2022-08-11T11:00:44+02:00","updated_at":"2022-08-11T11:00:44+02:00","admin_graphql_api_id":"gid://shopify/Metafield/23003805778168"},{"id":"23003805810936","namespace":"global","key":"0005","value":"gid://shopify/MediaImage/123","type":"file_reference","owner_id":"37914747076856","owner_resource":"product_image","created_at":"2022-08-11T11:00:44+02:00","updated_at":"2022-08-11T11:00:44+02:00","admin_graphql_api_id":"gid://shopify/Metafield/23003805810936"},{"id":"23003805843704","namespace":"global","key":"0006","value":"10","type":"number_integer","owner_id":"37914747076856","owner_resource":"product_image","created_at":"2022-08-11T11:00:44+02:00","updated_at":"2022-08-11T11:00:44+02:00","admin_graphql_api_id":"gid://shopify/Metafield/23003805843704"},{"id":"23003805876472","namespace":"global","key":"0007","value":"10.4","type":"number_decimal","owner_id":"37914747076856","owner_resource":"product_image","created_at":"2022-08-11T11:00:44+02:00","updated_at":"2022-08-11T11:00:44+02:00","admin_graphql_api_id":"gid://shopify/Metafield/23003805876472"},{"id":"23003805909240","namespace":"global","key":"0008","value":"2021-02-02","type":"date","owner_id":"37914747076856","owner_resource":"product_image","created_at":"2022-08-11T11:00:44+02:00","updated_at":"2022-08-11T11:00:44+02:00","admin_graphql_api_id":"gid://shopify/Metafield/23003805909240"},{"id":"23003805942008","namespace":"global","key":"0009","value":"2021-01-01T12:30:00+00:00","type":"date_time","owner_id":"37914747076856","owner_resource":"product_image","created_at":"2022-08-11T11:00:44+02:00","updated_at":"2022-08-11T11:00:44+02:00","admin_graphql_api_id":"gid://shopify/Metafield/23003805942008"},{"id":"23003805974776","namespace":"global","key":"0010","value":"https://www.shopify.com","type":"url","owner_id":"37914747076856","owner_resource":"product_image","created_at":"2022-08-11T11:00:44+02:00","updated_at":"2022-08-11T11:00:44+02:00","admin_graphql_api_id":"gid://shopify/Metafield/23003805974776"},{"id":"23003806007544","namespace":"global","key":"0011","value":"[{\"k\":\"v1\"},{\"k\":\"v2\"}]","type":"json","owner_id":"37914747076856","owner_resource":"product_image","created_at":"2022-08-11T11:00:44+02:00","updated_at":"2022-08-11T11:00:44+02:00","admin_graphql_api_id":"gid://shopify/Metafield/23003806007544"},{"id":"23003806040312","namespace":"global","key":"0012","value":"true","type":"boolean","owner_id":"37914747076856","owner_resource":"product_image","created_at":"2022-08-11T11:00:44+02:00","updated_at":"2022-08-11T11:00:44+02:00","admin_graphql_api_id":"gid://shopify/Metafield/23003806040312"},{"id":"23003806105848","namespace":"global","key":"0013","value":"#fff123","type":"color","owner_id":"37914747076856","owner_resource":"product_image","created_at":"2022-08-11T11:00:44+02:00","updated_at":"2022-08-11T11:00:44+02:00","admin_graphql_api_id":"gid://shopify/Metafield/23003806105848"},{"id":"23003806138616","namespace":"global","key":"0014","value":"{\"value\":2.5,\"unit\":\"kg\"}","type":"weight","owner_id":"37914747076856","owner_resource":"product_image","created_at":"2022-08-11T11:00:44+02:00","updated_at":"2022-08-11T11:00:44+02:00","admin_graphql_api_id":"gid://shopify/Metafield/23003806138616"},{"id":"23003806171384","namespace":"global","key":"0015","value":"{\"value\":20.0,\"unit\":\"ml\"}","type":"volume","owner_id":"37914747076856","owner_resource":"product_image","created_at":"2022-08-11T11:00:44+02:00","updated_at":"2022-08-11T11:00:44+02:00","admin_graphql_api_id":"gid://shopify/Metafield/23003806171384"},{"id":"23003806204152","namespace":"global","key":"0016","value":"{\"value\":20.5,\"unit\":\"cm\"}","type":"dimension","owner_id":"37914747076856","owner_resource":"product_image","created_at":"2022-08-11T11:00:44+02:00","updated_at":"2022-08-11T11:00:44+02:00","admin_graphql_api_id":"gid://shopify/Metafield/23003806204152"},{"id":"23003806236920","namespace":"global","key":"0017","value":"{\"scale_min\":\"1.0\",\"scale_max\":\"5.0\",\"value\":\"3.5\"}","type":"rating","owner_id":"37914747076856","owner_resource":"product_image","created_at":"2022-08-11T11:00:44+02:00","updated_at":"2022-08-11T11:00:44+02:00","admin_graphql_api_id":"gid://shopify/Metafield/23003806236920"}],"created_at":"2022-08-11T09:00:44+00:00","updated_at":"2022-08-11T11:00:47+02:00","admin_graphql_api_id":"gid://shopify/ProductImage/37914747076856"},{"id":"37914747109624","product_id":"7776963264760","position":3,"src":"https://cdn.shopify.com/s/files/1/0549/3132/5176/products/system_worthy_tasty_plastic_pizza.jpg?v=1660208447","filename":"system_worthy_tasty_plastic_pizza.jpg","width":"216","height":"216","variant_ids":["43140220584184"],"metafields":[{"id":"23003806302456","namespace":"global","key":"0000","value":"This item contains dairy products.","type":"single_line_text_field","owner_id":"37914747109624","owner_resource":"product_image","created_at":"2022-08-11T11:00:44+02:00","updated_at":"2022-08-11T11:00:44+02:00","admin_graphql_api_id":"gid://shopify/Metafield/23003806302456"},{"id":"23003806335224","namespace":"global","key":"0001","value":"Ingredients: \r\nFlour \r\nWater \r\nMilk \r\nEggs","type":"multi_line_text_field","owner_id":"37914747109624","owner_resource":"product_image","created_at":"2022-08-11T11:00:44+02:00","updated_at":"2022-08-11T11:00:44+02:00","admin_graphql_api_id":"gid://shopify/Metafield/23003806335224"},{"id":"23003806367992","namespace":"global","key":"0002","value":"gid://shopify/OnlineStorePage/1","type":"page_reference","owner_id":"37914747109624","owner_resource":"product_image","created_at":"2022-08-11T11:00:44+02:00","updated_at":"2022-08-11T11:00:44+02:00","admin_graphql_api_id":"gid://shopify/Metafield/23003806367992"},{"id":"23003806400760","namespace":"global","key":"0003","value":"gid://shopify/Product/1","type":"product_reference","owner_id":"37914747109624","owner_resource":"product_image","created_at":"2022-08-11T11:00:44+02:00","updated_at":"2022-08-11T11:00:44+02:00","admin_graphql_api_id":"gid://shopify/Metafield/23003806400760"},{"id":"23003806433528","namespace":"global","key":"0004","value":"gid://shopify/ProductVariant/1","type":"variant_reference","owner_id":"37914747109624","owner_resource":"product_image","created_at":"2022-08-11T11:00:44+02:00","updated_at":"2022-08-11T11:00:44+02:00","admin_graphql_api_id":"gid://shopify/Metafield/23003806433528"},{"id":"23003806466296","namespace":"global","key":"0005","value":"gid://shopify/MediaImage/123","type":"file_reference","owner_id":"37914747109624","owner_resource":"product_image","created_at":"2022-08-11T11:00:44+02:00","updated_at":"2022-08-11T11:00:44+02:00","admin_graphql_api_id":"gid://shopify/Metafield/23003806466296"},{"id":"23003806499064","namespace":"global","key":"0006","value":"10","type":"number_integer","owner_id":"37914747109624","owner_resource":"product_image","created_at":"2022-08-11T11:00:44+02:00","updated_at":"2022-08-11T11:00:44+02:00","admin_graphql_api_id":"gid://shopify/Metafield/23003806499064"},{"id":"23003806531832","namespace":"global","key":"0007","value":"10.4","type":"number_decimal","owner_id":"37914747109624","owner_resource":"product_image","created_at":"2022-08-11T11:00:44+02:00","updated_at":"2022-08-11T11:00:44+02:00","admin_graphql_api_id":"gid://shopify/Metafield/23003806531832"},{"id":"23003806564600","namespace":"global","key":"0008","value":"2021-02-02","type":"date","owner_id":"37914747109624","owner_resource":"product_image","created_at":"2022-08-11T11:00:44+02:00","updated_at":"2022-08-11T11:00:44+02:00","admin_graphql_api_id":"gid://shopify/Metafield/23003806564600"},{"id":"23003806597368","namespace":"global","key":"0009","value":"2021-01-01T12:30:00+00:00","type":"date_time","owner_id":"37914747109624","owner_resource":"product_image","created_at":"2022-08-11T11:00:44+02:00","updated_at":"2022-08-11T11:00:44+02:00","admin_graphql_api_id":"gid://shopify/Metafield/23003806597368"},{"id":"23003806630136","namespace":"global","key":"0010","value":"https://www.shopify.com","type":"url","owner_id":"37914747109624","owner_resource":"product_image","created_at":"2022-08-11T11:00:44+02:00","updated_at":"2022-08-11T11:00:44+02:00","admin_graphql_api_id":"gid://shopify/Metafield/23003806630136"},{"id":"23003806662904","namespace":"global","key":"0011","value":"[{\"k\":\"v1\"},{\"k\":\"v2\"}]","type":"json","owner_id":"37914747109624","owner_resource":"product_image","created_at":"2022-08-11T11:00:44+02:00","updated_at":"2022-08-11T11:00:44+02:00","admin_graphql_api_id":"gid://shopify/Metafield/23003806662904"},{"id":"23003806695672","namespace":"global","key":"0012","value":"true","type":"boolean","owner_id":"37914747109624","owner_resource":"product_image","created_at":"2022-08-11T11:00:44+02:00","updated_at":"2022-08-11T11:00:44+02:00","admin_graphql_api_id":"gid://shopify/Metafield/23003806695672"},{"id":"23003806728440","namespace":"global","key":"0013","value":"#fff123","type":"color","owner_id":"37914747109624","owner_resource":"product_image","created_at":"2022-08-11T11:00:44+02:00","updated_at":"2022-08-11T11:00:44+02:00","admin_graphql_api_id":"gid://shopify/Metafield/23003806728440"},{"id":"23003806761208","namespace":"global","key":"0014","value":"{\"value\":2.5,\"unit\":\"kg\"}","type":"weight","owner_id":"37914747109624","owner_resource":"product_image","created_at":"2022-08-11T11:00:44+02:00","updated_at":"2022-08-11T11:00:44+02:00","admin_graphql_api_id":"gid://shopify/Metafield/23003806761208"},{"id":"23003806793976","namespace":"global","key":"0015","value":"{\"value\":20.0,\"unit\":\"ml\"}","type":"volume","owner_id":"37914747109624","owner_resource":"product_image","created_at":"2022-08-11T11:00:44+02:00","updated_at":"2022-08-11T11:00:44+02:00","admin_graphql_api_id":"gid://shopify/Metafield/23003806793976"},{"id":"23003806826744","namespace":"global","key":"0016","value":"{\"value\":20.5,\"unit\":\"cm\"}","type":"dimension","owner_id":"37914747109624","owner_resource":"product_image","created_at":"2022-08-11T11:00:44+02:00","updated_at":"2022-08-11T11:00:44+02:00","admin_graphql_api_id":"gid://shopify/Metafield/23003806826744"},{"id":"23003806859512","namespace":"global","key":"0017","value":"{\"scale_min\":\"1.0\",\"scale_max\":\"5.0\",\"value\":\"3.5\"}","type":"rating","owner_id":"37914747109624","owner_resource":"product_image","created_at":"2022-08-11T11:00:44+02:00","updated_at":"2022-08-11T11:00:44+02:00","admin_graphql_api_id":"gid://shopify/Metafield/23003806859512"}],"created_at":"2022-08-11T09:00:44+00:00","updated_at":"2022-08-11T11:00:47+02:00","admin_graphql_api_id":"gid://shopify/ProductImage/37914747109624"},{"id":"37914747142392","product_id":"7776963264760","position":4,"src":"https://cdn.shopify.com/s/files/1/0549/3132/5176/products/zimbabwe_optical.jpg?v=1660208447","filename":"zimbabwe_optical.jpg","width":"128","height":"128","variant_ids":[],"metafields":[{"id":"23003806892280","namespace":"global","key":"0000","value":"This item contains dairy products.","type":"single_line_text_field","owner_id":"37914747142392","owner_resource":"product_image","created_at":"2022-08-11T11:00:44+02:00","updated_at":"2022-08-11T11:00:44+02:00","admin_graphql_api_id":"gid://shopify/Metafield/23003806892280"},{"id":"23003806925048","namespace":"global","key":"0001","value":"Ingredients: \r\nFlour \r\nWater \r\nMilk \r\nEggs","type":"multi_line_text_field","owner_id":"37914747142392","owner_resource":"product_image","created_at":"2022-08-11T11:00:44+02:00","updated_at":"2022-08-11T11:00:44+02:00","admin_graphql_api_id":"gid://shopify/Metafield/23003806925048"},{"id":"23003806957816","namespace":"global","key":"0002","value":"gid://shopify/OnlineStorePage/1","type":"page_reference","owner_id":"37914747142392","owner_resource":"product_image","created_at":"2022-08-11T11:00:44+02:00","updated_at":"2022-08-11T11:00:44+02:00","admin_graphql_api_id":"gid://shopify/Metafield/23003806957816"},{"id":"23003806990584","namespace":"global","key":"0003","value":"gid://shopify/Product/1","type":"product_reference","owner_id":"37914747142392","owner_resource":"product_image","created_at":"2022-08-11T11:00:44+02:00","updated_at":"2022-08-11T11:00:44+02:00","admin_graphql_api_id":"gid://shopify/Metafield/23003806990584"},{"id":"23003807023352","namespace":"global","key":"0004","value":"gid://shopify/ProductVariant/1","type":"variant_reference","owner_id":"37914747142392","owner_resource":"product_image","created_at":"2022-08-11T11:00:44+02:00","updated_at":"2022-08-11T11:00:44+02:00","admin_graphql_api_id":"gid://shopify/Metafield/23003807023352"},{"id":"23003807056120","namespace":"global","key":"0005","value":"gid://shopify/MediaImage/123","type":"file_reference","owner_id":"37914747142392","owner_resource":"product_image","created_at":"2022-08-11T11:00:44+02:00","updated_at":"2022-08-11T11:00:44+02:00","admin_graphql_api_id":"gid://shopify/Metafield/23003807056120"},{"id":"23003807088888","namespace":"global","key":"0006","value":"10","type":"number_integer","owner_id":"37914747142392","owner_resource":"product_image","created_at":"2022-08-11T11:00:44+02:00","updated_at":"2022-08-11T11:00:44+02:00","admin_graphql_api_id":"gid://shopify/Metafield/23003807088888"},{"id":"23003807121656","namespace":"global","key":"0007","value":"10.4","type":"number_decimal","owner_id":"37914747142392","owner_resource":"product_image","created_at":"2022-08-11T11:00:44+02:00","updated_at":"2022-08-11T11:00:44+02:00","admin_graphql_api_id":"gid://shopify/Metafield/23003807121656"},{"id":"23003807154424","namespace":"global","key":"0008","value":"2021-02-02","type":"date","owner_id":"37914747142392","owner_resource":"product_image","created_at":"2022-08-11T11:00:44+02:00","updated_at":"2022-08-11T11:00:44+02:00","admin_graphql_api_id":"gid://shopify/Metafield/23003807154424"},{"id":"23003807187192","namespace":"global","key":"0009","value":"2021-01-01T12:30:00+00:00","type":"date_time","owner_id":"37914747142392","owner_resource":"product_image","created_at":"2022-08-11T11:00:44+02:00","updated_at":"2022-08-11T11:00:44+02:00","admin_graphql_api_id":"gid://shopify/Metafield/23003807187192"},{"id":"23003807219960","namespace":"global","key":"0010","value":"https://www.shopify.com","type":"url","owner_id":"37914747142392","owner_resource":"product_image","created_at":"2022-08-11T11:00:44+02:00","updated_at":"2022-08-11T11:00:44+02:00","admin_graphql_api_id":"gid://shopify/Metafield/23003807219960"},{"id":"23003807252728","namespace":"global","key":"0011","value":"[{\"k\":\"v1\"},{\"k\":\"v2\"}]","type":"json","owner_id":"37914747142392","owner_resource":"product_image","created_at":"2022-08-11T11:00:44+02:00","updated_at":"2022-08-11T11:00:44+02:00","admin_graphql_api_id":"gid://shopify/Metafield/23003807252728"},{"id":"23003807285496","namespace":"global","key":"0012","value":"true","type":"boolean","owner_id":"37914747142392","owner_resource":"product_image","created_at":"2022-08-11T11:00:44+02:00","updated_at":"2022-08-11T11:00:44+02:00","admin_graphql_api_id":"gid://shopify/Metafield/23003807285496"},{"id":"23003807318264","namespace":"global","key":"0013","value":"#fff123","type":"color","owner_id":"37914747142392","owner_resource":"product_image","created_at":"2022-08-11T11:00:44+02:00","updated_at":"2022-08-11T11:00:44+02:00","admin_graphql_api_id":"gid://shopify/Metafield/23003807318264"},{"id":"23003807351032","namespace":"global","key":"0014","value":"{\"value\":2.5,\"unit\":\"kg\"}","type":"weight","owner_id":"37914747142392","owner_resource":"product_image","created_at":"2022-08-11T11:00:44+02:00","updated_at":"2022-08-11T11:00:44+02:00","admin_graphql_api_id":"gid://shopify/Metafield/23003807351032"},{"id":"23003807383800","namespace":"global","key":"0015","value":"{\"value\":20.0,\"unit\":\"ml\"}","type":"volume","owner_id":"37914747142392","owner_resource":"product_image","created_at":"2022-08-11T11:00:44+02:00","updated_at":"2022-08-11T11:00:44+02:00","admin_graphql_api_id":"gid://shopify/Metafield/23003807383800"},{"id":"23003807416568","namespace":"global","key":"0016","value":"{\"value\":20.5,\"unit\":\"cm\"}","type":"dimension","owner_id":"37914747142392","owner_resource":"product_image","created_at":"2022-08-11T11:00:44+02:00","updated_at":"2022-08-11T11:00:44+02:00","admin_graphql_api_id":"gid://shopify/Metafield/23003807416568"},{"id":"23003807449336","namespace":"global","key":"0017","value":"{\"scale_min\":\"1.0\",\"scale_max\":\"5.0\",\"value\":\"3.5\"}","type":"rating","owner_id":"37914747142392","owner_resource":"product_image","created_at":"2022-08-11T11:00:44+02:00","updated_at":"2022-08-11T11:00:44+02:00","admin_graphql_api_id":"gid://shopify/Metafield/23003807449336"}],"created_at":"2022-08-11T09:00:44+00:00","updated_at":"2022-08-11T11:00:47+02:00","admin_graphql_api_id":"gid://shopify/ProductImage/37914747142392"},{"id":"37914747175160","product_id":"7776963264760","position":5,"src":"https://cdn.shopify.com/s/files/1/0549/3132/5176/products/wireless_music_payment.jpg?v=1660208448","filename":"wireless_music_payment.jpg","width":"128","height":"128","variant_ids":[],"metafields":[{"id":"23003807514872","namespace":"global","key":"0000","value":"This item contains dairy products.","type":"single_line_text_field","owner_id":"37914747175160","owner_resource":"product_image","created_at":"2022-08-11T11:00:44+02:00","updated_at":"2022-08-11T11:00:44+02:00","admin_graphql_api_id":"gid://shopify/Metafield/23003807514872"},{"id":"23003807547640","namespace":"global","key":"0001","value":"Ingredients: \r\nFlour \r\nWater \r\nMilk \r\nEggs","type":"multi_line_text_field","owner_id":"37914747175160","owner_resource":"product_image","created_at":"2022-08-11T11:00:44+02:00","updated_at":"2022-08-11T11:00:44+02:00","admin_graphql_api_id":"gid://shopify/Metafield/23003807547640"},{"id":"23003807580408","namespace":"global","key":"0002","value":"gid://shopify/OnlineStorePage/1","type":"page_reference","owner_id":"37914747175160","owner_resource":"product_image","created_at":"2022-08-11T11:00:44+02:00","updated_at":"2022-08-11T11:00:44+02:00","admin_graphql_api_id":"gid://shopify/Metafield/23003807580408"},{"id":"23003807613176","namespace":"global","key":"0003","value":"gid://shopify/Product/1","type":"product_reference","owner_id":"37914747175160","owner_resource":"product_image","created_at":"2022-08-11T11:00:44+02:00","updated_at":"2022-08-11T11:00:44+02:00","admin_graphql_api_id":"gid://shopify/Metafield/23003807613176"},{"id":"23003807645944","namespace":"global","key":"0004","value":"gid://shopify/ProductVariant/1","type":"variant_reference","owner_id":"37914747175160","owner_resource":"product_image","created_at":"2022-08-11T11:00:44+02:00","updated_at":"2022-08-11T11:00:44+02:00","admin_graphql_api_id":"gid://shopify/Metafield/23003807645944"},{"id":"23003807678712","namespace":"global","key":"0005","value":"gid://shopify/MediaImage/123","type":"file_reference","owner_id":"37914747175160","owner_resource":"product_image","created_at":"2022-08-11T11:00:44+02:00","updated_at":"2022-08-11T11:00:44+02:00","admin_graphql_api_id":"gid://shopify/Metafield/23003807678712"},{"id":"23003807711480","namespace":"global","key":"0006","value":"10","type":"number_integer","owner_id":"37914747175160","owner_resource":"product_image","created_at":"2022-08-11T11:00:44+02:00","updated_at":"2022-08-11T11:00:44+02:00","admin_graphql_api_id":"gid://shopify/Metafield/23003807711480"},{"id":"23003807744248","namespace":"global","key":"0007","value":"10.4","type":"number_decimal","owner_id":"37914747175160","owner_resource":"product_image","created_at":"2022-08-11T11:00:44+02:00","updated_at":"2022-08-11T11:00:44+02:00","admin_graphql_api_id":"gid://shopify/Metafield/23003807744248"},{"id":"23003807777016","namespace":"global","key":"0008","value":"2021-02-02","type":"date","owner_id":"37914747175160","owner_resource":"product_image","created_at":"2022-08-11T11:00:44+02:00","updated_at":"2022-08-11T11:00:44+02:00","admin_graphql_api_id":"gid://shopify/Metafield/23003807777016"},{"id":"23003807809784","namespace":"global","key":"0009","value":"2021-01-01T12:30:00+00:00","type":"date_time","owner_id":"37914747175160","owner_resource":"product_image","created_at":"2022-08-11T11:00:44+02:00","updated_at":"2022-08-11T11:00:44+02:00","admin_graphql_api_id":"gid://shopify/Metafield/23003807809784"},{"id":"23003807842552","namespace":"global","key":"0010","value":"https://www.shopify.com","type":"url","owner_id":"37914747175160","owner_resource":"product_image","created_at":"2022-08-11T11:00:44+02:00","updated_at":"2022-08-11T11:00:44+02:00","admin_graphql_api_id":"gid://shopify/Metafield/23003807842552"},{"id":"23003807875320","namespace":"global","key":"0011","value":"[{\"k\":\"v1\"},{\"k\":\"v2\"}]","type":"json","owner_id":"37914747175160","owner_resource":"product_image","created_at":"2022-08-11T11:00:44+02:00","updated_at":"2022-08-11T11:00:44+02:00","admin_graphql_api_id":"gid://shopify/Metafield/23003807875320"},{"id":"23003807908088","namespace":"global","key":"0012","value":"true","type":"boolean","owner_id":"37914747175160","owner_resource":"product_image","created_at":"2022-08-11T11:00:44+02:00","updated_at":"2022-08-11T11:00:44+02:00","admin_graphql_api_id":"gid://shopify/Metafield/23003807908088"},{"id":"23003807940856","namespace":"global","key":"0013","value":"#fff123","type":"color","owner_id":"37914747175160","owner_resource":"product_image","created_at":"2022-08-11T11:00:44+02:00","updated_at":"2022-08-11T11:00:44+02:00","admin_graphql_api_id":"gid://shopify/Metafield/23003807940856"},{"id":"23003807973624","namespace":"global","key":"0014","value":"{\"value\":2.5,\"unit\":\"kg\"}","type":"weight","owner_id":"37914747175160","owner_resource":"product_image","created_at":"2022-08-11T11:00:44+02:00","updated_at":"2022-08-11T11:00:44+02:00","admin_graphql_api_id":"gid://shopify/Metafield/23003807973624"},{"id":"23003808006392","namespace":"global","key":"0015","value":"{\"value\":20.0,\"unit\":\"ml\"}","type":"volume","owner_id":"37914747175160","owner_resource":"product_image","created_at":"2022-08-11T11:00:44+02:00","updated_at":"2022-08-11T11:00:44+02:00","admin_graphql_api_id":"gid://shopify/Metafield/23003808006392"},{"id":"23003808039160","namespace":"global","key":"0016","value":"{\"value\":20.5,\"unit\":\"cm\"}","type":"dimension","owner_id":"37914747175160","owner_resource":"product_image","created_at":"2022-08-11T11:00:44+02:00","updated_at":"2022-08-11T11:00:44+02:00","admin_graphql_api_id":"gid://shopify/Metafield/23003808039160"},{"id":"23003808071928","namespace":"global","key":"0017","value":"{\"scale_min\":\"1.0\",\"scale_max\":\"5.0\",\"value\":\"3.5\"}","type":"rating","owner_id":"37914747175160","owner_resource":"product_image","created_at":"2022-08-11T11:00:44+02:00","updated_at":"2022-08-11T11:00:44+02:00","admin_graphql_api_id":"gid://shopify/Metafield/23003808071928"}],"created_at":"2022-08-11T09:00:44+00:00","updated_at":"2022-08-11T11:00:48+02:00","admin_graphql_api_id":"gid://shopify/ProductImage/37914747175160"}],"variants":[{"id":"43140220518648","barcode":"81332151","compare_at_price":"567.73","title":"Fresh / fuchsia / quidem","fulfillment_service":"manual","grams":"27301","image_id":"37914747011320","inventory_management":"shopify","inventory_policy":"deny","inventory_quantity":"0","metafields":[{"id":"23003808203000","namespace":"global","key":"0000","value":"This item contains dairy products.","type":"single_line_text_field","owner_id":"43140220518648","owner_resource":"variant","created_at":"2022-08-11T11:00:45+02:00","updated_at":"2022-08-11T11:00:45+02:00","admin_graphql_api_id":"gid://shopify/Metafield/23003808203000"},{"id":"23003808235768","namespace":"global","key":"0001","value":"Ingredients: \r\nFlour \r\nWater \r\nMilk \r\nEggs","type":"multi_line_text_field","owner_id":"43140220518648","owner_resource":"variant","created_at":"2022-08-11T11:00:45+02:00","updated_at":"2022-08-11T11:00:45+02:00","admin_graphql_api_id":"gid://shopify/Metafield/23003808235768"},{"id":"23003808268536","namespace":"global","key":"0002","value":"gid://shopify/OnlineStorePage/1","type":"page_reference","owner_id":"43140220518648","owner_resource":"variant","created_at":"2022-08-11T11:00:45+02:00","updated_at":"2022-08-11T11:00:45+02:00","admin_graphql_api_id":"gid://shopify/Metafield/23003808268536"},{"id":"23003808301304","namespace":"global","key":"0003","value":"gid://shopify/Product/1","type":"product_reference","owner_id":"43140220518648","owner_resource":"variant","created_at":"2022-08-11T11:00:45+02:00","updated_at":"2022-08-11T11:00:45+02:00","admin_graphql_api_id":"gid://shopify/Metafield/23003808301304"},{"id":"23003808334072","namespace":"global","key":"0004","value":"gid://shopify/ProductVariant/1","type":"variant_reference","owner_id":"43140220518648","owner_resource":"variant","created_at":"2022-08-11T11:00:45+02:00","updated_at":"2022-08-11T11:00:45+02:00","admin_graphql_api_id":"gid://shopify/Metafield/23003808334072"},{"id":"23003808366840","namespace":"global","key":"0005","value":"gid://shopify/MediaImage/123","type":"file_reference","owner_id":"43140220518648","owner_resource":"variant","created_at":"2022-08-11T11:00:45+02:00","updated_at":"2022-08-11T11:00:45+02:00","admin_graphql_api_id":"gid://shopify/Metafield/23003808366840"},{"id":"23003808399608","namespace":"global","key":"0006","value":"10","type":"number_integer","owner_id":"43140220518648","owner_resource":"variant","created_at":"2022-08-11T11:00:45+02:00","updated_at":"2022-08-11T11:00:45+02:00","admin_graphql_api_id":"gid://shopify/Metafield/23003808399608"},{"id":"23003808432376","namespace":"global","key":"0007","value":"10.4","type":"number_decimal","owner_id":"43140220518648","owner_resource":"variant","created_at":"2022-08-11T11:00:45+02:00","updated_at":"2022-08-11T11:00:45+02:00","admin_graphql_api_id":"gid://shopify/Metafield/23003808432376"},{"id":"23003808465144","namespace":"global","key":"0008","value":"2021-02-02","type":"date","owner_id":"43140220518648","owner_resource":"variant","created_at":"2022-08-11T11:00:45+02:00","updated_at":"2022-08-11T11:00:45+02:00","admin_graphql_api_id":"gid://shopify/Metafield/23003808465144"},{"id":"23003808497912","namespace":"global","key":"0009","value":"2021-01-01T12:30:00+00:00","type":"date_time","owner_id":"43140220518648","owner_resource":"variant","created_at":"2022-08-11T11:00:45+02:00","updated_at":"2022-08-11T11:00:45+02:00","admin_graphql_api_id":"gid://shopify/Metafield/23003808497912"},{"id":"23003808530680","namespace":"global","key":"0010","value":"https://www.shopify.com","type":"url","owner_id":"43140220518648","owner_resource":"variant","created_at":"2022-08-11T11:00:45+02:00","updated_at":"2022-08-11T11:00:45+02:00","admin_graphql_api_id":"gid://shopify/Metafield/23003808530680"},{"id":"23003808563448","namespace":"global","key":"0011","value":"[{\"k\":\"v1\"},{\"k\":\"v2\"}]","type":"json","owner_id":"43140220518648","owner_resource":"variant","created_at":"2022-08-11T11:00:45+02:00","updated_at":"2022-08-11T11:00:45+02:00","admin_graphql_api_id":"gid://shopify/Metafield/23003808563448"},{"id":"23003808596216","namespace":"global","key":"0012","value":"true","type":"boolean","owner_id":"43140220518648","owner_resource":"variant","created_at":"2022-08-11T11:00:45+02:00","updated_at":"2022-08-11T11:00:45+02:00","admin_graphql_api_id":"gid://shopify/Metafield/23003808596216"},{"id":"23003808628984","namespace":"global","key":"0013","value":"#fff123","type":"color","owner_id":"43140220518648","owner_resource":"variant","created_at":"2022-08-11T11:00:45+02:00","updated_at":"2022-08-11T11:00:45+02:00","admin_graphql_api_id":"gid://shopify/Metafield/23003808628984"},{"id":"23003808661752","namespace":"global","key":"0014","value":"{\"value\":2.5,\"unit\":\"kg\"}","type":"weight","owner_id":"43140220518648","owner_resource":"variant","created_at":"2022-08-11T11:00:45+02:00","updated_at":"2022-08-11T11:00:45+02:00","admin_graphql_api_id":"gid://shopify/Metafield/23003808661752"},{"id":"23003808694520","namespace":"global","key":"0015","value":"{\"value\":20.0,\"unit\":\"ml\"}","type":"volume","owner_id":"43140220518648","owner_resource":"variant","created_at":"2022-08-11T11:00:45+02:00","updated_at":"2022-08-11T11:00:45+02:00","admin_graphql_api_id":"gid://shopify/Metafield/23003808694520"},{"id":"23003808727288","namespace":"global","key":"0016","value":"{\"value\":20.5,\"unit\":\"cm\"}","type":"dimension","owner_id":"43140220518648","owner_resource":"variant","created_at":"2022-08-11T11:00:45+02:00","updated_at":"2022-08-11T11:00:45+02:00","admin_graphql_api_id":"gid://shopify/Metafield/23003808727288"},{"id":"23003808760056","namespace":"global","key":"0017","value":"{\"scale_min\":\"1.0\",\"scale_max\":\"5.0\",\"value\":\"3.5\"}","type":"rating","owner_id":"43140220518648","owner_resource":"variant","created_at":"2022-08-11T11:00:45+02:00","updated_at":"2022-08-11T11:00:45+02:00","admin_graphql_api_id":"gid://shopify/Metafield/23003808760056"}],"option1":"Fresh","option2":"fuchsia","option3":"quidem","position":"1","product_id":"7776963264760","sku":"5558913293361","taxable":"false","weight":"963.0","weight_unit":"oz","price":"852.49","updated_at":"2022-08-11T11:00:51+02:00","created_at":"2022-08-11T11:00:45+02:00","inventory_item_id":"45234792104184","admin_graphql_api_id":"gid://shopify/ProductVariant/43140220518648"},{"id":"43140220551416","barcode":"63582673","compare_at_price":"918.82","title":"Concrete / silver / hic","fulfillment_service":"manual","grams":"23218","image_id":"37914747076856","inventory_management":"shopify","inventory_policy":"deny","inventory_quantity":"0","metafields":[{"id":"23003808792824","namespace":"global","key":"0000","value":"This item contains dairy products.","type":"single_line_text_field","owner_id":"43140220551416","owner_resource":"variant","created_at":"2022-08-11T11:00:45+02:00","updated_at":"2022-08-11T11:00:45+02:00","admin_graphql_api_id":"gid://shopify/Metafield/23003808792824"},{"id":"23003808825592","namespace":"global","key":"0001","value":"Ingredients: \r\nFlour \r\nWater \r\nMilk \r\nEggs","type":"multi_line_text_field","owner_id":"43140220551416","owner_resource":"variant","created_at":"2022-08-11T11:00:45+02:00","updated_at":"2022-08-11T11:00:45+02:00","admin_graphql_api_id":"gid://shopify/Metafield/23003808825592"},{"id":"23003808858360","namespace":"global","key":"0002","value":"gid://shopify/OnlineStorePage/1","type":"page_reference","owner_id":"43140220551416","owner_resource":"variant","created_at":"2022-08-11T11:00:45+02:00","updated_at":"2022-08-11T11:00:45+02:00","admin_graphql_api_id":"gid://shopify/Metafield/23003808858360"},{"id":"23003808891128","namespace":"global","key":"0003","value":"gid://shopify/Product/1","type":"product_reference","owner_id":"43140220551416","owner_resource":"variant","created_at":"2022-08-11T11:00:45+02:00","updated_at":"2022-08-11T11:00:45+02:00","admin_graphql_api_id":"gid://shopify/Metafield/23003808891128"},{"id":"23003808923896","namespace":"global","key":"0004","value":"gid://shopify/ProductVariant/1","type":"variant_reference","owner_id":"43140220551416","owner_resource":"variant","created_at":"2022-08-11T11:00:45+02:00","updated_at":"2022-08-11T11:00:45+02:00","admin_graphql_api_id":"gid://shopify/Metafield/23003808923896"},{"id":"23003808956664","namespace":"global","key":"0005","value":"gid://shopify/MediaImage/123","type":"file_reference","owner_id":"43140220551416","owner_resource":"variant","created_at":"2022-08-11T11:00:45+02:00","updated_at":"2022-08-11T11:00:45+02:00","admin_graphql_api_id":"gid://shopify/Metafield/23003808956664"},{"id":"23003808989432","namespace":"global","key":"0006","value":"10","type":"number_integer","owner_id":"43140220551416","owner_resource":"variant","created_at":"2022-08-11T11:00:45+02:00","updated_at":"2022-08-11T11:00:45+02:00","admin_graphql_api_id":"gid://shopify/Metafield/23003808989432"},{"id":"23003809022200","namespace":"global","key":"0007","value":"10.4","type":"number_decimal","owner_id":"43140220551416","owner_resource":"variant","created_at":"2022-08-11T11:00:45+02:00","updated_at":"2022-08-11T11:00:45+02:00","admin_graphql_api_id":"gid://shopify/Metafield/23003809022200"},{"id":"23003809054968","namespace":"global","key":"0008","value":"2021-02-02","type":"date","owner_id":"43140220551416","owner_resource":"variant","created_at":"2022-08-11T11:00:45+02:00","updated_at":"2022-08-11T11:00:45+02:00","admin_graphql_api_id":"gid://shopify/Metafield/23003809054968"},{"id":"23003809087736","namespace":"global","key":"0009","value":"2021-01-01T12:30:00+00:00","type":"date_time","owner_id":"43140220551416","owner_resource":"variant","created_at":"2022-08-11T11:00:45+02:00","updated_at":"2022-08-11T11:00:45+02:00","admin_graphql_api_id":"gid://shopify/Metafield/23003809087736"},{"id":"23003809120504","namespace":"global","key":"0010","value":"https://www.shopify.com","type":"url","owner_id":"43140220551416","owner_resource":"variant","created_at":"2022-08-11T11:00:45+02:00","updated_at":"2022-08-11T11:00:45+02:00","admin_graphql_api_id":"gid://shopify/Metafield/23003809120504"},{"id":"23003809153272","namespace":"global","key":"0011","value":"[{\"k\":\"v1\"},{\"k\":\"v2\"}]","type":"json","owner_id":"43140220551416","owner_resource":"variant","created_at":"2022-08-11T11:00:45+02:00","updated_at":"2022-08-11T11:00:45+02:00","admin_graphql_api_id":"gid://shopify/Metafield/23003809153272"},{"id":"23003809186040","namespace":"global","key":"0012","value":"true","type":"boolean","owner_id":"43140220551416","owner_resource":"variant","created_at":"2022-08-11T11:00:45+02:00","updated_at":"2022-08-11T11:00:45+02:00","admin_graphql_api_id":"gid://shopify/Metafield/23003809186040"},{"id":"23003809218808","namespace":"global","key":"0013","value":"#fff123","type":"color","owner_id":"43140220551416","owner_resource":"variant","created_at":"2022-08-11T11:00:45+02:00","updated_at":"2022-08-11T11:00:45+02:00","admin_graphql_api_id":"gid://shopify/Metafield/23003809218808"},{"id":"23003809251576","namespace":"global","key":"0014","value":"{\"value\":2.5,\"unit\":\"kg\"}","type":"weight","owner_id":"43140220551416","owner_resource":"variant","created_at":"2022-08-11T11:00:45+02:00","updated_at":"2022-08-11T11:00:45+02:00","admin_graphql_api_id":"gid://shopify/Metafield/23003809251576"},{"id":"23003809284344","namespace":"global","key":"0015","value":"{\"value\":20.0,\"unit\":\"ml\"}","type":"volume","owner_id":"43140220551416","owner_resource":"variant","created_at":"2022-08-11T11:00:45+02:00","updated_at":"2022-08-11T11:00:45+02:00","admin_graphql_api_id":"gid://shopify/Metafield/23003809284344"},{"id":"23003809317112","namespace":"global","key":"0016","value":"{\"value\":20.5,\"unit\":\"cm\"}","type":"dimension","owner_id":"43140220551416","owner_resource":"variant","created_at":"2022-08-11T11:00:45+02:00","updated_at":"2022-08-11T11:00:45+02:00","admin_graphql_api_id":"gid://shopify/Metafield/23003809317112"},{"id":"23003809349880","namespace":"global","key":"0017","value":"{\"scale_min\":\"1.0\",\"scale_max\":\"5.0\",\"value\":\"3.5\"}","type":"rating","owner_id":"43140220551416","owner_resource":"variant","created_at":"2022-08-11T11:00:45+02:00","updated_at":"2022-08-11T11:00:45+02:00","admin_graphql_api_id":"gid://shopify/Metafield/23003809349880"}],"option1":"Concrete","option2":"silver","option3":"hic","position":"2","product_id":"7776963264760","sku":"6287436448062","taxable":"false","weight":"819.0","weight_unit":"oz","price":"949.87","updated_at":"2022-08-11T11:00:51+02:00","created_at":"2022-08-11T11:00:45+02:00","inventory_item_id":"45234792136952","admin_graphql_api_id":"gid://shopify/ProductVariant/43140220551416"},{"id":"43140220584184","barcode":"73396215","compare_at_price":"994.36","title":"Plastic / maroon / assumenda","fulfillment_service":"manual","grams":"24494","image_id":"37914747109624","inventory_management":"shopify","inventory_policy":"deny","inventory_quantity":"0","metafields":[{"id":"23003809382648","namespace":"global","key":"0000","value":"This item contains dairy products.","type":"single_line_text_field","owner_id":"43140220584184","owner_resource":"variant","created_at":"2022-08-11T11:00:45+02:00","updated_at":"2022-08-11T11:00:45+02:00","admin_graphql_api_id":"gid://shopify/Metafield/23003809382648"},{"id":"23003809415416","namespace":"global","key":"0001","value":"Ingredients: \r\nFlour \r\nWater \r\nMilk \r\nEggs","type":"multi_line_text_field","owner_id":"43140220584184","owner_resource":"variant","created_at":"2022-08-11T11:00:45+02:00","updated_at":"2022-08-11T11:00:45+02:00","admin_graphql_api_id":"gid://shopify/Metafield/23003809415416"},{"id":"23003809448184","namespace":"global","key":"0002","value":"gid://shopify/OnlineStorePage/1","type":"page_reference","owner_id":"43140220584184","owner_resource":"variant","created_at":"2022-08-11T11:00:45+02:00","updated_at":"2022-08-11T11:00:45+02:00","admin_graphql_api_id":"gid://shopify/Metafield/23003809448184"},{"id":"23003809480952","namespace":"global","key":"0003","value":"gid://shopify/Product/1","type":"product_reference","owner_id":"43140220584184","owner_resource":"variant","created_at":"2022-08-11T11:00:45+02:00","updated_at":"2022-08-11T11:00:45+02:00","admin_graphql_api_id":"gid://shopify/Metafield/23003809480952"},{"id":"23003809513720","namespace":"global","key":"0004","value":"gid://shopify/ProductVariant/1","type":"variant_reference","owner_id":"43140220584184","owner_resource":"variant","created_at":"2022-08-11T11:00:45+02:00","updated_at":"2022-08-11T11:00:45+02:00","admin_graphql_api_id":"gid://shopify/Metafield/23003809513720"},{"id":"23003809546488","namespace":"global","key":"0005","value":"gid://shopify/MediaImage/123","type":"file_reference","owner_id":"43140220584184","owner_resource":"variant","created_at":"2022-08-11T11:00:45+02:00","updated_at":"2022-08-11T11:00:45+02:00","admin_graphql_api_id":"gid://shopify/Metafield/23003809546488"},{"id":"23003809579256","namespace":"global","key":"0006","value":"10","type":"number_integer","owner_id":"43140220584184","owner_resource":"variant","created_at":"2022-08-11T11:00:45+02:00","updated_at":"2022-08-11T11:00:45+02:00","admin_graphql_api_id":"gid://shopify/Metafield/23003809579256"},{"id":"23003809612024","namespace":"global","key":"0007","value":"10.4","type":"number_decimal","owner_id":"43140220584184","owner_resource":"variant","created_at":"2022-08-11T11:00:45+02:00","updated_at":"2022-08-11T11:00:45+02:00","admin_graphql_api_id":"gid://shopify/Metafield/23003809612024"},{"id":"23003809644792","namespace":"global","key":"0008","value":"2021-02-02","type":"date","owner_id":"43140220584184","owner_resource":"variant","created_at":"2022-08-11T11:00:45+02:00","updated_at":"2022-08-11T11:00:45+02:00","admin_graphql_api_id":"gid://shopify/Metafield/23003809644792"},{"id":"23003809677560","namespace":"global","key":"0009","value":"2021-01-01T12:30:00+00:00","type":"date_time","owner_id":"43140220584184","owner_resource":"variant","created_at":"2022-08-11T11:00:45+02:00","updated_at":"2022-08-11T11:00:45+02:00","admin_graphql_api_id":"gid://shopify/Metafield/23003809677560"},{"id":"23003809710328","namespace":"global","key":"0010","value":"https://www.shopify.com","type":"url","owner_id":"43140220584184","owner_resource":"variant","created_at":"2022-08-11T11:00:45+02:00","updated_at":"2022-08-11T11:00:45+02:00","admin_graphql_api_id":"gid://shopify/Metafield/23003809710328"},{"id":"23003809743096","namespace":"global","key":"0011","value":"[{\"k\":\"v1\"},{\"k\":\"v2\"}]","type":"json","owner_id":"43140220584184","owner_resource":"variant","created_at":"2022-08-11T11:00:45+02:00","updated_at":"2022-08-11T11:00:45+02:00","admin_graphql_api_id":"gid://shopify/Metafield/23003809743096"},{"id":"23003809775864","namespace":"global","key":"0012","value":"true","type":"boolean","owner_id":"43140220584184","owner_resource":"variant","created_at":"2022-08-11T11:00:45+02:00","updated_at":"2022-08-11T11:00:45+02:00","admin_graphql_api_id":"gid://shopify/Metafield/23003809775864"},{"id":"23003809808632","namespace":"global","key":"0013","value":"#fff123","type":"color","owner_id":"43140220584184","owner_resource":"variant","created_at":"2022-08-11T11:00:45+02:00","updated_at":"2022-08-11T11:00:45+02:00","admin_graphql_api_id":"gid://shopify/Metafield/23003809808632"},{"id":"23003809841400","namespace":"global","key":"0014","value":"{\"value\":2.5,\"unit\":\"kg\"}","type":"weight","owner_id":"43140220584184","owner_resource":"variant","created_at":"2022-08-11T11:00:45+02:00","updated_at":"2022-08-11T11:00:45+02:00","admin_graphql_api_id":"gid://shopify/Metafield/23003809841400"},{"id":"23003809874168","namespace":"global","key":"0015","value":"{\"value\":20.0,\"unit\":\"ml\"}","type":"volume","owner_id":"43140220584184","owner_resource":"variant","created_at":"2022-08-11T11:00:45+02:00","updated_at":"2022-08-11T11:00:45+02:00","admin_graphql_api_id":"gid://shopify/Metafield/23003809874168"},{"id":"23003809906936","namespace":"global","key":"0016","value":"{\"value\":20.5,\"unit\":\"cm\"}","type":"dimension","owner_id":"43140220584184","owner_resource":"variant","created_at":"2022-08-11T11:00:45+02:00","updated_at":"2022-08-11T11:00:45+02:00","admin_graphql_api_id":"gid://shopify/Metafield/23003809906936"},{"id":"23003809939704","namespace":"global","key":"0017","value":"{\"scale_min\":\"1.0\",\"scale_max\":\"5.0\",\"value\":\"3.5\"}","type":"rating","owner_id":"43140220584184","owner_resource":"variant","created_at":"2022-08-11T11:00:45+02:00","updated_at":"2022-08-11T11:00:45+02:00","admin_graphql_api_id":"gid://shopify/Metafield/23003809939704"}],"option1":"Plastic","option2":"maroon","option3":"assumenda","position":"3","product_id":"7776963264760","sku":"6234320584887","taxable":"false","weight":"864.0","weight_unit":"oz","price":"610.00","updated_at":"2022-08-11T11:00:51+02:00","created_at":"2022-08-11T11:00:45+02:00","inventory_item_id":"45234792169720","admin_graphql_api_id":"gid://shopify/ProductVariant/43140220584184"}],"metafields":[{"id":"23003809972472","namespace":"global","key":"description_tag","value":"aliquid","type":"string","owner_id":"7776963264760","owner_resource":"product","created_at":"2022-08-11T11:00:45+02:00","updated_at":"2022-08-11T11:00:45+02:00","admin_graphql_api_id":"gid://shopify/Metafield/23003809972472"},{"id":"23003810005240","namespace":"global","key":"title_tag","value":"eaque","type":"string","owner_id":"7776963264760","owner_resource":"product","created_at":"2022-08-11T11:00:45+02:00","updated_at":"2022-08-11T11:00:45+02:00","admin_graphql_api_id":"gid://shopify/Metafield/23003810005240"},{"id":"23003810038008","namespace":"global","key":"0000","value":"This item contains dairy products.","type":"single_line_text_field","owner_id":"7776963264760","owner_resource":"product","created_at":"2022-08-11T11:00:45+02:00","updated_at":"2022-08-11T11:00:45+02:00","admin_graphql_api_id":"gid://shopify/Metafield/23003810038008"},{"id":"23003810070776","namespace":"global","key":"0001","value":"Ingredients: \r\nFlour \r\nWater \r\nMilk \r\nEggs","type":"multi_line_text_field","owner_id":"7776963264760","owner_resource":"product","created_at":"2022-08-11T11:00:45+02:00","updated_at":"2022-08-11T11:00:45+02:00","admin_graphql_api_id":"gid://shopify/Metafield/23003810070776"},{"id":"23003810136312","namespace":"global","key":"0002","value":"gid://shopify/OnlineStorePage/1","type":"page_reference","owner_id":"7776963264760","owner_resource":"product","created_at":"2022-08-11T11:00:45+02:00","updated_at":"2022-08-11T11:00:45+02:00","admin_graphql_api_id":"gid://shopify/Metafield/23003810136312"},{"id":"23003810169080","namespace":"global","key":"0003","value":"gid://shopify/Product/1","type":"product_reference","owner_id":"7776963264760","owner_resource":"product","created_at":"2022-08-11T11:00:45+02:00","updated_at":"2022-08-11T11:00:45+02:00","admin_graphql_api_id":"gid://shopify/Metafield/23003810169080"},{"id":"23003810201848","namespace":"global","key":"0004","value":"gid://shopify/ProductVariant/1","type":"variant_reference","owner_id":"7776963264760","owner_resource":"product","created_at":"2022-08-11T11:00:45+02:00","updated_at":"2022-08-11T11:00:45+02:00","admin_graphql_api_id":"gid://shopify/Metafield/23003810201848"},{"id":"23003810234616","namespace":"global","key":"0005","value":"gid://shopify/MediaImage/123","type":"file_reference","owner_id":"7776963264760","owner_resource":"product","created_at":"2022-08-11T11:00:45+02:00","updated_at":"2022-08-11T11:00:45+02:00","admin_graphql_api_id":"gid://shopify/Metafield/23003810234616"},{"id":"23003810267384","namespace":"global","key":"0006","value":"10","type":"number_integer","owner_id":"7776963264760","owner_resource":"product","created_at":"2022-08-11T11:00:45+02:00","updated_at":"2022-08-11T11:00:45+02:00","admin_graphql_api_id":"gid://shopify/Metafield/23003810267384"},{"id":"23003810300152","namespace":"global","key":"0007","value":"10.4","type":"number_decimal","owner_id":"7776963264760","owner_resource":"product","created_at":"2022-08-11T11:00:45+02:00","updated_at":"2022-08-11T11:00:45+02:00","admin_graphql_api_id":"gid://shopify/Metafield/23003810300152"},{"id":"23003810332920","namespace":"global","key":"0008","value":"2021-02-02","type":"date","owner_id":"7776963264760","owner_resource":"product","created_at":"2022-08-11T11:00:45+02:00","updated_at":"2022-08-11T11:00:45+02:00","admin_graphql_api_id":"gid://shopify/Metafield/23003810332920"},{"id":"23003810365688","namespace":"global","key":"0009","value":"2021-01-01T12:30:00+00:00","type":"date_time","owner_id":"7776963264760","owner_resource":"product","created_at":"2022-08-11T11:00:45+02:00","updated_at":"2022-08-11T11:00:45+02:00","admin_graphql_api_id":"gid://shopify/Metafield/23003810365688"},{"id":"23003810398456","namespace":"global","key":"0010","value":"https://www.shopify.com","type":"url","owner_id":"7776963264760","owner_resource":"product","created_at":"2022-08-11T11:00:45+02:00","updated_at":"2022-08-11T11:00:45+02:00","admin_graphql_api_id":"gid://shopify/Metafield/23003810398456"},{"id":"23003810431224","namespace":"global","key":"0011","value":"[{\"k\":\"v1\"},{\"k\":\"v2\"}]","type":"json","owner_id":"7776963264760","owner_resource":"product","created_at":"2022-08-11T11:00:45+02:00","updated_at":"2022-08-11T11:00:45+02:00","admin_graphql_api_id":"gid://shopify/Metafield/23003810431224"},{"id":"23003810463992","namespace":"global","key":"0012","value":"true","type":"boolean","owner_id":"7776963264760","owner_resource":"product","created_at":"2022-08-11T11:00:45+02:00","updated_at":"2022-08-11T11:00:45+02:00","admin_graphql_api_id":"gid://shopify/Metafield/23003810463992"},{"id":"23003810496760","namespace":"global","key":"0013","value":"#fff123","type":"color","owner_id":"7776963264760","owner_resource":"product","created_at":"2022-08-11T11:00:45+02:00","updated_at":"2022-08-11T11:00:45+02:00","admin_graphql_api_id":"gid://shopify/Metafield/23003810496760"},{"id":"23003810529528","namespace":"global","key":"0014","value":"{\"value\":2.5,\"unit\":\"kg\"}","type":"weight","owner_id":"7776963264760","owner_resource":"product","created_at":"2022-08-11T11:00:45+02:00","updated_at":"2022-08-11T11:00:45+02:00","admin_graphql_api_id":"gid://shopify/Metafield/23003810529528"},{"id":"23003810562296","namespace":"global","key":"0015","value":"{\"value\":20.0,\"unit\":\"ml\"}","type":"volume","owner_id":"7776963264760","owner_resource":"product","created_at":"2022-08-11T11:00:45+02:00","updated_at":"2022-08-11T11:00:45+02:00","admin_graphql_api_id":"gid://shopify/Metafield/23003810562296"},{"id":"23003810595064","namespace":"global","key":"0016","value":"{\"value\":20.5,\"unit\":\"cm\"}","type":"dimension","owner_id":"7776963264760","owner_resource":"product","created_at":"2022-08-11T11:00:45+02:00","updated_at":"2022-08-11T11:00:45+02:00","admin_graphql_api_id":"gid://shopify/Metafield/23003810595064"},{"id":"23003810627832","namespace":"global","key":"0017","value":"{\"scale_min\":\"1.0\",\"scale_max\":\"5.0\",\"value\":\"3.5\"}","type":"rating","owner_id":"7776963264760","owner_resource":"product","created_at":"2022-08-11T11:00:45+02:00","updated_at":"2022-08-11T11:00:45+02:00","admin_graphql_api_id":"gid://shopify/Metafield/23003810627832"}],"admin_graphql_api_id":"gid://shopify/Product/7776963264760"}