{"id":"7776971129080","title":"Sleek Concrete Chair","handle":"similique-saepe-repellendus","status":"active","options":[{"id":"9863873331448","product_id":"7776971129080","name":"Size","position":"1","values":["Frozen","Fresh","Metal"]},{"id":"9863873364216","product_id":"7776971129080","name":"Color","position":"2","values":["lime","cyan","olive"]},{"id":"9863873396984","product_id":"7776971129080","name":"Fabric","position":"3","values":["velit","non","assumenda"]}],"body_html":"New ABC 13 9370, 13.3, 5th Gen CoreA5-8250U, 8GB RAM, 256GB SSD, power UHD Graphics, OS 10 Home, OS Office A &amp; J 2016","tags":"placeat","product_type":"ut","ProductTypes":{"Id":null,"StandardizedProductType":{"ProductTaxonomyNode":{"Id":"gid://shopify/ProductTaxonomyNode/1192","FullName":"Cameras & Optics > Camera & Optic Accessories > Camera Parts & Accessories > Camera Replacement Screens & Displays","Name":"Camera Replacement Screens & Displays"}},"CustomProductType":"ut"},"vendor":"autem","published_at":"2022-07-30T23:47:49+00:00","published_scope":"web","updated_at":"2022-08-11T11:07:52+02:00","created_at":"2022-08-11T11:07:45+02:00","image":{"id":"37914779091192","product_id":"7776971129080","position":1,"src":"https://cdn.shopify.com/s/files/1/0549/3132/5176/products/games___home_credit_card_account_locks.jpg?v=1660208868","width":"128","height":"128","variant_ids":["43140237361400"],"created_at":"2022-08-11T09:07:45+00:00","updated_at":"2022-08-11T11:07:48+02:00","admin_graphql_api_id":"gid://shopify/ProductImage/37914779091192"},"images":[{"id":"37914779091192","product_id":"7776971129080","position":1,"src":"https://cdn.shopify.com/s/files/1/0549/3132/5176/products/games___home_credit_card_account_locks.jpg?v=1660208868","filename":"games___home_credit_card_account_locks.jpg","width":"128","height":"128","variant_ids":["43140237361400"],"metafields":[{"id":"23003949760760","namespace":"global","key":"0000","value":"This item contains dairy products.","type":"multi_line_text_field","owner_id":"37914779091192","owner_resource":"product_image","created_at":"2022-08-11T11:07:45+02:00","updated_at":"2022-08-11T11:07:45+02:00","admin_graphql_api_id":"gid://shopify/Metafield/23003949760760"},{"id":"23003949793528","namespace":"global","key":"0001","value":"Ingredients: \r\nFlour \r\nWater \r\nMilk \r\nEggs","type":"multi_line_text_field","owner_id":"37914779091192","owner_resource":"product_image","created_at":"2022-08-11T11:07:45+02:00","updated_at":"2022-08-11T11:07:45+02:00","admin_graphql_api_id":"gid://shopify/Metafield/23003949793528"},{"id":"23003949826296","namespace":"global","key":"0002","value":"gid://shopify/OnlineStorePage/1","type":"multi_line_text_field","owner_id":"37914779091192","owner_resource":"product_image","created_at":"2022-08-11T11:07:45+02:00","updated_at":"2022-08-11T11:07:45+02:00","admin_graphql_api_id":"gid://shopify/Metafield/23003949826296"},{"id":"23003949859064","namespace":"global","key":"0003","value":"gid://shopify/Product/1","type":"multi_line_text_field","owner_id":"37914779091192","owner_resource":"product_image","created_at":"2022-08-11T11:07:45+02:00","updated_at":"2022-08-11T11:07:45+02:00","admin_graphql_api_id":"gid://shopify/Metafield/23003949859064"},{"id":"23003949891832","namespace":"global","key":"0004","value":"gid://shopify/ProductVariant/1","type":"multi_line_text_field","owner_id":"37914779091192","owner_resource":"product_image","created_at":"2022-08-11T11:07:45+02:00","updated_at":"2022-08-11T11:07:45+02:00","admin_graphql_api_id":"gid://shopify/Metafield/23003949891832"},{"id":"23003949924600","namespace":"global","key":"0005","value":"gid://shopify/MediaImage/123","type":"multi_line_text_field","owner_id":"37914779091192","owner_resource":"product_image","created_at":"2022-08-11T11:07:45+02:00","updated_at":"2022-08-11T11:07:45+02:00","admin_graphql_api_id":"gid://shopify/Metafield/23003949924600"},{"id":"23003949957368","namespace":"global","key":"0006","value":"10","type":"number_integer","owner_id":"37914779091192","owner_resource":"product_image","created_at":"2022-08-11T11:07:45+02:00","updated_at":"2022-08-11T11:07:45+02:00","admin_graphql_api_id":"gid://shopify/Metafield/23003949957368"},{"id":"23003949990136","namespace":"global","key":"0007","value":"10.4","type":"multi_line_text_field","owner_id":"37914779091192","owner_resource":"product_image","created_at":"2022-08-11T11:07:45+02:00","updated_at":"2022-08-11T11:07:45+02:00","admin_graphql_api_id":"gid://shopify/Metafield/23003949990136"},{"id":"23003950022904","namespace":"global","key":"0008","value":"2021-02-02","type":"multi_line_text_field","owner_id":"37914779091192","owner_resource":"product_image","created_at":"2022-08-11T11:07:45+02:00","updated_at":"2022-08-11T11:07:45+02:00","admin_graphql_api_id":"gid://shopify/Metafield/23003950022904"},{"id":"23003950055672","namespace":"global","key":"0009","value":"2021-01-01T12:30:00+00:00","type":"multi_line_text_field","owner_id":"37914779091192","owner_resource":"product_image","created_at":"2022-08-11T11:07:45+02:00","updated_at":"2022-08-11T11:07:45+02:00","admin_graphql_api_id":"gid://shopify/Metafield/23003950055672"},{"id":"23003950088440","namespace":"global","key":"0010","value":"https://www.shopify.com","type":"multi_line_text_field","owner_id":"37914779091192","owner_resource":"product_image","created_at":"2022-08-11T11:07:45+02:00","updated_at":"2022-08-11T11:07:45+02:00","admin_graphql_api_id":"gid://shopify/Metafield/23003950088440"},{"id":"23003950121208","namespace":"global","key":"0011","value":"[{\"k\":\"v1\"},{\"k\":\"v2\"}]","type":"json","owner_id":"37914779091192","owner_resource":"product_image","created_at":"2022-08-11T11:07:45+02:00","updated_at":"2022-08-11T11:07:45+02:00","admin_graphql_api_id":"gid://shopify/Metafield/23003950121208"},{"id":"23003950153976","namespace":"global","key":"0012","value":"true","type":"boolean","owner_id":"37914779091192","owner_resource":"product_image","created_at":"2022-08-11T11:07:45+02:00","updated_at":"2022-08-11T11:07:45+02:00","admin_graphql_api_id":"gid://shopify/Metafield/23003950153976"},{"id":"23003950186744","namespace":"global","key":"0013","value":"#fff123","type":"multi_line_text_field","owner_id":"37914779091192","owner_resource":"product_image","created_at":"2022-08-11T11:07:45+02:00","updated_at":"2022-08-11T11:07:45+02:00","admin_graphql_api_id":"gid://shopify/Metafield/23003950186744"},{"id":"23003950219512","namespace":"global","key":"0014","value":"{\"value\":2.5,\"unit\":\"kg\"}","type":"multi_line_text_field","owner_id":"37914779091192","owner_resource":"product_image","created_at":"2022-08-11T11:07:45+02:00","updated_at":"2022-08-11T11:07:45+02:00","admin_graphql_api_id":"gid://shopify/Metafield/23003950219512"},{"id":"23003950252280","namespace":"global","key":"0015","value":"{\"value\":20.0,\"unit\":\"ml\"}","type":"multi_line_text_field","owner_id":"37914779091192","owner_resource":"product_image","created_at":"2022-08-11T11:07:45+02:00","updated_at":"2022-08-11T11:07:45+02:00","admin_graphql_api_id":"gid://shopify/Metafield/23003950252280"},{"id":"23003950285048","namespace":"global","key":"0016","value":"{\"value\":20.5,\"unit\":\"cm\"}","type":"multi_line_text_field","owner_id":"37914779091192","owner_resource":"product_image","created_at":"2022-08-11T11:07:45+02:00","updated_at":"2022-08-11T11:07:45+02:00","admin_graphql_api_id":"gid://shopify/Metafield/23003950285048"},{"id":"23003950317816","namespace":"global","key":"0017","value":"{\"scale_min\":\"1.0\",\"scale_max\":\"5.0\",\"value\":\"3.5\"}","type":"multi_line_text_field","owner_id":"37914779091192","owner_resource":"product_image","created_at":"2022-08-11T11:07:45+02:00","updated_at":"2022-08-11T11:07:45+02:00","admin_graphql_api_id":"gid://shopify/Metafield/23003950317816"}],"created_at":"2022-08-11T09:07:45+00:00","updated_at":"2022-08-11T11:07:48+02:00","admin_graphql_api_id":"gid://shopify/ProductImage/37914779091192"},{"id":"37914779123960","product_id":"7776971129080","position":2,"src":"https://cdn.shopify.com/s/files/1/0549/3132/5176/products/incredible_withdrawal.jpg?v=1660208868","filename":"incredible_withdrawal.jpg","width":"216","height":"216","variant_ids":["43140237394168"],"metafields":[{"id":"23003950383352","namespace":"global","key":"0000","value":"This item contains dairy products.","type":"multi_line_text_field","owner_id":"37914779123960","owner_resource":"product_image","created_at":"2022-08-11T11:07:45+02:00","updated_at":"2022-08-11T11:07:45+02:00","admin_graphql_api_id":"gid://shopify/Metafield/23003950383352"},{"id":"23003950416120","namespace":"global","key":"0001","value":"Ingredients: \r\nFlour \r\nWater \r\nMilk \r\nEggs","type":"multi_line_text_field","owner_id":"37914779123960","owner_resource":"product_image","created_at":"2022-08-11T11:07:45+02:00","updated_at":"2022-08-11T11:07:45+02:00","admin_graphql_api_id":"gid://shopify/Metafield/23003950416120"},{"id":"23003950448888","namespace":"global","key":"0002","value":"gid://shopify/OnlineStorePage/1","type":"multi_line_text_field","owner_id":"37914779123960","owner_resource":"product_image","created_at":"2022-08-11T11:07:45+02:00","updated_at":"2022-08-11T11:07:45+02:00","admin_graphql_api_id":"gid://shopify/Metafield/23003950448888"},{"id":"23003950481656","namespace":"global","key":"0003","value":"gid://shopify/Product/1","type":"multi_line_text_field","owner_id":"37914779123960","owner_resource":"product_image","created_at":"2022-08-11T11:07:45+02:00","updated_at":"2022-08-11T11:07:45+02:00","admin_graphql_api_id":"gid://shopify/Metafield/23003950481656"},{"id":"23003950514424","namespace":"global","key":"0004","value":"gid://shopify/ProductVariant/1","type":"multi_line_text_field","owner_id":"37914779123960","owner_resource":"product_image","created_at":"2022-08-11T11:07:45+02:00","updated_at":"2022-08-11T11:07:45+02:00","admin_graphql_api_id":"gid://shopify/Metafield/23003950514424"},{"id":"23003950547192","namespace":"global","key":"0005","value":"gid://shopify/MediaImage/123","type":"multi_line_text_field","owner_id":"37914779123960","owner_resource":"product_image","created_at":"2022-08-11T11:07:45+02:00","updated_at":"2022-08-11T11:07:45+02:00","admin_graphql_api_id":"gid://shopify/Metafield/23003950547192"},{"id":"23003950579960","namespace":"global","key":"0006","value":"10","type":"number_integer","owner_id":"37914779123960","owner_resource":"product_image","created_at":"2022-08-11T11:07:45+02:00","updated_at":"2022-08-11T11:07:45+02:00","admin_graphql_api_id":"gid://shopify/Metafield/23003950579960"},{"id":"23003950612728","namespace":"global","key":"0007","value":"10.4","type":"multi_line_text_field","owner_id":"37914779123960","owner_resource":"product_image","created_at":"2022-08-11T11:07:45+02:00","updated_at":"2022-08-11T11:07:45+02:00","admin_graphql_api_id":"gid://shopify/Metafield/23003950612728"},{"id":"23003950645496","namespace":"global","key":"0008","value":"2021-02-02","type":"multi_line_text_field","owner_id":"37914779123960","owner_resource":"product_image","created_at":"2022-08-11T11:07:45+02:00","updated_at":"2022-08-11T11:07:45+02:00","admin_graphql_api_id":"gid://shopify/Metafield/23003950645496"},{"id":"23003950678264","namespace":"global","key":"0009","value":"2021-01-01T12:30:00+00:00","type":"multi_line_text_field","owner_id":"37914779123960","owner_resource":"product_image","created_at":"2022-08-11T11:07:45+02:00","updated_at":"2022-08-11T11:07:45+02:00","admin_graphql_api_id":"gid://shopify/Metafield/23003950678264"},{"id":"23003950743800","namespace":"global","key":"0010","value":"https://www.shopify.com","type":"multi_line_text_field","owner_id":"37914779123960","owner_resource":"product_image","created_at":"2022-08-11T11:07:45+02:00","updated_at":"2022-08-11T11:07:45+02:00","admin_graphql_api_id":"gid://shopify/Metafield/23003950743800"},{"id":"23003950776568","namespace":"global","key":"0011","value":"[{\"k\":\"v1\"},{\"k\":\"v2\"}]","type":"json","owner_id":"37914779123960","owner_resource":"product_image","created_at":"2022-08-11T11:07:45+02:00","updated_at":"2022-08-11T11:07:45+02:00","admin_graphql_api_id":"gid://shopify/Metafield/23003950776568"},{"id":"23003950809336","namespace":"global","key":"0012","value":"true","type":"boolean","owner_id":"37914779123960","owner_resource":"product_image","created_at":"2022-08-11T11:07:45+02:00","updated_at":"2022-08-11T11:07:45+02:00","admin_graphql_api_id":"gid://shopify/Metafield/23003950809336"},{"id":"23003950842104","namespace":"global","key":"0013","value":"#fff123","type":"multi_line_text_field","owner_id":"37914779123960","owner_resource":"product_image","created_at":"2022-08-11T11:07:45+02:00","updated_at":"2022-08-11T11:07:45+02:00","admin_graphql_api_id":"gid://shopify/Metafield/23003950842104"},{"id":"23003950874872","namespace":"global","key":"0014","value":"{\"value\":2.5,\"unit\":\"kg\"}","type":"multi_line_text_field","owner_id":"37914779123960","owner_resource":"product_image","created_at":"2022-08-11T11:07:45+02:00","updated_at":"2022-08-11T11:07:45+02:00","admin_graphql_api_id":"gid://shopify/Metafield/23003950874872"},{"id":"23003950907640","namespace":"global","key":"0015","value":"{\"value\":20.0,\"unit\":\"ml\"}","type":"multi_line_text_field","owner_id":"37914779123960","owner_resource":"product_image","created_at":"2022-08-11T11:07:45+02:00","updated_at":"2022-08-11T11:07:45+02:00","admin_graphql_api_id":"gid://shopify/Metafield/23003950907640"},{"id":"23003950940408","namespace":"global","key":"0016","value":"{\"value\":20.5,\"unit\":\"cm\"}","type":"multi_line_text_field","owner_id":"37914779123960","owner_resource":"product_image","created_at":"2022-08-11T11:07:45+02:00","updated_at":"2022-08-11T11:07:45+02:00","admin_graphql_api_id":"gid://shopify/Metafield/23003950940408"},{"id":"23003950973176","namespace":"global","key":"0017","value":"{\"scale_min\":\"1.0\",\"scale_max\":\"5.0\",\"value\":\"3.5\"}","type":"multi_line_text_field","owner_id":"37914779123960","owner_resource":"product_image","created_at":"2022-08-11T11:07:45+02:00","updated_at":"2022-08-11T11:07:45+02:00","admin_graphql_api_id":"gid://shopify/Metafield/23003950973176"}],"created_at":"2022-08-11T09:07:45+00:00","updated_at":"2022-08-11T11:07:48+02:00","admin_graphql_api_id":"gid://shopify/ProductImage/37914779123960"},{"id":"37914779189496","product_id":"7776971129080","position":3,"src":"https://cdn.shopify.com/s/files/1/0549/3132/5176/products/reinvent_utah_system.jpg?v=1660208868","filename":"reinvent_utah_system.jpg","width":"128","height":"128","variant_ids":["43140237426936"],"metafields":[{"id":"23003951005944","namespace":"global","key":"0000","value":"This item contains dairy products.","type":"multi_line_text_field","owner_id":"37914779189496","owner_resource":"product_image","created_at":"2022-08-11T11:07:45+02:00","updated_at":"2022-08-11T11:07:45+02:00","admin_graphql_api_id":"gid://shopify/Metafield/23003951005944"},{"id":"23003951038712","namespace":"global","key":"0001","value":"Ingredients: \r\nFlour \r\nWater \r\nMilk \r\nEggs","type":"multi_line_text_field","owner_id":"37914779189496","owner_resource":"product_image","created_at":"2022-08-11T11:07:45+02:00","updated_at":"2022-08-11T11:07:45+02:00","admin_graphql_api_id":"gid://shopify/Metafield/23003951038712"},{"id":"23003951071480","namespace":"global","key":"0002","value":"gid://shopify/OnlineStorePage/1","type":"multi_line_text_field","owner_id":"37914779189496","owner_resource":"product_image","created_at":"2022-08-11T11:07:45+02:00","updated_at":"2022-08-11T11:07:45+02:00","admin_graphql_api_id":"gid://shopify/Metafield/23003951071480"},{"id":"23003951104248","namespace":"global","key":"0003","value":"gid://shopify/Product/1","type":"multi_line_text_field","owner_id":"37914779189496","owner_resource":"product_image","created_at":"2022-08-11T11:07:45+02:00","updated_at":"2022-08-11T11:07:45+02:00","admin_graphql_api_id":"gid://shopify/Metafield/23003951104248"},{"id":"23003951137016","namespace":"global","key":"0004","value":"gid://shopify/ProductVariant/1","type":"multi_line_text_field","owner_id":"37914779189496","owner_resource":"product_image","created_at":"2022-08-11T11:07:45+02:00","updated_at":"2022-08-11T11:07:45+02:00","admin_graphql_api_id":"gid://shopify/Metafield/23003951137016"},{"id":"23003951169784","namespace":"global","key":"0005","value":"gid://shopify/MediaImage/123","type":"multi_line_text_field","owner_id":"37914779189496","owner_resource":"product_image","created_at":"2022-08-11T11:07:45+02:00","updated_at":"2022-08-11T11:07:45+02:00","admin_graphql_api_id":"gid://shopify/Metafield/23003951169784"},{"id":"23003951202552","namespace":"global","key":"0006","value":"10","type":"number_integer","owner_id":"37914779189496","owner_resource":"product_image","created_at":"2022-08-11T11:07:45+02:00","updated_at":"2022-08-11T11:07:45+02:00","admin_graphql_api_id":"gid://shopify/Metafield/23003951202552"},{"id":"23003951235320","namespace":"global","key":"0007","value":"10.4","type":"multi_line_text_field","owner_id":"37914779189496","owner_resource":"product_image","created_at":"2022-08-11T11:07:45+02:00","updated_at":"2022-08-11T11:07:45+02:00","admin_graphql_api_id":"gid://shopify/Metafield/23003951235320"},{"id":"23003951268088","namespace":"global","key":"0008","value":"2021-02-02","type":"multi_line_text_field","owner_id":"37914779189496","owner_resource":"product_image","created_at":"2022-08-11T11:07:45+02:00","updated_at":"2022-08-11T11:07:45+02:00","admin_graphql_api_id":"gid://shopify/Metafield/23003951268088"},{"id":"23003951300856","namespace":"global","key":"0009","value":"2021-01-01T12:30:00+00:00","type":"multi_line_text_field","owner_id":"37914779189496","owner_resource":"product_image","created_at":"2022-08-11T11:07:45+02:00","updated_at":"2022-08-11T11:07:45+02:00","admin_graphql_api_id":"gid://shopify/Metafield/23003951300856"},{"id":"23003951333624","namespace":"global","key":"0010","value":"https://www.shopify.com","type":"multi_line_text_field","owner_id":"37914779189496","owner_resource":"product_image","created_at":"2022-08-11T11:07:45+02:00","updated_at":"2022-08-11T11:07:45+02:00","admin_graphql_api_id":"gid://shopify/Metafield/23003951333624"},{"id":"23003951366392","namespace":"global","key":"0011","value":"[{\"k\":\"v1\"},{\"k\":\"v2\"}]","type":"json","owner_id":"37914779189496","owner_resource":"product_image","created_at":"2022-08-11T11:07:45+02:00","updated_at":"2022-08-11T11:07:45+02:00","admin_graphql_api_id":"gid://shopify/Metafield/23003951366392"},{"id":"23003951399160","namespace":"global","key":"0012","value":"true","type":"boolean","owner_id":"37914779189496","owner_resource":"product_image","created_at":"2022-08-11T11:07:45+02:00","updated_at":"2022-08-11T11:07:45+02:00","admin_graphql_api_id":"gid://shopify/Metafield/23003951399160"},{"id":"23003951431928","namespace":"global","key":"0013","value":"#fff123","type":"multi_line_text_field","owner_id":"37914779189496","owner_resource":"product_image","created_at":"2022-08-11T11:07:45+02:00","updated_at":"2022-08-11T11:07:45+02:00","admin_graphql_api_id":"gid://shopify/Metafield/23003951431928"},{"id":"23003951464696","namespace":"global","key":"0014","value":"{\"value\":2.5,\"unit\":\"kg\"}","type":"multi_line_text_field","owner_id":"37914779189496","owner_resource":"product_image","created_at":"2022-08-11T11:07:45+02:00","updated_at":"2022-08-11T11:07:45+02:00","admin_graphql_api_id":"gid://shopify/Metafield/23003951464696"},{"id":"23003951497464","namespace":"global","key":"0015","value":"{\"value\":20.0,\"unit\":\"ml\"}","type":"multi_line_text_field","owner_id":"37914779189496","owner_resource":"product_image","created_at":"2022-08-11T11:07:45+02:00","updated_at":"2022-08-11T11:07:45+02:00","admin_graphql_api_id":"gid://shopify/Metafield/23003951497464"},{"id":"23003951530232","namespace":"global","key":"0016","value":"{\"value\":20.5,\"unit\":\"cm\"}","type":"multi_line_text_field","owner_id":"37914779189496","owner_resource":"product_image","created_at":"2022-08-11T11:07:45+02:00","updated_at":"2022-08-11T11:07:45+02:00","admin_graphql_api_id":"gid://shopify/Metafield/23003951530232"},{"id":"23003951563000","namespace":"global","key":"0017","value":"{\"scale_min\":\"1.0\",\"scale_max\":\"5.0\",\"value\":\"3.5\"}","type":"multi_line_text_field","owner_id":"37914779189496","owner_resource":"product_image","created_at":"2022-08-11T11:07:45+02:00","updated_at":"2022-08-11T11:07:45+02:00","admin_graphql_api_id":"gid://shopify/Metafield/23003951563000"}],"created_at":"2022-08-11T09:07:45+00:00","updated_at":"2022-08-11T11:07:48+02:00","admin_graphql_api_id":"gid://shopify/ProductImage/37914779189496"},{"id":"37914779222264","product_id":"7776971129080","position":4,"src":"https://cdn.shopify.com/s/files/1/0549/3132/5176/products/turquoise_sleek.jpg?v=1660208869","filename":"turquoise_sleek.jpg","width":"128","height":"128","variant_ids":[],"metafields":[{"id":"23003951661304","namespace":"global","key":"0000","value":"This item contains dairy products.","type":"multi_line_text_field","owner_id":"37914779222264","owner_resource":"product_image","created_at":"2022-08-11T11:07:46+02:00","updated_at":"2022-08-11T11:07:46+02:00","admin_graphql_api_id":"gid://shopify/Metafield/23003951661304"},{"id":"23003951694072","namespace":"global","key":"0001","value":"Ingredients: \r\nFlour \r\nWater \r\nMilk \r\nEggs","type":"multi_line_text_field","owner_id":"37914779222264","owner_resource":"product_image","created_at":"2022-08-11T11:07:46+02:00","updated_at":"2022-08-11T11:07:46+02:00","admin_graphql_api_id":"gid://shopify/Metafield/23003951694072"},{"id":"23003951726840","namespace":"global","key":"0002","value":"gid://shopify/OnlineStorePage/1","type":"multi_line_text_field","owner_id":"37914779222264","owner_resource":"product_image","created_at":"2022-08-11T11:07:46+02:00","updated_at":"2022-08-11T11:07:46+02:00","admin_graphql_api_id":"gid://shopify/Metafield/23003951726840"},{"id":"23003951759608","namespace":"global","key":"0003","value":"gid://shopify/Product/1","type":"multi_line_text_field","owner_id":"37914779222264","owner_resource":"product_image","created_at":"2022-08-11T11:07:46+02:00","updated_at":"2022-08-11T11:07:46+02:00","admin_graphql_api_id":"gid://shopify/Metafield/23003951759608"},{"id":"23003951792376","namespace":"global","key":"0004","value":"gid://shopify/ProductVariant/1","type":"multi_line_text_field","owner_id":"37914779222264","owner_resource":"product_image","created_at":"2022-08-11T11:07:46+02:00","updated_at":"2022-08-11T11:07:46+02:00","admin_graphql_api_id":"gid://shopify/Metafield/23003951792376"},{"id":"23003951825144","namespace":"global","key":"0005","value":"gid://shopify/MediaImage/123","type":"multi_line_text_field","owner_id":"37914779222264","owner_resource":"product_image","created_at":"2022-08-11T11:07:46+02:00","updated_at":"2022-08-11T11:07:46+02:00","admin_graphql_api_id":"gid://shopify/Metafield/23003951825144"},{"id":"23003951857912","namespace":"global","key":"0006","value":"10","type":"number_integer","owner_id":"37914779222264","owner_resource":"product_image","created_at":"2022-08-11T11:07:46+02:00","updated_at":"2022-08-11T11:07:46+02:00","admin_graphql_api_id":"gid://shopify/Metafield/23003951857912"},{"id":"23003951890680","namespace":"global","key":"0007","value":"10.4","type":"multi_line_text_field","owner_id":"37914779222264","owner_resource":"product_image","created_at":"2022-08-11T11:07:46+02:00","updated_at":"2022-08-11T11:07:46+02:00","admin_graphql_api_id":"gid://shopify/Metafield/23003951890680"},{"id":"23003951923448","namespace":"global","key":"0008","value":"2021-02-02","type":"multi_line_text_field","owner_id":"37914779222264","owner_resource":"product_image","created_at":"2022-08-11T11:07:46+02:00","updated_at":"2022-08-11T11:07:46+02:00","admin_graphql_api_id":"gid://shopify/Metafield/23003951923448"},{"id":"23003951956216","namespace":"global","key":"0009","value":"2021-01-01T12:30:00+00:00","type":"multi_line_text_field","owner_id":"37914779222264","owner_resource":"product_image","created_at":"2022-08-11T11:07:46+02:00","updated_at":"2022-08-11T11:07:46+02:00","admin_graphql_api_id":"gid://shopify/Metafield/23003951956216"},{"id":"23003951988984","namespace":"global","key":"0010","value":"https://www.shopify.com","type":"multi_line_text_field","owner_id":"37914779222264","owner_resource":"product_image","created_at":"2022-08-11T11:07:46+02:00","updated_at":"2022-08-11T11:07:46+02:00","admin_graphql_api_id":"gid://shopify/Metafield/23003951988984"},{"id":"23003952021752","namespace":"global","key":"0011","value":"[{\"k\":\"v1\"},{\"k\":\"v2\"}]","type":"json","owner_id":"37914779222264","owner_resource":"product_image","created_at":"2022-08-11T11:07:46+02:00","updated_at":"2022-08-11T11:07:46+02:00","admin_graphql_api_id":"gid://shopify/Metafield/23003952021752"},{"id":"23003952054520","namespace":"global","key":"0012","value":"true","type":"boolean","owner_id":"37914779222264","owner_resource":"product_image","created_at":"2022-08-11T11:07:46+02:00","updated_at":"2022-08-11T11:07:46+02:00","admin_graphql_api_id":"gid://shopify/Metafield/23003952054520"},{"id":"23003952087288","namespace":"global","key":"0013","value":"#fff123","type":"multi_line_text_field","owner_id":"37914779222264","owner_resource":"product_image","created_at":"2022-08-11T11:07:46+02:00","updated_at":"2022-08-11T11:07:46+02:00","admin_graphql_api_id":"gid://shopify/Metafield/23003952087288"},{"id":"23003952120056","namespace":"global","key":"0014","value":"{\"value\":2.5,\"unit\":\"kg\"}","type":"multi_line_text_field","owner_id":"37914779222264","owner_resource":"product_image","created_at":"2022-08-11T11:07:46+02:00","updated_at":"2022-08-11T11:07:46+02:00","admin_graphql_api_id":"gid://shopify/Metafield/23003952120056"},{"id":"23003952152824","namespace":"global","key":"0015","value":"{\"value\":20.0,\"unit\":\"ml\"}","type":"multi_line_text_field","owner_id":"37914779222264","owner_resource":"product_image","created_at":"2022-08-11T11:07:46+02:00","updated_at":"2022-08-11T11:07:46+02:00","admin_graphql_api_id":"gid://shopify/Metafield/23003952152824"},{"id":"23003952185592","namespace":"global","key":"0016","value":"{\"value\":20.5,\"unit\":\"cm\"}","type":"multi_line_text_field","owner_id":"37914779222264","owner_resource":"product_image","created_at":"2022-08-11T11:07:46+02:00","updated_at":"2022-08-11T11:07:46+02:00","admin_graphql_api_id":"gid://shopify/Metafield/23003952185592"},{"id":"23003952218360","namespace":"global","key":"0017","value":"{\"scale_min\":\"1.0\",\"scale_max\":\"5.0\",\"value\":\"3.5\"}","type":"multi_line_text_field","owner_id":"37914779222264","owner_resource":"product_image","created_at":"2022-08-11T11:07:46+02:00","updated_at":"2022-08-11T11:07:46+02:00","admin_graphql_api_id":"gid://shopify/Metafield/23003952218360"}],"created_at":"2022-08-11T09:07:46+00:00","updated_at":"2022-08-11T11:07:49+02:00","admin_graphql_api_id":"gid://shopify/ProductImage/37914779222264"},{"id":"37914779255032","product_id":"7776971129080","position":5,"src":"https://cdn.shopify.com/s/files/1/0549/3132/5176/products/rubber_vatu_movies___home.jpg?v=1660208869","filename":"rubber_vatu_movies___home.jpg","width":"128","height":"128","variant_ids":[],"metafields":[{"id":"23003952251128","namespace":"global","key":"0000","value":"This item contains dairy products.","type":"multi_line_text_field","owner_id":"37914779255032","owner_resource":"product_image","created_at":"2022-08-11T11:07:46+02:00","updated_at":"2022-08-11T11:07:46+02:00","admin_graphql_api_id":"gid://shopify/Metafield/23003952251128"},{"id":"23003952283896","namespace":"global","key":"0001","value":"Ingredients: \r\nFlour \r\nWater \r\nMilk \r\nEggs","type":"multi_line_text_field","owner_id":"37914779255032","owner_resource":"product_image","created_at":"2022-08-11T11:07:46+02:00","updated_at":"2022-08-11T11:07:46+02:00","admin_graphql_api_id":"gid://shopify/Metafield/23003952283896"},{"id":"23003952316664","namespace":"global","key":"0002","value":"gid://shopify/OnlineStorePage/1","type":"multi_line_text_field","owner_id":"37914779255032","owner_resource":"product_image","created_at":"2022-08-11T11:07:46+02:00","updated_at":"2022-08-11T11:07:46+02:00","admin_graphql_api_id":"gid://shopify/Metafield/23003952316664"},{"id":"23003952349432","namespace":"global","key":"0003","value":"gid://shopify/Product/1","type":"multi_line_text_field","owner_id":"37914779255032","owner_resource":"product_image","created_at":"2022-08-11T11:07:46+02:00","updated_at":"2022-08-11T11:07:46+02:00","admin_graphql_api_id":"gid://shopify/Metafield/23003952349432"},{"id":"23003952382200","namespace":"global","key":"0004","value":"gid://shopify/ProductVariant/1","type":"multi_line_text_field","owner_id":"37914779255032","owner_resource":"product_image","created_at":"2022-08-11T11:07:46+02:00","updated_at":"2022-08-11T11:07:46+02:00","admin_graphql_api_id":"gid://shopify/Metafield/23003952382200"},{"id":"23003952414968","namespace":"global","key":"0005","value":"gid://shopify/MediaImage/123","type":"multi_line_text_field","owner_id":"37914779255032","owner_resource":"product_image","created_at":"2022-08-11T11:07:46+02:00","updated_at":"2022-08-11T11:07:46+02:00","admin_graphql_api_id":"gid://shopify/Metafield/23003952414968"},{"id":"23003952447736","namespace":"global","key":"0006","value":"10","type":"number_integer","owner_id":"37914779255032","owner_resource":"product_image","created_at":"2022-08-11T11:07:46+02:00","updated_at":"2022-08-11T11:07:46+02:00","admin_graphql_api_id":"gid://shopify/Metafield/23003952447736"},{"id":"23003952480504","namespace":"global","key":"0007","value":"10.4","type":"multi_line_text_field","owner_id":"37914779255032","owner_resource":"product_image","created_at":"2022-08-11T11:07:46+02:00","updated_at":"2022-08-11T11:07:46+02:00","admin_graphql_api_id":"gid://shopify/Metafield/23003952480504"},{"id":"23003952513272","namespace":"global","key":"0008","value":"2021-02-02","type":"multi_line_text_field","owner_id":"37914779255032","owner_resource":"product_image","created_at":"2022-08-11T11:07:46+02:00","updated_at":"2022-08-11T11:07:46+02:00","admin_graphql_api_id":"gid://shopify/Metafield/23003952513272"},{"id":"23003952546040","namespace":"global","key":"0009","value":"2021-01-01T12:30:00+00:00","type":"multi_line_text_field","owner_id":"37914779255032","owner_resource":"product_image","created_at":"2022-08-11T11:07:46+02:00","updated_at":"2022-08-11T11:07:46+02:00","admin_graphql_api_id":"gid://shopify/Metafield/23003952546040"},{"id":"23003952578808","namespace":"global","key":"0010","value":"https://www.shopify.com","type":"multi_line_text_field","owner_id":"37914779255032","owner_resource":"product_image","created_at":"2022-08-11T11:07:46+02:00","updated_at":"2022-08-11T11:07:46+02:00","admin_graphql_api_id":"gid://shopify/Metafield/23003952578808"},{"id":"23003952611576","namespace":"global","key":"0011","value":"[{\"k\":\"v1\"},{\"k\":\"v2\"}]","type":"json","owner_id":"37914779255032","owner_resource":"product_image","created_at":"2022-08-11T11:07:46+02:00","updated_at":"2022-08-11T11:07:46+02:00","admin_graphql_api_id":"gid://shopify/Metafield/23003952611576"},{"id":"23003952644344","namespace":"global","key":"0012","value":"true","type":"boolean","owner_id":"37914779255032","owner_resource":"product_image","created_at":"2022-08-11T11:07:46+02:00","updated_at":"2022-08-11T11:07:46+02:00","admin_graphql_api_id":"gid://shopify/Metafield/23003952644344"},{"id":"23003952677112","namespace":"global","key":"0013","value":"#fff123","type":"multi_line_text_field","owner_id":"37914779255032","owner_resource":"product_image","created_at":"2022-08-11T11:07:46+02:00","updated_at":"2022-08-11T11:07:46+02:00","admin_graphql_api_id":"gid://shopify/Metafield/23003952677112"},{"id":"23003952709880","namespace":"global","key":"0014","value":"{\"value\":2.5,\"unit\":\"kg\"}","type":"multi_line_text_field","owner_id":"37914779255032","owner_resource":"product_image","created_at":"2022-08-11T11:07:46+02:00","updated_at":"2022-08-11T11:07:46+02:00","admin_graphql_api_id":"gid://shopify/Metafield/23003952709880"},{"id":"23003952742648","namespace":"global","key":"0015","value":"{\"value\":20.0,\"unit\":\"ml\"}","type":"multi_line_text_field","owner_id":"37914779255032","owner_resource":"product_image","created_at":"2022-08-11T11:07:46+02:00","updated_at":"2022-08-11T11:07:46+02:00","admin_graphql_api_id":"gid://shopify/Metafield/23003952742648"},{"id":"23003952775416","namespace":"global","key":"0016","value":"{\"value\":20.5,\"unit\":\"cm\"}","type":"multi_line_text_field","owner_id":"37914779255032","owner_resource":"product_image","created_at":"2022-08-11T11:07:46+02:00","updated_at":"2022-08-11T11:07:46+02:00","admin_graphql_api_id":"gid://shopify/Metafield/23003952775416"},{"id":"23003952808184","namespace":"global","key":"0017","value":"{\"scale_min\":\"1.0\",\"scale_max\":\"5.0\",\"value\":\"3.5\"}","type":"multi_line_text_field","owner_id":"37914779255032","owner_resource":"product_image","created_at":"2022-08-11T11:07:46+02:00","updated_at":"2022-08-11T11:07:46+02:00","admin_graphql_api_id":"gid://shopify/Metafield/23003952808184"}],"created_at":"2022-08-11T09:07:46+00:00","updated_at":"2022-08-11T11:07:49+02:00","admin_graphql_api_id":"gid://shopify/ProductImage/37914779255032"}],"variants":[{"id":"43140237361400","barcode":"46492005","compare_at_price":"932.43","title":"Frozen / lime / velit","fulfillment_service":"manual","grams":"13012","image_id":"37914779091192","inventory_management":"shopify","inventory_policy":"deny","inventory_quantity":"0","metafields":[{"id":"23003952873720","namespace":"global","key":"0000","value":"This item contains dairy products.","type":"multi_line_text_field","owner_id":"43140237361400","owner_resource":"variant","created_at":"2022-08-11T11:07:46+02:00","updated_at":"2022-08-11T11:07:46+02:00","admin_graphql_api_id":"gid://shopify/Metafield/23003952873720"},{"id":"23003952906488","namespace":"global","key":"0001","value":"Ingredients: \r\nFlour \r\nWater \r\nMilk \r\nEggs","type":"multi_line_text_field","owner_id":"43140237361400","owner_resource":"variant","created_at":"2022-08-11T11:07:46+02:00","updated_at":"2022-08-11T11:07:46+02:00","admin_graphql_api_id":"gid://shopify/Metafield/23003952906488"},{"id":"23003952939256","namespace":"global","key":"0002","value":"gid://shopify/OnlineStorePage/1","type":"multi_line_text_field","owner_id":"43140237361400","owner_resource":"variant","created_at":"2022-08-11T11:07:46+02:00","updated_at":"2022-08-11T11:07:46+02:00","admin_graphql_api_id":"gid://shopify/Metafield/23003952939256"},{"id":"23003952972024","namespace":"global","key":"0003","value":"gid://shopify/Product/1","type":"multi_line_text_field","owner_id":"43140237361400","owner_resource":"variant","created_at":"2022-08-11T11:07:46+02:00","updated_at":"2022-08-11T11:07:46+02:00","admin_graphql_api_id":"gid://shopify/Metafield/23003952972024"},{"id":"23003953004792","namespace":"global","key":"0004","value":"gid://shopify/ProductVariant/1","type":"multi_line_text_field","owner_id":"43140237361400","owner_resource":"variant","created_at":"2022-08-11T11:07:46+02:00","updated_at":"2022-08-11T11:07:46+02:00","admin_graphql_api_id":"gid://shopify/Metafield/23003953004792"},{"id":"23003953037560","namespace":"global","key":"0005","value":"gid://shopify/MediaImage/123","type":"multi_line_text_field","owner_id":"43140237361400","owner_resource":"variant","created_at":"2022-08-11T11:07:46+02:00","updated_at":"2022-08-11T11:07:46+02:00","admin_graphql_api_id":"gid://shopify/Metafield/23003953037560"},{"id":"23003953070328","namespace":"global","key":"0006","value":"10","type":"number_integer","owner_id":"43140237361400","owner_resource":"variant","created_at":"2022-08-11T11:07:46+02:00","updated_at":"2022-08-11T11:07:46+02:00","admin_graphql_api_id":"gid://shopify/Metafield/23003953070328"},{"id":"23003953103096","namespace":"global","key":"0007","value":"10.4","type":"multi_line_text_field","owner_id":"43140237361400","owner_resource":"variant","created_at":"2022-08-11T11:07:46+02:00","updated_at":"2022-08-11T11:07:46+02:00","admin_graphql_api_id":"gid://shopify/Metafield/23003953103096"},{"id":"23003953135864","namespace":"global","key":"0008","value":"2021-02-02","type":"multi_line_text_field","owner_id":"43140237361400","owner_resource":"variant","created_at":"2022-08-11T11:07:46+02:00","updated_at":"2022-08-11T11:07:46+02:00","admin_graphql_api_id":"gid://shopify/Metafield/23003953135864"},{"id":"23003953168632","namespace":"global","key":"0009","value":"2021-01-01T12:30:00+00:00","type":"multi_line_text_field","owner_id":"43140237361400","owner_resource":"variant","created_at":"2022-08-11T11:07:46+02:00","updated_at":"2022-08-11T11:07:46+02:00","admin_graphql_api_id":"gid://shopify/Metafield/23003953168632"},{"id":"23003953201400","namespace":"global","key":"0010","value":"https://www.shopify.com","type":"multi_line_text_field","owner_id":"43140237361400","owner_resource":"variant","created_at":"2022-08-11T11:07:46+02:00","updated_at":"2022-08-11T11:07:46+02:00","admin_graphql_api_id":"gid://shopify/Metafield/23003953201400"},{"id":"23003953234168","namespace":"global","key":"0011","value":"[{\"k\":\"v1\"},{\"k\":\"v2\"}]","type":"json","owner_id":"43140237361400","owner_resource":"variant","created_at":"2022-08-11T11:07:46+02:00","updated_at":"2022-08-11T11:07:46+02:00","admin_graphql_api_id":"gid://shopify/Metafield/23003953234168"},{"id":"23003953266936","namespace":"global","key":"0012","value":"true","type":"boolean","owner_id":"43140237361400","owner_resource":"variant","created_at":"2022-08-11T11:07:46+02:00","updated_at":"2022-08-11T11:07:46+02:00","admin_graphql_api_id":"gid://shopify/Metafield/23003953266936"},{"id":"23003953299704","namespace":"global","key":"0013","value":"#fff123","type":"multi_line_text_field","owner_id":"43140237361400","owner_resource":"variant","created_at":"2022-08-11T11:07:46+02:00","updated_at":"2022-08-11T11:07:46+02:00","admin_graphql_api_id":"gid://shopify/Metafield/23003953299704"},{"id":"23003953332472","namespace":"global","key":"0014","value":"{\"value\":2.5,\"unit\":\"kg\"}","type":"multi_line_text_field","owner_id":"43140237361400","owner_resource":"variant","created_at":"2022-08-11T11:07:46+02:00","updated_at":"2022-08-11T11:07:46+02:00","admin_graphql_api_id":"gid://shopify/Metafield/23003953332472"},{"id":"23003953365240","namespace":"global","key":"0015","value":"{\"value\":20.0,\"unit\":\"ml\"}","type":"multi_line_text_field","owner_id":"43140237361400","owner_resource":"variant","created_at":"2022-08-11T11:07:46+02:00","updated_at":"2022-08-11T11:07:46+02:00","admin_graphql_api_id":"gid://shopify/Metafield/23003953365240"},{"id":"23003953398008","namespace":"global","key":"0016","value":"{\"value\":20.5,\"unit\":\"cm\"}","type":"multi_line_text_field","owner_id":"43140237361400","owner_resource":"variant","created_at":"2022-08-11T11:07:46+02:00","updated_at":"2022-08-11T11:07:46+02:00","admin_graphql_api_id":"gid://shopify/Metafield/23003953398008"},{"id":"23003953430776","namespace":"global","key":"0017","value":"{\"scale_min\":\"1.0\",\"scale_max\":\"5.0\",\"value\":\"3.5\"}","type":"multi_line_text_field","owner_id":"43140237361400","owner_resource":"variant","created_at":"2022-08-11T11:07:46+02:00","updated_at":"2022-08-11T11:07:46+02:00","admin_graphql_api_id":"gid://shopify/Metafield/23003953430776"}],"option1":"Frozen","option2":"lime","option3":"velit","position":"1","product_id":"7776971129080","sku":"1814653252452","taxable":"false","weight":"459.0","weight_unit":"oz","price":"180.39","updated_at":"2022-08-11T11:07:52+02:00","created_at":"2022-08-11T11:07:46+02:00","inventory_item_id":"45234808979704","admin_graphql_api_id":"gid://shopify/ProductVariant/43140237361400"},{"id":"43140237394168","barcode":"04068044","compare_at_price":"881.02","title":"Fresh / cyan / non","fulfillment_service":"manual","grams":"595","image_id":"37914779123960","inventory_management":"shopify","inventory_policy":"deny","inventory_quantity":"0","metafields":[{"id":"23003953463544","namespace":"global","key":"0000","value":"This item contains dairy products.","type":"multi_line_text_field","owner_id":"43140237394168","owner_resource":"variant","created_at":"2022-08-11T11:07:46+02:00","updated_at":"2022-08-11T11:07:46+02:00","admin_graphql_api_id":"gid://shopify/Metafield/23003953463544"},{"id":"23003953496312","namespace":"global","key":"0001","value":"Ingredients: \r\nFlour \r\nWater \r\nMilk \r\nEggs","type":"multi_line_text_field","owner_id":"43140237394168","owner_resource":"variant","created_at":"2022-08-11T11:07:46+02:00","updated_at":"2022-08-11T11:07:46+02:00","admin_graphql_api_id":"gid://shopify/Metafield/23003953496312"},{"id":"23003953529080","namespace":"global","key":"0002","value":"gid://shopify/OnlineStorePage/1","type":"multi_line_text_field","owner_id":"43140237394168","owner_resource":"variant","created_at":"2022-08-11T11:07:46+02:00","updated_at":"2022-08-11T11:07:46+02:00","admin_graphql_api_id":"gid://shopify/Metafield/23003953529080"},{"id":"23003953561848","namespace":"global","key":"0003","value":"gid://shopify/Product/1","type":"multi_line_text_field","owner_id":"43140237394168","owner_resource":"variant","created_at":"2022-08-11T11:07:46+02:00","updated_at":"2022-08-11T11:07:46+02:00","admin_graphql_api_id":"gid://shopify/Metafield/23003953561848"},{"id":"23003953594616","namespace":"global","key":"0004","value":"gid://shopify/ProductVariant/1","type":"multi_line_text_field","owner_id":"43140237394168","owner_resource":"variant","created_at":"2022-08-11T11:07:46+02:00","updated_at":"2022-08-11T11:07:46+02:00","admin_graphql_api_id":"gid://shopify/Metafield/23003953594616"},{"id":"23003953627384","namespace":"global","key":"0005","value":"gid://shopify/MediaImage/123","type":"multi_line_text_field","owner_id":"43140237394168","owner_resource":"variant","created_at":"2022-08-11T11:07:46+02:00","updated_at":"2022-08-11T11:07:46+02:00","admin_graphql_api_id":"gid://shopify/Metafield/23003953627384"},{"id":"23003953660152","namespace":"global","key":"0006","value":"10","type":"number_integer","owner_id":"43140237394168","owner_resource":"variant","created_at":"2022-08-11T11:07:46+02:00","updated_at":"2022-08-11T11:07:46+02:00","admin_graphql_api_id":"gid://shopify/Metafield/23003953660152"},{"id":"23003953692920","namespace":"global","key":"0007","value":"10.4","type":"multi_line_text_field","owner_id":"43140237394168","owner_resource":"variant","created_at":"2022-08-11T11:07:46+02:00","updated_at":"2022-08-11T11:07:46+02:00","admin_graphql_api_id":"gid://shopify/Metafield/23003953692920"},{"id":"23003953725688","namespace":"global","key":"0008","value":"2021-02-02","type":"multi_line_text_field","owner_id":"43140237394168","owner_resource":"variant","created_at":"2022-08-11T11:07:46+02:00","updated_at":"2022-08-11T11:07:46+02:00","admin_graphql_api_id":"gid://shopify/Metafield/23003953725688"},{"id":"23003953758456","namespace":"global","key":"0009","value":"2021-01-01T12:30:00+00:00","type":"multi_line_text_field","owner_id":"43140237394168","owner_resource":"variant","created_at":"2022-08-11T11:07:46+02:00","updated_at":"2022-08-11T11:07:46+02:00","admin_graphql_api_id":"gid://shopify/Metafield/23003953758456"},{"id":"23003953791224","namespace":"global","key":"0010","value":"https://www.shopify.com","type":"multi_line_text_field","owner_id":"43140237394168","owner_resource":"variant","created_at":"2022-08-11T11:07:46+02:00","updated_at":"2022-08-11T11:07:46+02:00","admin_graphql_api_id":"gid://shopify/Metafield/23003953791224"},{"id":"23003953823992","namespace":"global","key":"0011","value":"[{\"k\":\"v1\"},{\"k\":\"v2\"}]","type":"json","owner_id":"43140237394168","owner_resource":"variant","created_at":"2022-08-11T11:07:46+02:00","updated_at":"2022-08-11T11:07:46+02:00","admin_graphql_api_id":"gid://shopify/Metafield/23003953823992"},{"id":"23003953856760","namespace":"global","key":"0012","value":"true","type":"boolean","owner_id":"43140237394168","owner_resource":"variant","created_at":"2022-08-11T11:07:46+02:00","updated_at":"2022-08-11T11:07:46+02:00","admin_graphql_api_id":"gid://shopify/Metafield/23003953856760"},{"id":"23003953889528","namespace":"global","key":"0013","value":"#fff123","type":"multi_line_text_field","owner_id":"43140237394168","owner_resource":"variant","created_at":"2022-08-11T11:07:46+02:00","updated_at":"2022-08-11T11:07:46+02:00","admin_graphql_api_id":"gid://shopify/Metafield/23003953889528"},{"id":"23003953922296","namespace":"global","key":"0014","value":"{\"value\":2.5,\"unit\":\"kg\"}","type":"multi_line_text_field","owner_id":"43140237394168","owner_resource":"variant","created_at":"2022-08-11T11:07:46+02:00","updated_at":"2022-08-11T11:07:46+02:00","admin_graphql_api_id":"gid://shopify/Metafield/23003953922296"},{"id":"23003953955064","namespace":"global","key":"0015","value":"{\"value\":20.0,\"unit\":\"ml\"}","type":"multi_line_text_field","owner_id":"43140237394168","owner_resource":"variant","created_at":"2022-08-11T11:07:46+02:00","updated_at":"2022-08-11T11:07:46+02:00","admin_graphql_api_id":"gid://shopify/Metafield/23003953955064"},{"id":"23003953987832","namespace":"global","key":"0016","value":"{\"value\":20.5,\"unit\":\"cm\"}","type":"multi_line_text_field","owner_id":"43140237394168","owner_resource":"variant","created_at":"2022-08-11T11:07:46+02:00","updated_at":"2022-08-11T11:07:46+02:00","admin_graphql_api_id":"gid://shopify/Metafield/23003953987832"},{"id":"23003954020600","namespace":"global","key":"0017","value":"{\"scale_min\":\"1.0\",\"scale_max\":\"5.0\",\"value\":\"3.5\"}","type":"multi_line_text_field","owner_id":"43140237394168","owner_resource":"variant","created_at":"2022-08-11T11:07:46+02:00","updated_at":"2022-08-11T11:07:46+02:00","admin_graphql_api_id":"gid://shopify/Metafield/23003954020600"}],"option1":"Fresh","option2":"cyan","option3":"non","position":"2","product_id":"7776971129080","sku":"2257207727379","taxable":"false","weight":"21.0","weight_unit":"oz","price":"693.26","updated_at":"2022-08-11T11:07:52+02:00","created_at":"2022-08-11T11:07:46+02:00","inventory_item_id":"45234809012472","admin_graphql_api_id":"gid://shopify/ProductVariant/43140237394168"},{"id":"43140237426936","barcode":"83364075","compare_at_price":"813.19","title":"Metal / olive / assumenda","fulfillment_service":"manual","grams":"21886","image_id":"37914779189496","inventory_management":"shopify","inventory_policy":"deny","inventory_quantity":"0","metafields":[{"id":"23003954053368","namespace":"global","key":"0000","value":"This item contains dairy products.","type":"multi_line_text_field","owner_id":"43140237426936","owner_resource":"variant","created_at":"2022-08-11T11:07:47+02:00","updated_at":"2022-08-11T11:07:47+02:00","admin_graphql_api_id":"gid://shopify/Metafield/23003954053368"},{"id":"23003954086136","namespace":"global","key":"0001","value":"Ingredients: \r\nFlour \r\nWater \r\nMilk \r\nEggs","type":"multi_line_text_field","owner_id":"43140237426936","owner_resource":"variant","created_at":"2022-08-11T11:07:47+02:00","updated_at":"2022-08-11T11:07:47+02:00","admin_graphql_api_id":"gid://shopify/Metafield/23003954086136"},{"id":"23003954118904","namespace":"global","key":"0002","value":"gid://shopify/OnlineStorePage/1","type":"multi_line_text_field","owner_id":"43140237426936","owner_resource":"variant","created_at":"2022-08-11T11:07:47+02:00","updated_at":"2022-08-11T11:07:47+02:00","admin_graphql_api_id":"gid://shopify/Metafield/23003954118904"},{"id":"23003954151672","namespace":"global","key":"0003","value":"gid://shopify/Product/1","type":"multi_line_text_field","owner_id":"43140237426936","owner_resource":"variant","created_at":"2022-08-11T11:07:47+02:00","updated_at":"2022-08-11T11:07:47+02:00","admin_graphql_api_id":"gid://shopify/Metafield/23003954151672"},{"id":"23003954184440","namespace":"global","key":"0004","value":"gid://shopify/ProductVariant/1","type":"multi_line_text_field","owner_id":"43140237426936","owner_resource":"variant","created_at":"2022-08-11T11:07:47+02:00","updated_at":"2022-08-11T11:07:47+02:00","admin_graphql_api_id":"gid://shopify/Metafield/23003954184440"},{"id":"23003954217208","namespace":"global","key":"0005","value":"gid://shopify/MediaImage/123","type":"multi_line_text_field","owner_id":"43140237426936","owner_resource":"variant","created_at":"2022-08-11T11:07:47+02:00","updated_at":"2022-08-11T11:07:47+02:00","admin_graphql_api_id":"gid://shopify/Metafield/23003954217208"},{"id":"23003954249976","namespace":"global","key":"0006","value":"10","type":"number_integer","owner_id":"43140237426936","owner_resource":"variant","created_at":"2022-08-11T11:07:47+02:00","updated_at":"2022-08-11T11:07:47+02:00","admin_graphql_api_id":"gid://shopify/Metafield/23003954249976"},{"id":"23003954282744","namespace":"global","key":"0007","value":"10.4","type":"multi_line_text_field","owner_id":"43140237426936","owner_resource":"variant","created_at":"2022-08-11T11:07:47+02:00","updated_at":"2022-08-11T11:07:47+02:00","admin_graphql_api_id":"gid://shopify/Metafield/23003954282744"},{"id":"23003954315512","namespace":"global","key":"0008","value":"2021-02-02","type":"multi_line_text_field","owner_id":"43140237426936","owner_resource":"variant","created_at":"2022-08-11T11:07:47+02:00","updated_at":"2022-08-11T11:07:47+02:00","admin_graphql_api_id":"gid://shopify/Metafield/23003954315512"},{"id":"23003954348280","namespace":"global","key":"0009","value":"2021-01-01T12:30:00+00:00","type":"multi_line_text_field","owner_id":"43140237426936","owner_resource":"variant","created_at":"2022-08-11T11:07:47+02:00","updated_at":"2022-08-11T11:07:47+02:00","admin_graphql_api_id":"gid://shopify/Metafield/23003954348280"},{"id":"23003954381048","namespace":"global","key":"0010","value":"https://www.shopify.com","type":"multi_line_text_field","owner_id":"43140237426936","owner_resource":"variant","created_at":"2022-08-11T11:07:47+02:00","updated_at":"2022-08-11T11:07:47+02:00","admin_graphql_api_id":"gid://shopify/Metafield/23003954381048"},{"id":"23003954413816","namespace":"global","key":"0011","value":"[{\"k\":\"v1\"},{\"k\":\"v2\"}]","type":"json","owner_id":"43140237426936","owner_resource":"variant","created_at":"2022-08-11T11:07:47+02:00","updated_at":"2022-08-11T11:07:47+02:00","admin_graphql_api_id":"gid://shopify/Metafield/23003954413816"},{"id":"23003954446584","namespace":"global","key":"0012","value":"true","type":"boolean","owner_id":"43140237426936","owner_resource":"variant","created_at":"2022-08-11T11:07:47+02:00","updated_at":"2022-08-11T11:07:47+02:00","admin_graphql_api_id":"gid://shopify/Metafield/23003954446584"},{"id":"23003954479352","namespace":"global","key":"0013","value":"#fff123","type":"multi_line_text_field","owner_id":"43140237426936","owner_resource":"variant","created_at":"2022-08-11T11:07:47+02:00","updated_at":"2022-08-11T11:07:47+02:00","admin_graphql_api_id":"gid://shopify/Metafield/23003954479352"},{"id":"23003954512120","namespace":"global","key":"0014","value":"{\"value\":2.5,\"unit\":\"kg\"}","type":"multi_line_text_field","owner_id":"43140237426936","owner_resource":"variant","created_at":"2022-08-11T11:07:47+02:00","updated_at":"2022-08-11T11:07:47+02:00","admin_graphql_api_id":"gid://shopify/Metafield/23003954512120"},{"id":"23003954544888","namespace":"global","key":"0015","value":"{\"value\":20.0,\"unit\":\"ml\"}","type":"multi_line_text_field","owner_id":"43140237426936","owner_resource":"variant","created_at":"2022-08-11T11:07:47+02:00","updated_at":"2022-08-11T11:07:47+02:00","admin_graphql_api_id":"gid://shopify/Metafield/23003954544888"},{"id":"23003954577656","namespace":"global","key":"0016","value":"{\"value\":20.5,\"unit\":\"cm\"}","type":"multi_line_text_field","owner_id":"43140237426936","owner_resource":"variant","created_at":"2022-08-11T11:07:47+02:00","updated_at":"2022-08-11T11:07:47+02:00","admin_graphql_api_id":"gid://shopify/Metafield/23003954577656"},{"id":"23003954610424","namespace":"global","key":"0017","value":"{\"scale_min\":\"1.0\",\"scale_max\":\"5.0\",\"value\":\"3.5\"}","type":"multi_line_text_field","owner_id":"43140237426936","owner_resource":"variant","created_at":"2022-08-11T11:07:47+02:00","updated_at":"2022-08-11T11:07:47+02:00","admin_graphql_api_id":"gid://shopify/Metafield/23003954610424"}],"option1":"Metal","option2":"olive","option3":"assumenda","position":"3","product_id":"7776971129080","sku":"6604529883362","taxable":"false","weight":"772.0","weight_unit":"oz","price":"485.96","updated_at":"2022-08-11T11:07:52+02:00","created_at":"2022-08-11T11:07:46+02:00","inventory_item_id":"45234809045240","admin_graphql_api_id":"gid://shopify/ProductVariant/43140237426936"}],"metafields":[{"id":"23003954643192","namespace":"global","key":"description_tag","value":"quam","type":"multi_line_text_field","owner_id":"7776971129080","owner_resource":"product","created_at":"2022-08-11T11:07:47+02:00","updated_at":"2022-08-11T11:07:47+02:00","admin_graphql_api_id":"gid://shopify/Metafield/23003954643192"},{"id":"23003954675960","namespace":"global","key":"title_tag","value":"non","type":"multi_line_text_field","owner_id":"7776971129080","owner_resource":"product","created_at":"2022-08-11T11:07:47+02:00","updated_at":"2022-08-11T11:07:47+02:00","admin_graphql_api_id":"gid://shopify/Metafield/23003954675960"},{"id":"23003954708728","namespace":"global","key":"0000","value":"This item contains dairy products.","type":"multi_line_text_field","owner_id":"7776971129080","owner_resource":"product","created_at":"2022-08-11T11:07:47+02:00","updated_at":"2022-08-11T11:07:47+02:00","admin_graphql_api_id":"gid://shopify/Metafield/23003954708728"},{"id":"23003954741496","namespace":"global","key":"0001","value":"Ingredients: \r\nFlour \r\nWater \r\nMilk \r\nEggs","type":"multi_line_text_field","owner_id":"7776971129080","owner_resource":"product","created_at":"2022-08-11T11:07:47+02:00","updated_at":"2022-08-11T11:07:47+02:00","admin_graphql_api_id":"gid://shopify/Metafield/23003954741496"},{"id":"23003954774264","namespace":"global","key":"0002","value":"gid://shopify/OnlineStorePage/1","type":"multi_line_text_field","owner_id":"7776971129080","owner_resource":"product","created_at":"2022-08-11T11:07:47+02:00","updated_at":"2022-08-11T11:07:47+02:00","admin_graphql_api_id":"gid://shopify/Metafield/23003954774264"},{"id":"23003954807032","namespace":"global","key":"0003","value":"gid://shopify/Product/1","type":"multi_line_text_field","owner_id":"7776971129080","owner_resource":"product","created_at":"2022-08-11T11:07:47+02:00","updated_at":"2022-08-11T11:07:47+02:00","admin_graphql_api_id":"gid://shopify/Metafield/23003954807032"},{"id":"23003954839800","namespace":"global","key":"0004","value":"gid://shopify/ProductVariant/1","type":"multi_line_text_field","owner_id":"7776971129080","owner_resource":"product","created_at":"2022-08-11T11:07:47+02:00","updated_at":"2022-08-11T11:07:47+02:00","admin_graphql_api_id":"gid://shopify/Metafield/23003954839800"},{"id":"23003954872568","namespace":"global","key":"0005","value":"gid://shopify/MediaImage/123","type":"multi_line_text_field","owner_id":"7776971129080","owner_resource":"product","created_at":"2022-08-11T11:07:47+02:00","updated_at":"2022-08-11T11:07:47+02:00","admin_graphql_api_id":"gid://shopify/Metafield/23003954872568"},{"id":"23003954905336","namespace":"global","key":"0006","value":"10","type":"number_integer","owner_id":"7776971129080","owner_resource":"product","created_at":"2022-08-11T11:07:47+02:00","updated_at":"2022-08-11T11:07:47+02:00","admin_graphql_api_id":"gid://shopify/Metafield/23003954905336"},{"id":"23003954938104","namespace":"global","key":"0007","value":"10.4","type":"multi_line_text_field","owner_id":"7776971129080","owner_resource":"product","created_at":"2022-08-11T11:07:47+02:00","updated_at":"2022-08-11T11:07:47+02:00","admin_graphql_api_id":"gid://shopify/Metafield/23003954938104"},{"id":"23003954970872","namespace":"global","key":"0008","value":"2021-02-02","type":"multi_line_text_field","owner_id":"7776971129080","owner_resource":"product","created_at":"2022-08-11T11:07:47+02:00","updated_at":"2022-08-11T11:07:47+02:00","admin_graphql_api_id":"gid://shopify/Metafield/23003954970872"},{"id":"23003955003640","namespace":"global","key":"0009","value":"2021-01-01T12:30:00+00:00","type":"multi_line_text_field","owner_id":"7776971129080","owner_resource":"product","created_at":"2022-08-11T11:07:47+02:00","updated_at":"2022-08-11T11:07:47+02:00","admin_graphql_api_id":"gid://shopify/Metafield/23003955003640"},{"id":"23003955036408","namespace":"global","key":"0010","value":"https://www.shopify.com","type":"multi_line_text_field","owner_id":"7776971129080","owner_resource":"product","created_at":"2022-08-11T11:07:47+02:00","updated_at":"2022-08-11T11:07:47+02:00","admin_graphql_api_id":"gid://shopify/Metafield/23003955036408"},{"id":"23003955069176","namespace":"global","key":"0011","value":"[{\"k\":\"v1\"},{\"k\":\"v2\"}]","type":"json","owner_id":"7776971129080","owner_resource":"product","created_at":"2022-08-11T11:07:47+02:00","updated_at":"2022-08-11T11:07:47+02:00","admin_graphql_api_id":"gid://shopify/Metafield/23003955069176"},{"id":"23003955101944","namespace":"global","key":"0012","value":"true","type":"boolean","owner_id":"7776971129080","owner_resource":"product","created_at":"2022-08-11T11:07:47+02:00","updated_at":"2022-08-11T11:07:47+02:00","admin_graphql_api_id":"gid://shopify/Metafield/23003955101944"},{"id":"23003955134712","namespace":"global","key":"0013","value":"#fff123","type":"multi_line_text_field","owner_id":"7776971129080","owner_resource":"product","created_at":"2022-08-11T11:07:47+02:00","updated_at":"2022-08-11T11:07:47+02:00","admin_graphql_api_id":"gid://shopify/Metafield/23003955134712"},{"id":"23003955167480","namespace":"global","key":"0014","value":"{\"value\":2.5,\"unit\":\"kg\"}","type":"multi_line_text_field","owner_id":"7776971129080","owner_resource":"product","created_at":"2022-08-11T11:07:47+02:00","updated_at":"2022-08-11T11:07:47+02:00","admin_graphql_api_id":"gid://shopify/Metafield/23003955167480"},{"id":"23003955200248","namespace":"global","key":"0015","value":"{\"value\":20.0,\"unit\":\"ml\"}","type":"multi_line_text_field","owner_id":"7776971129080","owner_resource":"product","created_at":"2022-08-11T11:07:47+02:00","updated_at":"2022-08-11T11:07:47+02:00","admin_graphql_api_id":"gid://shopify/Metafield/23003955200248"},{"id":"23003955233016","namespace":"global","key":"0016","value":"{\"value\":20.5,\"unit\":\"cm\"}","type":"multi_line_text_field","owner_id":"7776971129080","owner_resource":"product","created_at":"2022-08-11T11:07:47+02:00","updated_at":"2022-08-11T11:07:47+02:00","admin_graphql_api_id":"gid://shopify/Metafield/23003955233016"},{"id":"23003955265784","namespace":"global","key":"0017","value":"{\"scale_min\":\"1.0\",\"scale_max\":\"5.0\",\"value\":\"3.5\"}","type":"multi_line_text_field","owner_id":"7776971129080","owner_resource":"product","created_at":"2022-08-11T11:07:47+02:00","updated_at":"2022-08-11T11:07:47+02:00","admin_graphql_api_id":"gid://shopify/Metafield/23003955265784"}],"admin_graphql_api_id":"gid://shopify/Product/7776971129080"}