{"id":"6404731306232","email":"weldon27@gmail.com","phone":"+15208825091","accepts_marketing":true,"accepts_marketing_updated_at":"2022-04-13T16:00:56+02:00","marketing_opt_in_level":"single_opt_in","created_at":"2022-04-13T16:01:13+02:00","updated_at":"2022-04-13T16:01:14+02:00","first_name":"Maureen","last_name":"McDermott","orders_count":0,"state":"disabled","total_spent":0.00,"note":"Eligendi quo cum ducimus neque ut optio sit.\nCumque porro vel et dolor fugit qui.\nEt veniam tempora minus sunt sapiente.\nOccaecati temporibus odio labore nihil molestiae ipsum consequatur soluta sunt.\nSed non cum in tempore quidem.\nNihil voluptatum natus magni quod eius culpa repellat.","verified_email":true,"multipass_identifier":"aut","tax_exempt":false,"tax_exemptions":[],"tags":"System.String[]","default_address":{"id":"7780446994680","customer_id":"6404731306232","first_name":"Garrison","last_name":"Schimmel","company":"Ullrich - Corkery","address1":"5675 Lind Glen, Landenton, Taiwan","address2":"Apt. 430","city":"Tucson","province":"Arkansas","country":"United States","zip":"85705","phone":"+1 520-882-2206","name":"Garrison Schimmel","province_code":"AR","country_code":"US","country_name":"United States","default":true},"addresses":[{"id":"7780446994680","customer_id":"6404731306232","first_name":"Garrison","last_name":"Schimmel","company":"Ullrich - Corkery","address1":"5675 Lind Glen, Landenton, Taiwan","address2":"Apt. 430","city":"Tucson","province":"Arkansas","country":"United States","zip":"85705","phone":"+1 520-882-2206","name":"Garrison Schimmel","province_code":"AR","country_code":"US","country_name":"United States","default":true},{"id":"7780447027448","customer_id":"6404731306232","first_name":"Sydni","last_name":"Abbott","company":"Hirthe LLC","address1":"759 Seth Estate, South Colemanside, Afghanistan","address2":"Apt. 968","city":"Tucson","province":"Arkansas","country":"United States","zip":"85705","phone":"+1 520-882-0883","name":"Sydni Abbott","province_code":"AR","country_code":"US","country_name":"United States","default":false}],"admin_graphql_api_id":"gid://shopify/Customer/6404731306232","currency":"AUD"}