{"id":"7776957169912","title":"Intelligent Cotton Gloves","handle":"et","status":"active","options":[{"id":"9863853736184","product_id":"7776957169912","name":"Size","position":"1","values":["Frozen","Concrete"]},{"id":"9863853768952","product_id":"7776957169912","name":"Color","position":"2","values":["fuchsia","orchid","orange"]},{"id":"9863853801720","product_id":"7776957169912","name":"Fabric","position":"3","values":["magni","voluptatem","voluptate"]}],"body_html":"Ergonomic executive chair upholstered in bonded black leather and PVC padded seat and back for all-day comfort and support","tags":"ducimus, eligendi, voluptatem","product_type":"itaque","ProductTypes":{"Id":null,"StandardizedProductType":null,"CustomProductType":"itaque"},"vendor":"beatae","published_at":"2022-05-04T06:50:51+00:00","published_scope":"web","updated_at":"2022-08-11T10:55:54+02:00","created_at":"2022-08-11T10:55:51+02:00","image":{"id":"37914723680504","product_id":"7776957169912","position":1,"src":"https://cdn.shopify.com/s/files/1/0549/3132/5176/products/maroon_impactful_borders.jpg?v=1660208154","width":"128","height":"128","variant_ids":[],"created_at":"2022-08-11T08:55:51+00:00","updated_at":"2022-08-11T10:55:54+02:00","admin_graphql_api_id":"gid://shopify/ProductImage/37914723680504"},"images":[{"id":"37914723680504","product_id":"7776957169912","position":1,"src":"https://cdn.shopify.com/s/files/1/0549/3132/5176/products/maroon_impactful_borders.jpg?v=1660208154","filename":"maroon_impactful_borders.jpg","width":"128","height":"128","variant_ids":[],"metafields":[{"id":"23003657928952","namespace":"global","key":"0000","value":"This item contains dairy products.","type":"single_line_text_field","owner_id":"37914723680504","owner_resource":"product_image","created_at":"2022-08-11T10:55:51+02:00","updated_at":"2022-08-11T10:55:51+02:00","admin_graphql_api_id":"gid://shopify/Metafield/23003657928952"},{"id":"23003657961720","namespace":"global","key":"0001","value":"Ingredients: \r\nFlour \r\nWater \r\nMilk \r\nEggs","type":"multi_line_text_field","owner_id":"37914723680504","owner_resource":"product_image","created_at":"2022-08-11T10:55:52+02:00","updated_at":"2022-08-11T10:55:52+02:00","admin_graphql_api_id":"gid://shopify/Metafield/23003657961720"},{"id":"23003657994488","namespace":"global","key":"0002","value":"gid://shopify/OnlineStorePage/1","type":"page_reference","owner_id":"37914723680504","owner_resource":"product_image","created_at":"2022-08-11T10:55:52+02:00","updated_at":"2022-08-11T10:55:52+02:00","admin_graphql_api_id":"gid://shopify/Metafield/23003657994488"},{"id":"23003658027256","namespace":"global","key":"0003","value":"gid://shopify/Product/1","type":"product_reference","owner_id":"37914723680504","owner_resource":"product_image","created_at":"2022-08-11T10:55:52+02:00","updated_at":"2022-08-11T10:55:52+02:00","admin_graphql_api_id":"gid://shopify/Metafield/23003658027256"},{"id":"23003658060024","namespace":"global","key":"0004","value":"gid://shopify/ProductVariant/1","type":"variant_reference","owner_id":"37914723680504","owner_resource":"product_image","created_at":"2022-08-11T10:55:52+02:00","updated_at":"2022-08-11T10:55:52+02:00","admin_graphql_api_id":"gid://shopify/Metafield/23003658060024"},{"id":"23003658092792","namespace":"global","key":"0005","value":"gid://shopify/MediaImage/123","type":"file_reference","owner_id":"37914723680504","owner_resource":"product_image","created_at":"2022-08-11T10:55:52+02:00","updated_at":"2022-08-11T10:55:52+02:00","admin_graphql_api_id":"gid://shopify/Metafield/23003658092792"},{"id":"23003658125560","namespace":"global","key":"0006","value":"10","type":"number_integer","owner_id":"37914723680504","owner_resource":"product_image","created_at":"2022-08-11T10:55:52+02:00","updated_at":"2022-08-11T10:55:52+02:00","admin_graphql_api_id":"gid://shopify/Metafield/23003658125560"},{"id":"23003658158328","namespace":"global","key":"0007","value":"10.4","type":"number_decimal","owner_id":"37914723680504","owner_resource":"product_image","created_at":"2022-08-11T10:55:52+02:00","updated_at":"2022-08-11T10:55:52+02:00","admin_graphql_api_id":"gid://shopify/Metafield/23003658158328"},{"id":"23003658191096","namespace":"global","key":"0008","value":"2021-02-02","type":"date","owner_id":"37914723680504","owner_resource":"product_image","created_at":"2022-08-11T10:55:52+02:00","updated_at":"2022-08-11T10:55:52+02:00","admin_graphql_api_id":"gid://shopify/Metafield/23003658191096"},{"id":"23003658223864","namespace":"global","key":"0009","value":"2021-01-01T12:30:00+00:00","type":"date_time","owner_id":"37914723680504","owner_resource":"product_image","created_at":"2022-08-11T10:55:52+02:00","updated_at":"2022-08-11T10:55:52+02:00","admin_graphql_api_id":"gid://shopify/Metafield/23003658223864"},{"id":"23003658256632","namespace":"global","key":"0010","value":"https://www.shopify.com","type":"url","owner_id":"37914723680504","owner_resource":"product_image","created_at":"2022-08-11T10:55:52+02:00","updated_at":"2022-08-11T10:55:52+02:00","admin_graphql_api_id":"gid://shopify/Metafield/23003658256632"},{"id":"23003658289400","namespace":"global","key":"0011","value":"[{\"k\":\"v1\"},{\"k\":\"v2\"}]","type":"json","owner_id":"37914723680504","owner_resource":"product_image","created_at":"2022-08-11T10:55:52+02:00","updated_at":"2022-08-11T10:55:52+02:00","admin_graphql_api_id":"gid://shopify/Metafield/23003658289400"},{"id":"23003658322168","namespace":"global","key":"0012","value":"true","type":"boolean","owner_id":"37914723680504","owner_resource":"product_image","created_at":"2022-08-11T10:55:52+02:00","updated_at":"2022-08-11T10:55:52+02:00","admin_graphql_api_id":"gid://shopify/Metafield/23003658322168"},{"id":"23003658354936","namespace":"global","key":"0013","value":"#fff123","type":"color","owner_id":"37914723680504","owner_resource":"product_image","created_at":"2022-08-11T10:55:52+02:00","updated_at":"2022-08-11T10:55:52+02:00","admin_graphql_api_id":"gid://shopify/Metafield/23003658354936"},{"id":"23003658387704","namespace":"global","key":"0014","value":"{\"value\":2.5,\"unit\":\"kg\"}","type":"weight","owner_id":"37914723680504","owner_resource":"product_image","created_at":"2022-08-11T10:55:52+02:00","updated_at":"2022-08-11T10:55:52+02:00","admin_graphql_api_id":"gid://shopify/Metafield/23003658387704"},{"id":"23003658420472","namespace":"global","key":"0015","value":"{\"value\":20.0,\"unit\":\"ml\"}","type":"volume","owner_id":"37914723680504","owner_resource":"product_image","created_at":"2022-08-11T10:55:52+02:00","updated_at":"2022-08-11T10:55:52+02:00","admin_graphql_api_id":"gid://shopify/Metafield/23003658420472"},{"id":"23003658453240","namespace":"global","key":"0016","value":"{\"value\":20.5,\"unit\":\"cm\"}","type":"dimension","owner_id":"37914723680504","owner_resource":"product_image","created_at":"2022-08-11T10:55:52+02:00","updated_at":"2022-08-11T10:55:52+02:00","admin_graphql_api_id":"gid://shopify/Metafield/23003658453240"},{"id":"23003658486008","namespace":"global","key":"0017","value":"{\"scale_min\":\"1.0\",\"scale_max\":\"5.0\",\"value\":\"3.5\"}","type":"rating","owner_id":"37914723680504","owner_resource":"product_image","created_at":"2022-08-11T10:55:52+02:00","updated_at":"2022-08-11T10:55:52+02:00","admin_graphql_api_id":"gid://shopify/Metafield/23003658486008"}],"created_at":"2022-08-11T08:55:51+00:00","updated_at":"2022-08-11T10:55:54+02:00","admin_graphql_api_id":"gid://shopify/ProductImage/37914723680504"},{"id":"37914723713272","product_id":"7776957169912","position":2,"src":"https://cdn.shopify.com/s/files/1/0549/3132/5176/products/red_views_music_0310ba70-d67c-4b65-bdc7-95c3f79ba849.jpg?v=1660208155","filename":"red_views_music_0310ba70-d67c-4b65-bdc7-95c3f79ba849.jpg","width":"128","height":"128","variant_ids":[],"metafields":[{"id":"23003658551544","namespace":"global","key":"0000","value":"This item contains dairy products.","type":"single_line_text_field","owner_id":"37914723713272","owner_resource":"product_image","created_at":"2022-08-11T10:55:52+02:00","updated_at":"2022-08-11T10:55:52+02:00","admin_graphql_api_id":"gid://shopify/Metafield/23003658551544"},{"id":"23003658584312","namespace":"global","key":"0001","value":"Ingredients: \r\nFlour \r\nWater \r\nMilk \r\nEggs","type":"multi_line_text_field","owner_id":"37914723713272","owner_resource":"product_image","created_at":"2022-08-11T10:55:52+02:00","updated_at":"2022-08-11T10:55:52+02:00","admin_graphql_api_id":"gid://shopify/Metafield/23003658584312"},{"id":"23003658617080","namespace":"global","key":"0002","value":"gid://shopify/OnlineStorePage/1","type":"page_reference","owner_id":"37914723713272","owner_resource":"product_image","created_at":"2022-08-11T10:55:52+02:00","updated_at":"2022-08-11T10:55:52+02:00","admin_graphql_api_id":"gid://shopify/Metafield/23003658617080"},{"id":"23003658649848","namespace":"global","key":"0003","value":"gid://shopify/Product/1","type":"product_reference","owner_id":"37914723713272","owner_resource":"product_image","created_at":"2022-08-11T10:55:52+02:00","updated_at":"2022-08-11T10:55:52+02:00","admin_graphql_api_id":"gid://shopify/Metafield/23003658649848"},{"id":"23003658682616","namespace":"global","key":"0004","value":"gid://shopify/ProductVariant/1","type":"variant_reference","owner_id":"37914723713272","owner_resource":"product_image","created_at":"2022-08-11T10:55:52+02:00","updated_at":"2022-08-11T10:55:52+02:00","admin_graphql_api_id":"gid://shopify/Metafield/23003658682616"},{"id":"23003658715384","namespace":"global","key":"0005","value":"gid://shopify/MediaImage/123","type":"file_reference","owner_id":"37914723713272","owner_resource":"product_image","created_at":"2022-08-11T10:55:52+02:00","updated_at":"2022-08-11T10:55:52+02:00","admin_graphql_api_id":"gid://shopify/Metafield/23003658715384"},{"id":"23003658748152","namespace":"global","key":"0006","value":"10","type":"number_integer","owner_id":"37914723713272","owner_resource":"product_image","created_at":"2022-08-11T10:55:52+02:00","updated_at":"2022-08-11T10:55:52+02:00","admin_graphql_api_id":"gid://shopify/Metafield/23003658748152"},{"id":"23003658780920","namespace":"global","key":"0007","value":"10.4","type":"number_decimal","owner_id":"37914723713272","owner_resource":"product_image","created_at":"2022-08-11T10:55:52+02:00","updated_at":"2022-08-11T10:55:52+02:00","admin_graphql_api_id":"gid://shopify/Metafield/23003658780920"},{"id":"23003658813688","namespace":"global","key":"0008","value":"2021-02-02","type":"date","owner_id":"37914723713272","owner_resource":"product_image","created_at":"2022-08-11T10:55:52+02:00","updated_at":"2022-08-11T10:55:52+02:00","admin_graphql_api_id":"gid://shopify/Metafield/23003658813688"},{"id":"23003658846456","namespace":"global","key":"0009","value":"2021-01-01T12:30:00+00:00","type":"date_time","owner_id":"37914723713272","owner_resource":"product_image","created_at":"2022-08-11T10:55:52+02:00","updated_at":"2022-08-11T10:55:52+02:00","admin_graphql_api_id":"gid://shopify/Metafield/23003658846456"},{"id":"23003658879224","namespace":"global","key":"0010","value":"https://www.shopify.com","type":"url","owner_id":"37914723713272","owner_resource":"product_image","created_at":"2022-08-11T10:55:52+02:00","updated_at":"2022-08-11T10:55:52+02:00","admin_graphql_api_id":"gid://shopify/Metafield/23003658879224"},{"id":"23003658911992","namespace":"global","key":"0011","value":"[{\"k\":\"v1\"},{\"k\":\"v2\"}]","type":"json","owner_id":"37914723713272","owner_resource":"product_image","created_at":"2022-08-11T10:55:52+02:00","updated_at":"2022-08-11T10:55:52+02:00","admin_graphql_api_id":"gid://shopify/Metafield/23003658911992"},{"id":"23003658944760","namespace":"global","key":"0012","value":"true","type":"boolean","owner_id":"37914723713272","owner_resource":"product_image","created_at":"2022-08-11T10:55:52+02:00","updated_at":"2022-08-11T10:55:52+02:00","admin_graphql_api_id":"gid://shopify/Metafield/23003658944760"},{"id":"23003658977528","namespace":"global","key":"0013","value":"#fff123","type":"color","owner_id":"37914723713272","owner_resource":"product_image","created_at":"2022-08-11T10:55:52+02:00","updated_at":"2022-08-11T10:55:52+02:00","admin_graphql_api_id":"gid://shopify/Metafield/23003658977528"},{"id":"23003659010296","namespace":"global","key":"0014","value":"{\"value\":2.5,\"unit\":\"kg\"}","type":"weight","owner_id":"37914723713272","owner_resource":"product_image","created_at":"2022-08-11T10:55:52+02:00","updated_at":"2022-08-11T10:55:52+02:00","admin_graphql_api_id":"gid://shopify/Metafield/23003659010296"},{"id":"23003659043064","namespace":"global","key":"0015","value":"{\"value\":20.0,\"unit\":\"ml\"}","type":"volume","owner_id":"37914723713272","owner_resource":"product_image","created_at":"2022-08-11T10:55:52+02:00","updated_at":"2022-08-11T10:55:52+02:00","admin_graphql_api_id":"gid://shopify/Metafield/23003659043064"},{"id":"23003659075832","namespace":"global","key":"0016","value":"{\"value\":20.5,\"unit\":\"cm\"}","type":"dimension","owner_id":"37914723713272","owner_resource":"product_image","created_at":"2022-08-11T10:55:52+02:00","updated_at":"2022-08-11T10:55:52+02:00","admin_graphql_api_id":"gid://shopify/Metafield/23003659075832"},{"id":"23003659108600","namespace":"global","key":"0017","value":"{\"scale_min\":\"1.0\",\"scale_max\":\"5.0\",\"value\":\"3.5\"}","type":"rating","owner_id":"37914723713272","owner_resource":"product_image","created_at":"2022-08-11T10:55:52+02:00","updated_at":"2022-08-11T10:55:52+02:00","admin_graphql_api_id":"gid://shopify/Metafield/23003659108600"}],"created_at":"2022-08-11T08:55:52+00:00","updated_at":"2022-08-11T10:55:55+02:00","admin_graphql_api_id":"gid://shopify/ProductImage/37914723713272"},{"id":"37914723778808","product_id":"7776957169912","position":3,"src":"https://cdn.shopify.com/s/files/1/0549/3132/5176/products/directives_287879b7-b847-4fb4-b6d7-49e45a792a49.jpg?v=1660208155","filename":"directives_287879b7-b847-4fb4-b6d7-49e45a792a49.jpg","width":"128","height":"128","variant_ids":[],"metafields":[{"id":"23003659141368","namespace":"global","key":"0000","value":"This item contains dairy products.","type":"single_line_text_field","owner_id":"37914723778808","owner_resource":"product_image","created_at":"2022-08-11T10:55:52+02:00","updated_at":"2022-08-11T10:55:52+02:00","admin_graphql_api_id":"gid://shopify/Metafield/23003659141368"},{"id":"23003659174136","namespace":"global","key":"0001","value":"Ingredients: \r\nFlour \r\nWater \r\nMilk \r\nEggs","type":"multi_line_text_field","owner_id":"37914723778808","owner_resource":"product_image","created_at":"2022-08-11T10:55:52+02:00","updated_at":"2022-08-11T10:55:52+02:00","admin_graphql_api_id":"gid://shopify/Metafield/23003659174136"},{"id":"23003659206904","namespace":"global","key":"0002","value":"gid://shopify/OnlineStorePage/1","type":"page_reference","owner_id":"37914723778808","owner_resource":"product_image","created_at":"2022-08-11T10:55:52+02:00","updated_at":"2022-08-11T10:55:52+02:00","admin_graphql_api_id":"gid://shopify/Metafield/23003659206904"},{"id":"23003659239672","namespace":"global","key":"0003","value":"gid://shopify/Product/1","type":"product_reference","owner_id":"37914723778808","owner_resource":"product_image","created_at":"2022-08-11T10:55:52+02:00","updated_at":"2022-08-11T10:55:52+02:00","admin_graphql_api_id":"gid://shopify/Metafield/23003659239672"},{"id":"23003659272440","namespace":"global","key":"0004","value":"gid://shopify/ProductVariant/1","type":"variant_reference","owner_id":"37914723778808","owner_resource":"product_image","created_at":"2022-08-11T10:55:52+02:00","updated_at":"2022-08-11T10:55:52+02:00","admin_graphql_api_id":"gid://shopify/Metafield/23003659272440"},{"id":"23003659305208","namespace":"global","key":"0005","value":"gid://shopify/MediaImage/123","type":"file_reference","owner_id":"37914723778808","owner_resource":"product_image","created_at":"2022-08-11T10:55:52+02:00","updated_at":"2022-08-11T10:55:52+02:00","admin_graphql_api_id":"gid://shopify/Metafield/23003659305208"},{"id":"23003659337976","namespace":"global","key":"0006","value":"10","type":"number_integer","owner_id":"37914723778808","owner_resource":"product_image","created_at":"2022-08-11T10:55:52+02:00","updated_at":"2022-08-11T10:55:52+02:00","admin_graphql_api_id":"gid://shopify/Metafield/23003659337976"},{"id":"23003659370744","namespace":"global","key":"0007","value":"10.4","type":"number_decimal","owner_id":"37914723778808","owner_resource":"product_image","created_at":"2022-08-11T10:55:52+02:00","updated_at":"2022-08-11T10:55:52+02:00","admin_graphql_api_id":"gid://shopify/Metafield/23003659370744"},{"id":"23003659403512","namespace":"global","key":"0008","value":"2021-02-02","type":"date","owner_id":"37914723778808","owner_resource":"product_image","created_at":"2022-08-11T10:55:52+02:00","updated_at":"2022-08-11T10:55:52+02:00","admin_graphql_api_id":"gid://shopify/Metafield/23003659403512"},{"id":"23003659436280","namespace":"global","key":"0009","value":"2021-01-01T12:30:00+00:00","type":"date_time","owner_id":"37914723778808","owner_resource":"product_image","created_at":"2022-08-11T10:55:52+02:00","updated_at":"2022-08-11T10:55:52+02:00","admin_graphql_api_id":"gid://shopify/Metafield/23003659436280"},{"id":"23003659469048","namespace":"global","key":"0010","value":"https://www.shopify.com","type":"url","owner_id":"37914723778808","owner_resource":"product_image","created_at":"2022-08-11T10:55:52+02:00","updated_at":"2022-08-11T10:55:52+02:00","admin_graphql_api_id":"gid://shopify/Metafield/23003659469048"},{"id":"23003659501816","namespace":"global","key":"0011","value":"[{\"k\":\"v1\"},{\"k\":\"v2\"}]","type":"json","owner_id":"37914723778808","owner_resource":"product_image","created_at":"2022-08-11T10:55:52+02:00","updated_at":"2022-08-11T10:55:52+02:00","admin_graphql_api_id":"gid://shopify/Metafield/23003659501816"},{"id":"23003659534584","namespace":"global","key":"0012","value":"true","type":"boolean","owner_id":"37914723778808","owner_resource":"product_image","created_at":"2022-08-11T10:55:52+02:00","updated_at":"2022-08-11T10:55:52+02:00","admin_graphql_api_id":"gid://shopify/Metafield/23003659534584"},{"id":"23003659567352","namespace":"global","key":"0013","value":"#fff123","type":"color","owner_id":"37914723778808","owner_resource":"product_image","created_at":"2022-08-11T10:55:52+02:00","updated_at":"2022-08-11T10:55:52+02:00","admin_graphql_api_id":"gid://shopify/Metafield/23003659567352"},{"id":"23003659600120","namespace":"global","key":"0014","value":"{\"value\":2.5,\"unit\":\"kg\"}","type":"weight","owner_id":"37914723778808","owner_resource":"product_image","created_at":"2022-08-11T10:55:52+02:00","updated_at":"2022-08-11T10:55:52+02:00","admin_graphql_api_id":"gid://shopify/Metafield/23003659600120"},{"id":"23003659632888","namespace":"global","key":"0015","value":"{\"value\":20.0,\"unit\":\"ml\"}","type":"volume","owner_id":"37914723778808","owner_resource":"product_image","created_at":"2022-08-11T10:55:52+02:00","updated_at":"2022-08-11T10:55:52+02:00","admin_graphql_api_id":"gid://shopify/Metafield/23003659632888"},{"id":"23003659665656","namespace":"global","key":"0016","value":"{\"value\":20.5,\"unit\":\"cm\"}","type":"dimension","owner_id":"37914723778808","owner_resource":"product_image","created_at":"2022-08-11T10:55:52+02:00","updated_at":"2022-08-11T10:55:52+02:00","admin_graphql_api_id":"gid://shopify/Metafield/23003659665656"},{"id":"23003659698424","namespace":"global","key":"0017","value":"{\"scale_min\":\"1.0\",\"scale_max\":\"5.0\",\"value\":\"3.5\"}","type":"rating","owner_id":"37914723778808","owner_resource":"product_image","created_at":"2022-08-11T10:55:52+02:00","updated_at":"2022-08-11T10:55:52+02:00","admin_graphql_api_id":"gid://shopify/Metafield/23003659698424"}],"created_at":"2022-08-11T08:55:52+00:00","updated_at":"2022-08-11T10:55:55+02:00","admin_graphql_api_id":"gid://shopify/ProductImage/37914723778808"},{"id":"37914723811576","product_id":"7776957169912","position":4,"src":"https://cdn.shopify.com/s/files/1/0549/3132/5176/products/reboot_indiana_558edc4a-5d2a-4646-a2f0-8b392ce6280c.jpg?v=1660208155","filename":"reboot_indiana_558edc4a-5d2a-4646-a2f0-8b392ce6280c.jpg","width":"128","height":"128","variant_ids":[],"metafields":[{"id":"23003659731192","namespace":"global","key":"0000","value":"This item contains dairy products.","type":"single_line_text_field","owner_id":"37914723811576","owner_resource":"product_image","created_at":"2022-08-11T10:55:52+02:00","updated_at":"2022-08-11T10:55:52+02:00","admin_graphql_api_id":"gid://shopify/Metafield/23003659731192"},{"id":"23003659763960","namespace":"global","key":"0001","value":"Ingredients: \r\nFlour \r\nWater \r\nMilk \r\nEggs","type":"multi_line_text_field","owner_id":"37914723811576","owner_resource":"product_image","created_at":"2022-08-11T10:55:52+02:00","updated_at":"2022-08-11T10:55:52+02:00","admin_graphql_api_id":"gid://shopify/Metafield/23003659763960"},{"id":"23003659796728","namespace":"global","key":"0002","value":"gid://shopify/OnlineStorePage/1","type":"page_reference","owner_id":"37914723811576","owner_resource":"product_image","created_at":"2022-08-11T10:55:52+02:00","updated_at":"2022-08-11T10:55:52+02:00","admin_graphql_api_id":"gid://shopify/Metafield/23003659796728"},{"id":"23003659829496","namespace":"global","key":"0003","value":"gid://shopify/Product/1","type":"product_reference","owner_id":"37914723811576","owner_resource":"product_image","created_at":"2022-08-11T10:55:52+02:00","updated_at":"2022-08-11T10:55:52+02:00","admin_graphql_api_id":"gid://shopify/Metafield/23003659829496"},{"id":"23003659862264","namespace":"global","key":"0004","value":"gid://shopify/ProductVariant/1","type":"variant_reference","owner_id":"37914723811576","owner_resource":"product_image","created_at":"2022-08-11T10:55:52+02:00","updated_at":"2022-08-11T10:55:52+02:00","admin_graphql_api_id":"gid://shopify/Metafield/23003659862264"},{"id":"23003659895032","namespace":"global","key":"0005","value":"gid://shopify/MediaImage/123","type":"file_reference","owner_id":"37914723811576","owner_resource":"product_image","created_at":"2022-08-11T10:55:52+02:00","updated_at":"2022-08-11T10:55:52+02:00","admin_graphql_api_id":"gid://shopify/Metafield/23003659895032"},{"id":"23003659927800","namespace":"global","key":"0006","value":"10","type":"number_integer","owner_id":"37914723811576","owner_resource":"product_image","created_at":"2022-08-11T10:55:52+02:00","updated_at":"2022-08-11T10:55:52+02:00","admin_graphql_api_id":"gid://shopify/Metafield/23003659927800"},{"id":"23003659960568","namespace":"global","key":"0007","value":"10.4","type":"number_decimal","owner_id":"37914723811576","owner_resource":"product_image","created_at":"2022-08-11T10:55:52+02:00","updated_at":"2022-08-11T10:55:52+02:00","admin_graphql_api_id":"gid://shopify/Metafield/23003659960568"},{"id":"23003659993336","namespace":"global","key":"0008","value":"2021-02-02","type":"date","owner_id":"37914723811576","owner_resource":"product_image","created_at":"2022-08-11T10:55:52+02:00","updated_at":"2022-08-11T10:55:52+02:00","admin_graphql_api_id":"gid://shopify/Metafield/23003659993336"},{"id":"23003660026104","namespace":"global","key":"0009","value":"2021-01-01T12:30:00+00:00","type":"date_time","owner_id":"37914723811576","owner_resource":"product_image","created_at":"2022-08-11T10:55:52+02:00","updated_at":"2022-08-11T10:55:52+02:00","admin_graphql_api_id":"gid://shopify/Metafield/23003660026104"},{"id":"23003660058872","namespace":"global","key":"0010","value":"https://www.shopify.com","type":"url","owner_id":"37914723811576","owner_resource":"product_image","created_at":"2022-08-11T10:55:52+02:00","updated_at":"2022-08-11T10:55:52+02:00","admin_graphql_api_id":"gid://shopify/Metafield/23003660058872"},{"id":"23003660091640","namespace":"global","key":"0011","value":"[{\"k\":\"v1\"},{\"k\":\"v2\"}]","type":"json","owner_id":"37914723811576","owner_resource":"product_image","created_at":"2022-08-11T10:55:52+02:00","updated_at":"2022-08-11T10:55:52+02:00","admin_graphql_api_id":"gid://shopify/Metafield/23003660091640"},{"id":"23003660124408","namespace":"global","key":"0012","value":"true","type":"boolean","owner_id":"37914723811576","owner_resource":"product_image","created_at":"2022-08-11T10:55:52+02:00","updated_at":"2022-08-11T10:55:52+02:00","admin_graphql_api_id":"gid://shopify/Metafield/23003660124408"},{"id":"23003660157176","namespace":"global","key":"0013","value":"#fff123","type":"color","owner_id":"37914723811576","owner_resource":"product_image","created_at":"2022-08-11T10:55:52+02:00","updated_at":"2022-08-11T10:55:52+02:00","admin_graphql_api_id":"gid://shopify/Metafield/23003660157176"},{"id":"23003660189944","namespace":"global","key":"0014","value":"{\"value\":2.5,\"unit\":\"kg\"}","type":"weight","owner_id":"37914723811576","owner_resource":"product_image","created_at":"2022-08-11T10:55:52+02:00","updated_at":"2022-08-11T10:55:52+02:00","admin_graphql_api_id":"gid://shopify/Metafield/23003660189944"},{"id":"23003660222712","namespace":"global","key":"0015","value":"{\"value\":20.0,\"unit\":\"ml\"}","type":"volume","owner_id":"37914723811576","owner_resource":"product_image","created_at":"2022-08-11T10:55:52+02:00","updated_at":"2022-08-11T10:55:52+02:00","admin_graphql_api_id":"gid://shopify/Metafield/23003660222712"},{"id":"23003660255480","namespace":"global","key":"0016","value":"{\"value\":20.5,\"unit\":\"cm\"}","type":"dimension","owner_id":"37914723811576","owner_resource":"product_image","created_at":"2022-08-11T10:55:52+02:00","updated_at":"2022-08-11T10:55:52+02:00","admin_graphql_api_id":"gid://shopify/Metafield/23003660255480"},{"id":"23003660288248","namespace":"global","key":"0017","value":"{\"scale_min\":\"1.0\",\"scale_max\":\"5.0\",\"value\":\"3.5\"}","type":"rating","owner_id":"37914723811576","owner_resource":"product_image","created_at":"2022-08-11T10:55:52+02:00","updated_at":"2022-08-11T10:55:52+02:00","admin_graphql_api_id":"gid://shopify/Metafield/23003660288248"}],"created_at":"2022-08-11T08:55:52+00:00","updated_at":"2022-08-11T10:55:55+02:00","admin_graphql_api_id":"gid://shopify/ProductImage/37914723811576"},{"id":"37914723942648","product_id":"7776957169912","position":5,"src":"https://cdn.shopify.com/s/files/1/0549/3132/5176/products/cambridgeshire_override_copy_f769a47f-739f-4987-bb82-b27a04cddcdf.jpg?v=1660208156","filename":"cambridgeshire_override_copy_f769a47f-739f-4987-bb82-b27a04cddcdf.jpg","width":"128","height":"128","variant_ids":[],"metafields":[{"id":"23003660321016","namespace":"global","key":"0000","value":"This item contains dairy products.","type":"single_line_text_field","owner_id":"37914723942648","owner_resource":"product_image","created_at":"2022-08-11T10:55:53+02:00","updated_at":"2022-08-11T10:55:53+02:00","admin_graphql_api_id":"gid://shopify/Metafield/23003660321016"},{"id":"23003660353784","namespace":"global","key":"0001","value":"Ingredients: \r\nFlour \r\nWater \r\nMilk \r\nEggs","type":"multi_line_text_field","owner_id":"37914723942648","owner_resource":"product_image","created_at":"2022-08-11T10:55:53+02:00","updated_at":"2022-08-11T10:55:53+02:00","admin_graphql_api_id":"gid://shopify/Metafield/23003660353784"},{"id":"23003660386552","namespace":"global","key":"0002","value":"gid://shopify/OnlineStorePage/1","type":"page_reference","owner_id":"37914723942648","owner_resource":"product_image","created_at":"2022-08-11T10:55:53+02:00","updated_at":"2022-08-11T10:55:53+02:00","admin_graphql_api_id":"gid://shopify/Metafield/23003660386552"},{"id":"23003660419320","namespace":"global","key":"0003","value":"gid://shopify/Product/1","type":"product_reference","owner_id":"37914723942648","owner_resource":"product_image","created_at":"2022-08-11T10:55:53+02:00","updated_at":"2022-08-11T10:55:53+02:00","admin_graphql_api_id":"gid://shopify/Metafield/23003660419320"},{"id":"23003660452088","namespace":"global","key":"0004","value":"gid://shopify/ProductVariant/1","type":"variant_reference","owner_id":"37914723942648","owner_resource":"product_image","created_at":"2022-08-11T10:55:53+02:00","updated_at":"2022-08-11T10:55:53+02:00","admin_graphql_api_id":"gid://shopify/Metafield/23003660452088"},{"id":"23003660484856","namespace":"global","key":"0005","value":"gid://shopify/MediaImage/123","type":"file_reference","owner_id":"37914723942648","owner_resource":"product_image","created_at":"2022-08-11T10:55:53+02:00","updated_at":"2022-08-11T10:55:53+02:00","admin_graphql_api_id":"gid://shopify/Metafield/23003660484856"},{"id":"23003660517624","namespace":"global","key":"0006","value":"10","type":"number_integer","owner_id":"37914723942648","owner_resource":"product_image","created_at":"2022-08-11T10:55:53+02:00","updated_at":"2022-08-11T10:55:53+02:00","admin_graphql_api_id":"gid://shopify/Metafield/23003660517624"},{"id":"23003660550392","namespace":"global","key":"0007","value":"10.4","type":"number_decimal","owner_id":"37914723942648","owner_resource":"product_image","created_at":"2022-08-11T10:55:53+02:00","updated_at":"2022-08-11T10:55:53+02:00","admin_graphql_api_id":"gid://shopify/Metafield/23003660550392"},{"id":"23003660583160","namespace":"global","key":"0008","value":"2021-02-02","type":"date","owner_id":"37914723942648","owner_resource":"product_image","created_at":"2022-08-11T10:55:53+02:00","updated_at":"2022-08-11T10:55:53+02:00","admin_graphql_api_id":"gid://shopify/Metafield/23003660583160"},{"id":"23003660615928","namespace":"global","key":"0009","value":"2021-01-01T12:30:00+00:00","type":"date_time","owner_id":"37914723942648","owner_resource":"product_image","created_at":"2022-08-11T10:55:53+02:00","updated_at":"2022-08-11T10:55:53+02:00","admin_graphql_api_id":"gid://shopify/Metafield/23003660615928"},{"id":"23003660648696","namespace":"global","key":"0010","value":"https://www.shopify.com","type":"url","owner_id":"37914723942648","owner_resource":"product_image","created_at":"2022-08-11T10:55:53+02:00","updated_at":"2022-08-11T10:55:53+02:00","admin_graphql_api_id":"gid://shopify/Metafield/23003660648696"},{"id":"23003660681464","namespace":"global","key":"0011","value":"[{\"k\":\"v1\"},{\"k\":\"v2\"}]","type":"json","owner_id":"37914723942648","owner_resource":"product_image","created_at":"2022-08-11T10:55:53+02:00","updated_at":"2022-08-11T10:55:53+02:00","admin_graphql_api_id":"gid://shopify/Metafield/23003660681464"},{"id":"23003660714232","namespace":"global","key":"0012","value":"true","type":"boolean","owner_id":"37914723942648","owner_resource":"product_image","created_at":"2022-08-11T10:55:53+02:00","updated_at":"2022-08-11T10:55:53+02:00","admin_graphql_api_id":"gid://shopify/Metafield/23003660714232"},{"id":"23003660747000","namespace":"global","key":"0013","value":"#fff123","type":"color","owner_id":"37914723942648","owner_resource":"product_image","created_at":"2022-08-11T10:55:53+02:00","updated_at":"2022-08-11T10:55:53+02:00","admin_graphql_api_id":"gid://shopify/Metafield/23003660747000"},{"id":"23003660779768","namespace":"global","key":"0014","value":"{\"value\":2.5,\"unit\":\"kg\"}","type":"weight","owner_id":"37914723942648","owner_resource":"product_image","created_at":"2022-08-11T10:55:53+02:00","updated_at":"2022-08-11T10:55:53+02:00","admin_graphql_api_id":"gid://shopify/Metafield/23003660779768"},{"id":"23003660812536","namespace":"global","key":"0015","value":"{\"value\":20.0,\"unit\":\"ml\"}","type":"volume","owner_id":"37914723942648","owner_resource":"product_image","created_at":"2022-08-11T10:55:53+02:00","updated_at":"2022-08-11T10:55:53+02:00","admin_graphql_api_id":"gid://shopify/Metafield/23003660812536"},{"id":"23003660845304","namespace":"global","key":"0016","value":"{\"value\":20.5,\"unit\":\"cm\"}","type":"dimension","owner_id":"37914723942648","owner_resource":"product_image","created_at":"2022-08-11T10:55:53+02:00","updated_at":"2022-08-11T10:55:53+02:00","admin_graphql_api_id":"gid://shopify/Metafield/23003660845304"},{"id":"23003660878072","namespace":"global","key":"0017","value":"{\"scale_min\":\"1.0\",\"scale_max\":\"5.0\",\"value\":\"3.5\"}","type":"rating","owner_id":"37914723942648","owner_resource":"product_image","created_at":"2022-08-11T10:55:53+02:00","updated_at":"2022-08-11T10:55:53+02:00","admin_graphql_api_id":"gid://shopify/Metafield/23003660878072"}],"created_at":"2022-08-11T08:55:53+00:00","updated_at":"2022-08-11T10:55:56+02:00","admin_graphql_api_id":"gid://shopify/ProductImage/37914723942648"}],"variants":[{"id":"43140209541368","barcode":"65799260","compare_at_price":"879.82","title":"Frozen / fuchsia / magni","fulfillment_service":"manual","grams":"18002","inventory_management":"shopify","inventory_policy":"deny","inventory_quantity":"0","metafields":[{"id":"23003660910840","namespace":"global","key":"0000","value":"This item contains dairy products.","type":"single_line_text_field","owner_id":"43140209541368","owner_resource":"variant","created_at":"2022-08-11T10:55:53+02:00","updated_at":"2022-08-11T10:55:53+02:00","admin_graphql_api_id":"gid://shopify/Metafield/23003660910840"},{"id":"23003660943608","namespace":"global","key":"0001","value":"Ingredients: \r\nFlour \r\nWater \r\nMilk \r\nEggs","type":"multi_line_text_field","owner_id":"43140209541368","owner_resource":"variant","created_at":"2022-08-11T10:55:53+02:00","updated_at":"2022-08-11T10:55:53+02:00","admin_graphql_api_id":"gid://shopify/Metafield/23003660943608"},{"id":"23003660976376","namespace":"global","key":"0002","value":"gid://shopify/OnlineStorePage/1","type":"page_reference","owner_id":"43140209541368","owner_resource":"variant","created_at":"2022-08-11T10:55:53+02:00","updated_at":"2022-08-11T10:55:53+02:00","admin_graphql_api_id":"gid://shopify/Metafield/23003660976376"},{"id":"23003661009144","namespace":"global","key":"0003","value":"gid://shopify/Product/1","type":"product_reference","owner_id":"43140209541368","owner_resource":"variant","created_at":"2022-08-11T10:55:53+02:00","updated_at":"2022-08-11T10:55:53+02:00","admin_graphql_api_id":"gid://shopify/Metafield/23003661009144"},{"id":"23003661041912","namespace":"global","key":"0004","value":"gid://shopify/ProductVariant/1","type":"variant_reference","owner_id":"43140209541368","owner_resource":"variant","created_at":"2022-08-11T10:55:53+02:00","updated_at":"2022-08-11T10:55:53+02:00","admin_graphql_api_id":"gid://shopify/Metafield/23003661041912"},{"id":"23003661074680","namespace":"global","key":"0005","value":"gid://shopify/MediaImage/123","type":"file_reference","owner_id":"43140209541368","owner_resource":"variant","created_at":"2022-08-11T10:55:53+02:00","updated_at":"2022-08-11T10:55:53+02:00","admin_graphql_api_id":"gid://shopify/Metafield/23003661074680"},{"id":"23003661107448","namespace":"global","key":"0006","value":"10","type":"number_integer","owner_id":"43140209541368","owner_resource":"variant","created_at":"2022-08-11T10:55:53+02:00","updated_at":"2022-08-11T10:55:53+02:00","admin_graphql_api_id":"gid://shopify/Metafield/23003661107448"},{"id":"23003661140216","namespace":"global","key":"0007","value":"10.4","type":"number_decimal","owner_id":"43140209541368","owner_resource":"variant","created_at":"2022-08-11T10:55:53+02:00","updated_at":"2022-08-11T10:55:53+02:00","admin_graphql_api_id":"gid://shopify/Metafield/23003661140216"},{"id":"23003661172984","namespace":"global","key":"0008","value":"2021-02-02","type":"date","owner_id":"43140209541368","owner_resource":"variant","created_at":"2022-08-11T10:55:53+02:00","updated_at":"2022-08-11T10:55:53+02:00","admin_graphql_api_id":"gid://shopify/Metafield/23003661172984"},{"id":"23003661205752","namespace":"global","key":"0009","value":"2021-01-01T12:30:00+00:00","type":"date_time","owner_id":"43140209541368","owner_resource":"variant","created_at":"2022-08-11T10:55:53+02:00","updated_at":"2022-08-11T10:55:53+02:00","admin_graphql_api_id":"gid://shopify/Metafield/23003661205752"},{"id":"23003661238520","namespace":"global","key":"0010","value":"https://www.shopify.com","type":"url","owner_id":"43140209541368","owner_resource":"variant","created_at":"2022-08-11T10:55:53+02:00","updated_at":"2022-08-11T10:55:53+02:00","admin_graphql_api_id":"gid://shopify/Metafield/23003661238520"},{"id":"23003661271288","namespace":"global","key":"0011","value":"[{\"k\":\"v1\"},{\"k\":\"v2\"}]","type":"json","owner_id":"43140209541368","owner_resource":"variant","created_at":"2022-08-11T10:55:53+02:00","updated_at":"2022-08-11T10:55:53+02:00","admin_graphql_api_id":"gid://shopify/Metafield/23003661271288"},{"id":"23003661304056","namespace":"global","key":"0012","value":"true","type":"boolean","owner_id":"43140209541368","owner_resource":"variant","created_at":"2022-08-11T10:55:53+02:00","updated_at":"2022-08-11T10:55:53+02:00","admin_graphql_api_id":"gid://shopify/Metafield/23003661304056"},{"id":"23003661336824","namespace":"global","key":"0013","value":"#fff123","type":"color","owner_id":"43140209541368","owner_resource":"variant","created_at":"2022-08-11T10:55:53+02:00","updated_at":"2022-08-11T10:55:53+02:00","admin_graphql_api_id":"gid://shopify/Metafield/23003661336824"},{"id":"23003661369592","namespace":"global","key":"0014","value":"{\"value\":2.5,\"unit\":\"kg\"}","type":"weight","owner_id":"43140209541368","owner_resource":"variant","created_at":"2022-08-11T10:55:53+02:00","updated_at":"2022-08-11T10:55:53+02:00","admin_graphql_api_id":"gid://shopify/Metafield/23003661369592"},{"id":"23003661402360","namespace":"global","key":"0015","value":"{\"value\":20.0,\"unit\":\"ml\"}","type":"volume","owner_id":"43140209541368","owner_resource":"variant","created_at":"2022-08-11T10:55:53+02:00","updated_at":"2022-08-11T10:55:53+02:00","admin_graphql_api_id":"gid://shopify/Metafield/23003661402360"},{"id":"23003661435128","namespace":"global","key":"0016","value":"{\"value\":20.5,\"unit\":\"cm\"}","type":"dimension","owner_id":"43140209541368","owner_resource":"variant","created_at":"2022-08-11T10:55:53+02:00","updated_at":"2022-08-11T10:55:53+02:00","admin_graphql_api_id":"gid://shopify/Metafield/23003661435128"},{"id":"23003661467896","namespace":"global","key":"0017","value":"{\"scale_min\":\"1.0\",\"scale_max\":\"5.0\",\"value\":\"3.5\"}","type":"rating","owner_id":"43140209541368","owner_resource":"variant","created_at":"2022-08-11T10:55:53+02:00","updated_at":"2022-08-11T10:55:53+02:00","admin_graphql_api_id":"gid://shopify/Metafield/23003661467896"}],"option1":"Frozen","option2":"fuchsia","option3":"magni","position":"1","product_id":"7776957169912","sku":"9992562370404","taxable":"false","weight":"635.0","weight_unit":"oz","price":"640.50","updated_at":"2022-08-11T10:55:56+02:00","created_at":"2022-08-11T10:55:53+02:00","inventory_item_id":"45234781716728","admin_graphql_api_id":"gid://shopify/ProductVariant/43140209541368"},{"id":"43140209574136","barcode":"44475895","compare_at_price":"323.01","title":"Concrete / orchid / voluptatem","fulfillment_service":"manual","grams":"24721","inventory_management":"shopify","inventory_policy":"deny","inventory_quantity":"0","metafields":[{"id":"23003661500664","namespace":"global","key":"0000","value":"This item contains dairy products.","type":"single_line_text_field","owner_id":"43140209574136","owner_resource":"variant","created_at":"2022-08-11T10:55:53+02:00","updated_at":"2022-08-11T10:55:53+02:00","admin_graphql_api_id":"gid://shopify/Metafield/23003661500664"},{"id":"23003661533432","namespace":"global","key":"0001","value":"Ingredients: \r\nFlour \r\nWater \r\nMilk \r\nEggs","type":"multi_line_text_field","owner_id":"43140209574136","owner_resource":"variant","created_at":"2022-08-11T10:55:53+02:00","updated_at":"2022-08-11T10:55:53+02:00","admin_graphql_api_id":"gid://shopify/Metafield/23003661533432"},{"id":"23003661566200","namespace":"global","key":"0002","value":"gid://shopify/OnlineStorePage/1","type":"page_reference","owner_id":"43140209574136","owner_resource":"variant","created_at":"2022-08-11T10:55:53+02:00","updated_at":"2022-08-11T10:55:53+02:00","admin_graphql_api_id":"gid://shopify/Metafield/23003661566200"},{"id":"23003661598968","namespace":"global","key":"0003","value":"gid://shopify/Product/1","type":"product_reference","owner_id":"43140209574136","owner_resource":"variant","created_at":"2022-08-11T10:55:53+02:00","updated_at":"2022-08-11T10:55:53+02:00","admin_graphql_api_id":"gid://shopify/Metafield/23003661598968"},{"id":"23003661631736","namespace":"global","key":"0004","value":"gid://shopify/ProductVariant/1","type":"variant_reference","owner_id":"43140209574136","owner_resource":"variant","created_at":"2022-08-11T10:55:53+02:00","updated_at":"2022-08-11T10:55:53+02:00","admin_graphql_api_id":"gid://shopify/Metafield/23003661631736"},{"id":"23003661664504","namespace":"global","key":"0005","value":"gid://shopify/MediaImage/123","type":"file_reference","owner_id":"43140209574136","owner_resource":"variant","created_at":"2022-08-11T10:55:53+02:00","updated_at":"2022-08-11T10:55:53+02:00","admin_graphql_api_id":"gid://shopify/Metafield/23003661664504"},{"id":"23003661697272","namespace":"global","key":"0006","value":"10","type":"number_integer","owner_id":"43140209574136","owner_resource":"variant","created_at":"2022-08-11T10:55:53+02:00","updated_at":"2022-08-11T10:55:53+02:00","admin_graphql_api_id":"gid://shopify/Metafield/23003661697272"},{"id":"23003661730040","namespace":"global","key":"0007","value":"10.4","type":"number_decimal","owner_id":"43140209574136","owner_resource":"variant","created_at":"2022-08-11T10:55:53+02:00","updated_at":"2022-08-11T10:55:53+02:00","admin_graphql_api_id":"gid://shopify/Metafield/23003661730040"},{"id":"23003661762808","namespace":"global","key":"0008","value":"2021-02-02","type":"date","owner_id":"43140209574136","owner_resource":"variant","created_at":"2022-08-11T10:55:53+02:00","updated_at":"2022-08-11T10:55:53+02:00","admin_graphql_api_id":"gid://shopify/Metafield/23003661762808"},{"id":"23003661795576","namespace":"global","key":"0009","value":"2021-01-01T12:30:00+00:00","type":"date_time","owner_id":"43140209574136","owner_resource":"variant","created_at":"2022-08-11T10:55:53+02:00","updated_at":"2022-08-11T10:55:53+02:00","admin_graphql_api_id":"gid://shopify/Metafield/23003661795576"},{"id":"23003661828344","namespace":"global","key":"0010","value":"https://www.shopify.com","type":"url","owner_id":"43140209574136","owner_resource":"variant","created_at":"2022-08-11T10:55:53+02:00","updated_at":"2022-08-11T10:55:53+02:00","admin_graphql_api_id":"gid://shopify/Metafield/23003661828344"},{"id":"23003661861112","namespace":"global","key":"0011","value":"[{\"k\":\"v1\"},{\"k\":\"v2\"}]","type":"json","owner_id":"43140209574136","owner_resource":"variant","created_at":"2022-08-11T10:55:53+02:00","updated_at":"2022-08-11T10:55:53+02:00","admin_graphql_api_id":"gid://shopify/Metafield/23003661861112"},{"id":"23003661893880","namespace":"global","key":"0012","value":"true","type":"boolean","owner_id":"43140209574136","owner_resource":"variant","created_at":"2022-08-11T10:55:53+02:00","updated_at":"2022-08-11T10:55:53+02:00","admin_graphql_api_id":"gid://shopify/Metafield/23003661893880"},{"id":"23003661926648","namespace":"global","key":"0013","value":"#fff123","type":"color","owner_id":"43140209574136","owner_resource":"variant","created_at":"2022-08-11T10:55:53+02:00","updated_at":"2022-08-11T10:55:53+02:00","admin_graphql_api_id":"gid://shopify/Metafield/23003661926648"},{"id":"23003661959416","namespace":"global","key":"0014","value":"{\"value\":2.5,\"unit\":\"kg\"}","type":"weight","owner_id":"43140209574136","owner_resource":"variant","created_at":"2022-08-11T10:55:53+02:00","updated_at":"2022-08-11T10:55:53+02:00","admin_graphql_api_id":"gid://shopify/Metafield/23003661959416"},{"id":"23003661992184","namespace":"global","key":"0015","value":"{\"value\":20.0,\"unit\":\"ml\"}","type":"volume","owner_id":"43140209574136","owner_resource":"variant","created_at":"2022-08-11T10:55:53+02:00","updated_at":"2022-08-11T10:55:53+02:00","admin_graphql_api_id":"gid://shopify/Metafield/23003661992184"},{"id":"23003662024952","namespace":"global","key":"0016","value":"{\"value\":20.5,\"unit\":\"cm\"}","type":"dimension","owner_id":"43140209574136","owner_resource":"variant","created_at":"2022-08-11T10:55:53+02:00","updated_at":"2022-08-11T10:55:53+02:00","admin_graphql_api_id":"gid://shopify/Metafield/23003662024952"},{"id":"23003662057720","namespace":"global","key":"0017","value":"{\"scale_min\":\"1.0\",\"scale_max\":\"5.0\",\"value\":\"3.5\"}","type":"rating","owner_id":"43140209574136","owner_resource":"variant","created_at":"2022-08-11T10:55:53+02:00","updated_at":"2022-08-11T10:55:53+02:00","admin_graphql_api_id":"gid://shopify/Metafield/23003662057720"}],"option1":"Concrete","option2":"orchid","option3":"voluptatem","position":"2","product_id":"7776957169912","sku":"1770321893566","taxable":"false","weight":"872.0","weight_unit":"oz","price":"821.60","updated_at":"2022-08-11T10:55:57+02:00","created_at":"2022-08-11T10:55:53+02:00","inventory_item_id":"45234781749496","admin_graphql_api_id":"gid://shopify/ProductVariant/43140209574136"},{"id":"43140209639672","barcode":"90452253","compare_at_price":"507.53","title":"Frozen / orange / voluptate","fulfillment_service":"manual","grams":"17690","inventory_management":"shopify","inventory_policy":"deny","inventory_quantity":"0","metafields":[{"id":"23003662123256","namespace":"global","key":"0000","value":"This item contains dairy products.","type":"single_line_text_field","owner_id":"43140209639672","owner_resource":"variant","created_at":"2022-08-11T10:55:53+02:00","updated_at":"2022-08-11T10:55:53+02:00","admin_graphql_api_id":"gid://shopify/Metafield/23003662123256"},{"id":"23003662156024","namespace":"global","key":"0001","value":"Ingredients: \r\nFlour \r\nWater \r\nMilk \r\nEggs","type":"multi_line_text_field","owner_id":"43140209639672","owner_resource":"variant","created_at":"2022-08-11T10:55:53+02:00","updated_at":"2022-08-11T10:55:53+02:00","admin_graphql_api_id":"gid://shopify/Metafield/23003662156024"},{"id":"23003662188792","namespace":"global","key":"0002","value":"gid://shopify/OnlineStorePage/1","type":"page_reference","owner_id":"43140209639672","owner_resource":"variant","created_at":"2022-08-11T10:55:53+02:00","updated_at":"2022-08-11T10:55:53+02:00","admin_graphql_api_id":"gid://shopify/Metafield/23003662188792"},{"id":"23003662221560","namespace":"global","key":"0003","value":"gid://shopify/Product/1","type":"product_reference","owner_id":"43140209639672","owner_resource":"variant","created_at":"2022-08-11T10:55:53+02:00","updated_at":"2022-08-11T10:55:53+02:00","admin_graphql_api_id":"gid://shopify/Metafield/23003662221560"},{"id":"23003662254328","namespace":"global","key":"0004","value":"gid://shopify/ProductVariant/1","type":"variant_reference","owner_id":"43140209639672","owner_resource":"variant","created_at":"2022-08-11T10:55:53+02:00","updated_at":"2022-08-11T10:55:53+02:00","admin_graphql_api_id":"gid://shopify/Metafield/23003662254328"},{"id":"23003662287096","namespace":"global","key":"0005","value":"gid://shopify/MediaImage/123","type":"file_reference","owner_id":"43140209639672","owner_resource":"variant","created_at":"2022-08-11T10:55:53+02:00","updated_at":"2022-08-11T10:55:53+02:00","admin_graphql_api_id":"gid://shopify/Metafield/23003662287096"},{"id":"23003662319864","namespace":"global","key":"0006","value":"10","type":"number_integer","owner_id":"43140209639672","owner_resource":"variant","created_at":"2022-08-11T10:55:53+02:00","updated_at":"2022-08-11T10:55:53+02:00","admin_graphql_api_id":"gid://shopify/Metafield/23003662319864"},{"id":"23003662352632","namespace":"global","key":"0007","value":"10.4","type":"number_decimal","owner_id":"43140209639672","owner_resource":"variant","created_at":"2022-08-11T10:55:53+02:00","updated_at":"2022-08-11T10:55:53+02:00","admin_graphql_api_id":"gid://shopify/Metafield/23003662352632"},{"id":"23003662385400","namespace":"global","key":"0008","value":"2021-02-02","type":"date","owner_id":"43140209639672","owner_resource":"variant","created_at":"2022-08-11T10:55:53+02:00","updated_at":"2022-08-11T10:55:53+02:00","admin_graphql_api_id":"gid://shopify/Metafield/23003662385400"},{"id":"23003662418168","namespace":"global","key":"0009","value":"2021-01-01T12:30:00+00:00","type":"date_time","owner_id":"43140209639672","owner_resource":"variant","created_at":"2022-08-11T10:55:53+02:00","updated_at":"2022-08-11T10:55:53+02:00","admin_graphql_api_id":"gid://shopify/Metafield/23003662418168"},{"id":"23003662450936","namespace":"global","key":"0010","value":"https://www.shopify.com","type":"url","owner_id":"43140209639672","owner_resource":"variant","created_at":"2022-08-11T10:55:53+02:00","updated_at":"2022-08-11T10:55:53+02:00","admin_graphql_api_id":"gid://shopify/Metafield/23003662450936"},{"id":"23003662483704","namespace":"global","key":"0011","value":"[{\"k\":\"v1\"},{\"k\":\"v2\"}]","type":"json","owner_id":"43140209639672","owner_resource":"variant","created_at":"2022-08-11T10:55:53+02:00","updated_at":"2022-08-11T10:55:53+02:00","admin_graphql_api_id":"gid://shopify/Metafield/23003662483704"},{"id":"23003662516472","namespace":"global","key":"0012","value":"true","type":"boolean","owner_id":"43140209639672","owner_resource":"variant","created_at":"2022-08-11T10:55:53+02:00","updated_at":"2022-08-11T10:55:53+02:00","admin_graphql_api_id":"gid://shopify/Metafield/23003662516472"},{"id":"23003662549240","namespace":"global","key":"0013","value":"#fff123","type":"color","owner_id":"43140209639672","owner_resource":"variant","created_at":"2022-08-11T10:55:53+02:00","updated_at":"2022-08-11T10:55:53+02:00","admin_graphql_api_id":"gid://shopify/Metafield/23003662549240"},{"id":"23003662582008","namespace":"global","key":"0014","value":"{\"value\":2.5,\"unit\":\"kg\"}","type":"weight","owner_id":"43140209639672","owner_resource":"variant","created_at":"2022-08-11T10:55:53+02:00","updated_at":"2022-08-11T10:55:53+02:00","admin_graphql_api_id":"gid://shopify/Metafield/23003662582008"},{"id":"23003662614776","namespace":"global","key":"0015","value":"{\"value\":20.0,\"unit\":\"ml\"}","type":"volume","owner_id":"43140209639672","owner_resource":"variant","created_at":"2022-08-11T10:55:53+02:00","updated_at":"2022-08-11T10:55:53+02:00","admin_graphql_api_id":"gid://shopify/Metafield/23003662614776"},{"id":"23003662647544","namespace":"global","key":"0016","value":"{\"value\":20.5,\"unit\":\"cm\"}","type":"dimension","owner_id":"43140209639672","owner_resource":"variant","created_at":"2022-08-11T10:55:53+02:00","updated_at":"2022-08-11T10:55:53+02:00","admin_graphql_api_id":"gid://shopify/Metafield/23003662647544"},{"id":"23003662680312","namespace":"global","key":"0017","value":"{\"scale_min\":\"1.0\",\"scale_max\":\"5.0\",\"value\":\"3.5\"}","type":"rating","owner_id":"43140209639672","owner_resource":"variant","created_at":"2022-08-11T10:55:53+02:00","updated_at":"2022-08-11T10:55:53+02:00","admin_graphql_api_id":"gid://shopify/Metafield/23003662680312"}],"option1":"Frozen","option2":"orange","option3":"voluptate","position":"3","product_id":"7776957169912","sku":"7669452796973","taxable":"false","weight":"624.0","weight_unit":"oz","price":"177.74","updated_at":"2022-08-11T10:55:58+02:00","created_at":"2022-08-11T10:55:53+02:00","inventory_item_id":"45234781782264","admin_graphql_api_id":"gid://shopify/ProductVariant/43140209639672"}],"metafields":[{"id":"23003662713080","namespace":"global","key":"description_tag","value":"ratione","type":"string","owner_id":"7776957169912","owner_resource":"product","created_at":"2022-08-11T10:55:53+02:00","updated_at":"2022-08-11T10:55:53+02:00","admin_graphql_api_id":"gid://shopify/Metafield/23003662713080"},{"id":"23003662745848","namespace":"global","key":"title_tag","value":"voluptatem","type":"string","owner_id":"7776957169912","owner_resource":"product","created_at":"2022-08-11T10:55:53+02:00","updated_at":"2022-08-11T10:55:53+02:00","admin_graphql_api_id":"gid://shopify/Metafield/23003662745848"},{"id":"23003662778616","namespace":"global","key":"0000","value":"This item contains dairy products.","type":"single_line_text_field","owner_id":"7776957169912","owner_resource":"product","created_at":"2022-08-11T10:55:53+02:00","updated_at":"2022-08-11T10:55:53+02:00","admin_graphql_api_id":"gid://shopify/Metafield/23003662778616"},{"id":"23003662811384","namespace":"global","key":"0001","value":"Ingredients: \r\nFlour \r\nWater \r\nMilk \r\nEggs","type":"multi_line_text_field","owner_id":"7776957169912","owner_resource":"product","created_at":"2022-08-11T10:55:53+02:00","updated_at":"2022-08-11T10:55:53+02:00","admin_graphql_api_id":"gid://shopify/Metafield/23003662811384"},{"id":"23003662844152","namespace":"global","key":"0002","value":"gid://shopify/OnlineStorePage/1","type":"page_reference","owner_id":"7776957169912","owner_resource":"product","created_at":"2022-08-11T10:55:53+02:00","updated_at":"2022-08-11T10:55:53+02:00","admin_graphql_api_id":"gid://shopify/Metafield/23003662844152"},{"id":"23003662876920","namespace":"global","key":"0003","value":"gid://shopify/Product/1","type":"product_reference","owner_id":"7776957169912","owner_resource":"product","created_at":"2022-08-11T10:55:54+02:00","updated_at":"2022-08-11T10:55:54+02:00","admin_graphql_api_id":"gid://shopify/Metafield/23003662876920"},{"id":"23003662909688","namespace":"global","key":"0004","value":"gid://shopify/ProductVariant/1","type":"variant_reference","owner_id":"7776957169912","owner_resource":"product","created_at":"2022-08-11T10:55:54+02:00","updated_at":"2022-08-11T10:55:54+02:00","admin_graphql_api_id":"gid://shopify/Metafield/23003662909688"},{"id":"23003662942456","namespace":"global","key":"0005","value":"gid://shopify/MediaImage/123","type":"file_reference","owner_id":"7776957169912","owner_resource":"product","created_at":"2022-08-11T10:55:54+02:00","updated_at":"2022-08-11T10:55:54+02:00","admin_graphql_api_id":"gid://shopify/Metafield/23003662942456"},{"id":"23003662975224","namespace":"global","key":"0006","value":"10","type":"number_integer","owner_id":"7776957169912","owner_resource":"product","created_at":"2022-08-11T10:55:54+02:00","updated_at":"2022-08-11T10:55:54+02:00","admin_graphql_api_id":"gid://shopify/Metafield/23003662975224"},{"id":"23003663007992","namespace":"global","key":"0007","value":"10.4","type":"number_decimal","owner_id":"7776957169912","owner_resource":"product","created_at":"2022-08-11T10:55:54+02:00","updated_at":"2022-08-11T10:55:54+02:00","admin_graphql_api_id":"gid://shopify/Metafield/23003663007992"},{"id":"23003663040760","namespace":"global","key":"0008","value":"2021-02-02","type":"date","owner_id":"7776957169912","owner_resource":"product","created_at":"2022-08-11T10:55:54+02:00","updated_at":"2022-08-11T10:55:54+02:00","admin_graphql_api_id":"gid://shopify/Metafield/23003663040760"},{"id":"23003663073528","namespace":"global","key":"0009","value":"2021-01-01T12:30:00+00:00","type":"date_time","owner_id":"7776957169912","owner_resource":"product","created_at":"2022-08-11T10:55:54+02:00","updated_at":"2022-08-11T10:55:54+02:00","admin_graphql_api_id":"gid://shopify/Metafield/23003663073528"},{"id":"23003663106296","namespace":"global","key":"0010","value":"https://www.shopify.com","type":"url","owner_id":"7776957169912","owner_resource":"product","created_at":"2022-08-11T10:55:54+02:00","updated_at":"2022-08-11T10:55:54+02:00","admin_graphql_api_id":"gid://shopify/Metafield/23003663106296"},{"id":"23003663139064","namespace":"global","key":"0011","value":"[{\"k\":\"v1\"},{\"k\":\"v2\"}]","type":"json","owner_id":"7776957169912","owner_resource":"product","created_at":"2022-08-11T10:55:54+02:00","updated_at":"2022-08-11T10:55:54+02:00","admin_graphql_api_id":"gid://shopify/Metafield/23003663139064"},{"id":"23003663171832","namespace":"global","key":"0012","value":"true","type":"boolean","owner_id":"7776957169912","owner_resource":"product","created_at":"2022-08-11T10:55:54+02:00","updated_at":"2022-08-11T10:55:54+02:00","admin_graphql_api_id":"gid://shopify/Metafield/23003663171832"},{"id":"23003663204600","namespace":"global","key":"0013","value":"#fff123","type":"color","owner_id":"7776957169912","owner_resource":"product","created_at":"2022-08-11T10:55:54+02:00","updated_at":"2022-08-11T10:55:54+02:00","admin_graphql_api_id":"gid://shopify/Metafield/23003663204600"},{"id":"23003663237368","namespace":"global","key":"0014","value":"{\"value\":2.5,\"unit\":\"kg\"}","type":"weight","owner_id":"7776957169912","owner_resource":"product","created_at":"2022-08-11T10:55:54+02:00","updated_at":"2022-08-11T10:55:54+02:00","admin_graphql_api_id":"gid://shopify/Metafield/23003663237368"},{"id":"23003663270136","namespace":"global","key":"0015","value":"{\"value\":20.0,\"unit\":\"ml\"}","type":"volume","owner_id":"7776957169912","owner_resource":"product","created_at":"2022-08-11T10:55:54+02:00","updated_at":"2022-08-11T10:55:54+02:00","admin_graphql_api_id":"gid://shopify/Metafield/23003663270136"},{"id":"23003663302904","namespace":"global","key":"0016","value":"{\"value\":20.5,\"unit\":\"cm\"}","type":"dimension","owner_id":"7776957169912","owner_resource":"product","created_at":"2022-08-11T10:55:54+02:00","updated_at":"2022-08-11T10:55:54+02:00","admin_graphql_api_id":"gid://shopify/Metafield/23003663302904"},{"id":"23003663335672","namespace":"global","key":"0017","value":"{\"scale_min\":\"1.0\",\"scale_max\":\"5.0\",\"value\":\"3.5\"}","type":"rating","owner_id":"7776957169912","owner_resource":"product","created_at":"2022-08-11T10:55:54+02:00","updated_at":"2022-08-11T10:55:54+02:00","admin_graphql_api_id":"gid://shopify/Metafield/23003663335672"}],"admin_graphql_api_id":"gid://shopify/Product/7776957169912"}